Workbook
Name BAIRROS_SAO_SEBASTIAO: Bairros!$A$6:$A$41
Name BAIRROS_BERTIOGA: Bairros!$E$6:$E$24
Name LISTA_CIDADES: Listas!$A$2:$A$3
Name LISTA_TIPOS: Listas!$B$2:$B$8
Name LISTA_PADROES: Listas!$C$2:$C$5
Name LISTA_ORIGEM_PADRAO: Listas!$D$2:$D$5
Name LISTA_NATUREZAS: Listas!$E$2:$E$2
Name LISTA_FONTES: Listas!$F$2:$F$3
Name LISTA_ORIGEM_FOTO: Listas!$G$2:$G$5
Name LISTA_FORMA_PAGAMENTO: Listas!$H$2:$H$4
Name LISTA_STATUS: Listas!$I$2:$I$4
Name AMOSTRA_MIN: 'Análise ITBI'!$B$4

Sheet Instruções
A1: Base de imóveis vendidos — São Sebastião e Bertioga
A3: Tópico | B3: Descrição
A4: O que é | B4: Base de vendas efetivas de imóveis com o valor REAL de venda (escritura/registro ou ITBI), nunca o valor anunciado. Cada linha precisa de um documento comprobatório.
A5: Por que começa vazia | B5: Não existem dados públicos de vendas para estas cidades. Os dados entram à medida que chegam as respostas dos pedidos LAI e as certidões de matrícula.
A6: Onde digitar | B6: Aba Vendas. Células comuns = entrada. Células cinza = fórmulas (não editar): R$/m², Alerta e Street View. Passe o mouse no cabeçalho para ver a explicação de cada coluna.
A7: Importar LAI | B7: python scripts/importar_lai.py <arquivo_da_prefeitura> <mapa_colunas.json>
A8: Fotos | B8: Salve as fotos em fotos/ com o nome do ID (ex.: fotos/CRI-SS-12345-R7.jpg; várias: ..._2.jpg) e rode python scripts/vincular_fotos.py. A coluna 'Foto da fachada' recebe o link e a aba Galeria mostra as miniaturas.
A9: Resumo | B9: Aba Resumo: por cidade/bairro e por padrão, só com linhas Validado.
A10: Regras | B10: Aba Regras. Critério de padrão na aba Padrão. Documentos recebidos na aba Fontes.
A12: Exemplo de preenchimento (FICTÍCIO — só mostra o formato; não é dado real e não está na aba Vendas)
A13: ID | B13: CRI-SS-00000-R0
A14: Cidade | B14: São Sebastião
A15: Bairro | B15: Maresias
A16: Logradouro e nº | B16: Rua Exemplo, 000
A17: Condomínio / Complemento | B17: Cond. Exemplo, casa 0
A18: Inscrição imobiliária | B18: 0000.000.000
A19: Tipo | B19: Casa em condomínio
A20: Área construída/privativa (m²) | B20: 000,00
A21: Área do terreno (m²) | B21: 000,00
A22: Padrão | B22: Alto
A23: Origem do padrão | B23: Certidão/memorial/habite-se
A24: Padrão (texto do documento) | B24: texto literal
... A49: Status | B49: Validado
A50: Observações

Sheet Vendas
A1: ID | B1: Cidade | C1: Bairro | D1: Logradouro e nº | E1: Condomínio / Complemento | F1: Inscrição imobiliária | G1: Tipo | H1: Área construída/privativa (m²) | I1: Área do terreno (m²) | J1: Padrão | K1: Origem do padrão | L1: Padrão (texto do documento) | M1: Valor de venda (R$) | N1: Base de cálculo ITBI (R$) | O1: Valor venal IPTU (R$) | P1: Forma de pagamento | Q1: Valor financiado (R$) | R1: Valor p/ leilão – alienação fiduciária (R$) | S1: R$/m² (calculado) | T1: Alerta | U1: Declarado ÷ Base ITBI | V1: Declarado ÷ Venal IPTU | W1: Declarado ÷ Valor leilão | X1: Financiado ÷ Declarado | Y1: Ano | Z1: Data da escritura / transação | AA1: Data do registro | AB1: Natureza | AC1: Fonte | AD1: Documento comprobatório | AE1: CRI / Órgão | AF1: Coordenadas (lat,long) | AG1: Foto da fachada | AH1: Origem da foto | AI1: Data da foto | AJ1: Street View | AK1: Status | AL1: Observações
S2: =IF(NOT(ISNUMBER(M2)),"",IF(G2="Terreno",IF(AND(ISNUMBER(I2),I2>0),M2/I2,""),IF(AND(ISNUMBER(H2),H2>0),M2/H2,""))) | T2: =IF(AND(ISNUMBER(M2),ISNUMBER(O2)),IF(M2<=O2,"Valor ≤ venal IPTU",""),"") | U2: =IF(AND(ISNUMBER(M2),ISNUMBER(N2)),IF(N2>0,M2/N2,""),"") | V2: =IF(AND(ISNUMBER(M2),ISNUMBER(O2)),IF(O2>0,M2/O2,""),"") | W2: =IF(AND(ISNUMBER(M2),ISNUMBER(R2)),IF(R2>0,M2/R2,""),"") | X2: =IF(AND(ISNUMBER(Q2),ISNUMBER(M2)),IF(M2>0,Q2/M2,""),"") | Y2: =IF(ISNUMBER(Z2),YEAR(Z2),"") | AJ2: =IF(LEN(TRIM(AF2))=0,"",HYPERLINK("https://www.google.com/maps/@?api=1&map_action=pano&viewpoint="&SUBSTITUTE(AF2," ",""),"Abrir Street View"))
S3: =IF(NOT(ISNUMBER(M3)),"",IF(G3="Terreno",IF(AND(ISNUMBER(I3),I3>0),M3/I3,""),IF(AND(ISNUMBER(H3),H3>0),M3/H3,""))) | T3: =IF(AND(ISNUMBER(M3),ISNUMBER(O3)),IF(M3<=O3,"Valor ≤ venal IPTU",""),"") | U3: =IF(AND(ISNUMBER(M3),ISNUMBER(N3)),IF(N3>0,M3/N3,""),"") | V3: =IF(AND(ISNUMBER(M3),ISNUMBER(O3)),IF(O3>0,M3/O3,""),"") | W3: =IF(AND(ISNUMBER(M3),ISNUMBER(R3)),IF(R3>0,M3/R3,""),"") | X3: =IF(AND(ISNUMBER(Q3),ISNUMBER(M3)),IF(M3>0,Q3/M3,""),"") | Y3: =IF(ISNUMBER(Z3),YEAR(Z3),"") | AJ3: =IF(LEN(TRIM(AF3))=0,"",HYPERLINK("https://www.google.com/maps/@?api=1&map_action=pano&viewpoint="&SUBSTITUTE(AF3," ",""),"Abrir Street View"))
S4: =IF(NOT(ISNUMBER(M4)),"",IF(G4="Terreno",IF(AND(ISNUMBER(I4),I4>0),M4/I4,""),IF(AND(ISNUMBER(H4),H4>0),M4/H4,""))) | T4: =IF(AND(ISNUMBER(M4),ISNUMBER(O4)),IF(M4<=O4,"Valor ≤ venal IPTU",""),"") | U4: =IF(AND(ISNUMBER(M4),ISNUMBER(N4)),IF(N4>0,M4/N4,""),"") | V4: =IF(AND(ISNUMBER(M4),ISNUMBER(O4)),IF(O4>0,M4/O4,""),"") | W4: =IF(AND(ISNUMBER(M4),ISNUMBER(R4)),IF(R4>0,M4/R4,""),"") | X4: =IF(AND(ISNUMBER(Q4),ISNUMBER(M4)),IF(M4>0,Q4/M4,""),"") | Y4: =IF(ISNUMBER(Z4),YEAR(Z4),"") | AJ4: =IF(LEN(TRIM(AF4))=0,"",HYPERLINK("https://www.google.com/maps/@?api=1&map_action=pano&viewpoint="&SUBSTITUTE(AF4," ",""),"Abrir Street View"))
S5: =IF(NOT(ISNUMBER(M5)),"",IF(G5="Terreno",IF(AND(ISNUMBER(I5),I5>0),M5/I5,""),IF(AND(ISNUMBER(H5),H5>0),M5/H5,""))) | T5: =IF(AND(ISNUMBER(M5),ISNUMBER(O5)),IF(M5<=O5,"Valor ≤ venal IPTU",""),"") | U5: =IF(AND(ISNUMBER(M5),ISNUMBER(N5)),IF(N5>0,M5/N5,""),"") | V5: =IF(AND(ISNUMBER(M5),ISNUMBER(O5)),IF(O5>0,M5/O5,""),"") | W5: =IF(AND(ISNUMBER(M5),ISNUMBER(R5)),IF(R5>0,M5/R5,""),"") | X5: =IF(AND(ISNUMBER(Q5),ISNUMBER(M5)),IF(M5>0,Q5/M5,""),"") | Y5: =IF(ISNUMBER(Z5),YEAR(Z5),"") | AJ5: =IF(LEN(TRIM(AF5))=0,"",HYPERLINK("https://www.google.com/maps/@?api=1&map_action=pano&viewpoint="&SUBSTITUTE(AF5," ",""),"Abrir Street View"))
S6: =IF(NOT(ISNUMBER(M6)),"",IF(G6="Terreno",IF(AND(ISNUMBER(I6),I6>0),M6/I6,""),IF(AND(ISNUMBER(H6),H6>0),M6/H6,""))) | T6: =IF(AND(ISNUMBER(M6),ISNUMBER(O6)),IF(M6<=O6,"Valor ≤ venal IPTU",""),"") | U6: =IF(AND(ISNUMBER(M6),ISNUMBER(N6)),IF(N6>0,M6/N6,""),"") | V6: =IF(AND(ISNUMBER(M6),ISNUMBER(O6)),IF(O6>0,M6/O6,""),"") | W6: =IF(AND(ISNUMBER(M6),ISNUMBER(R6)),IF(R6>0,M6/R6,""),"") | X6: =IF(AND(ISNUMBER(Q6),ISNUMBER(M6)),IF(M6>0,Q6/M6,""),"") | Y6: =IF(ISNUMBER(Z6),YEAR(Z6),"") | AJ6: =IF(LEN(TRIM(AF6))=0,"",HYPERLINK("https://www.google.com/maps/@?api=1&map_action=pano&viewpoint="&SUBSTITUTE(AF6," ",""),"Abrir Street View"))
S7: =IF(NOT(ISNUMBER(M7)),"",IF(G7="Terreno",IF(AND(ISNUMBER(I7),I7>0),M7/I7,""),IF(AND(ISNUMBER(H7),H7>0),M7/H7,""))) | T7: =IF(AND(ISNUMBER(M7),ISNUMBER(O7)),IF(M7<=O7,"Valor ≤ venal IPTU",""),"") | U7: =IF(AND(ISNUMBER(M7),ISNUMBER(N7)),IF(N7>0,M7/N7,""),"") | V7: =IF(AND(ISNUMBER(M7),ISNUMBER(O7)),IF(O7>0,M7/O7,""),"") | W7: =IF(AND(ISNUMBER(M7),ISNUMBER(R7)),IF(R7>0,M7/R7,""),"") | X7: =IF(AND(ISNUMBER(Q7),ISNUMBER(M7)),IF(M7>0,Q7/M7,""),"") | Y7: =IF(ISNUMBER(Z7),YEAR(Z7),"") | AJ7: =IF(LEN(TRIM(AF7))=0,"",HYPERLINK("https://www.google.com/maps/@?api=1&map_action=pano&viewpoint="&SUBSTITUTE(AF7," ",""),"Abrir Street View"))
S8: =IF(NOT(ISNUMBER(M8)),"",IF(G8="Terreno",IF(AND(ISNUMBER(I8),I8>0),M8/I8,""),IF(AND(ISNUMBER(H8),H8>0),M8/H8,""))) | T8: =IF(AND(ISNUMBER(M8),ISNUMBER(O8)),IF(M8<=O8,"Valor ≤ venal IPTU",""),"") | U8: =IF(AND(ISNUMBER(M8),ISNUMBER(N8)),IF(N8>0,M8/N8,""),"") | V8: =IF(AND(ISNUMBER(M8),ISNUMBER(O8)),IF(O8>0,M8/O8,""),"") | W8: =IF(AND(ISNUMBER(M8),ISNUMBER(R8)),IF(R8>0,M8/R8,""),"") | X8: =IF(AND(ISNUMBER(Q8),ISNUMBER(M8)),IF(M8>0,Q8/M8,""),"") | Y8: =IF(ISNUMBER(Z8),YEAR(Z8),"") | AJ8: =IF(LEN(TRIM(AF8))=0,"",HYPERLINK("https://www.google.com/maps/@?api=1&map_action=pano&viewpoint="&SUBSTITUTE(AF8," ",""),"Abrir Street View"))
S9: =IF(NOT(ISNUMBER(M9)),"",IF(G9="Terreno",IF(AND(ISNUMBER(I9),I9>0),M9/I9,""),IF(AND(ISNUMBER(H9),H9>0),M9/H9,""))) | T9: =IF(AND(ISNUMBER(M9),ISNUMBER(O9)),IF(M9<=O9,"Valor ≤ venal IPTU",""),"") | U9: =IF(AND(ISNUMBER(M9),ISNUMBER(N9)),IF(N9>0,M9/N9,""),"") | V9: =IF(AND(ISNUMBER(M9),ISNUMBER(O9)),IF(O9>0,M9/O9,""),"") | W9: =IF(AND(ISNUMBER(M9),ISNUMBER(R9)),IF(R9>0,M9/R9,""),"") | X9: =IF(AND(ISNUMBER(Q9),ISNUMBER(M9)),IF(M9>0,Q9/M9,""),"") | Y9: =IF(ISNUMBER(Z9),YEAR(Z9),"") | AJ9: =IF(LEN(TRIM(AF9))=0,"",HYPERLINK("https://www.google.com/maps/@?api=1&map_action=pano&viewpoint="&SUBSTITUTE(AF9," ",""),"Abrir Street View"))
S10: =IF(NOT(ISNUMBER(M10)),"",IF(G10="Terreno",IF(AND(ISNUMBER(I10),I10>0),M10/I10,""),IF(AND(ISNUMBER(H10),H10>0),M10/H10,""))) | T10: =IF(AND(ISNUMBER(M10),ISNUMBER(O10)),IF(M10<=O10,"Valor ≤ venal IPTU",""),"") | U10: =IF(AND(ISNUMBER(M10),ISNUMBER(N10)),IF(N10>0,M10/N10,""),"") | V10: =IF(AND(ISNUMBER(M10),ISNUMBER(O10)),IF(O10>0,M10/O10,""),"") | W10: =IF(AND(ISNUMBER(M10),ISNUMBER(R10)),IF(R10>0,M10/R10,""),"") | X10: =IF(AND(ISNUMBER(Q10),ISNUMBER(M10)),IF(M10>0,Q10/M10,""),"") | Y10: =IF(ISNUMBER(Z10),YEAR(Z10),"") | AJ10: =IF(LEN(TRIM(AF10))=0,"",HYPERLINK("https://www.google.com/maps/@?api=1&map_action=pano&viewpoint="&SUBSTITUTE(AF10," ",""),"Abrir Street View"))
S11: =IF(NOT(ISNUMBER(M11)),"",IF(G11="Terreno",IF(AND(ISNUMBER(I11),I11>0),M11/I11,""),IF(AND(ISNUMBER(H11),H11>0),M11/H11,""))) | T11: =IF(AND(ISNUMBER(M11),ISNUMBER(O11)),IF(M11<=O11,"Valor ≤ venal IPTU",""),"") | U11: =IF(AND(ISNUMBER(M11),ISNUMBER(N11)),IF(N11>0,M11/N11,""),"") | V11: =IF(AND(ISNUMBER(M11),ISNUMBER(O11)),IF(O11>0,M11/O11,""),"") | W11: =IF(AND(ISNUMBER(M11),ISNUMBER(R11)),IF(R11>0,M11/R11,""),"") | X11: =IF(AND(ISNUMBER(Q11),ISNUMBER(M11)),IF(M11>0,Q11/M11,""),"") | Y11: =IF(ISNUMBER(Z11),YEAR(Z11),"") | AJ11: =IF(LEN(TRIM(AF11))=0,"",HYPERLINK("https://www.google.com/maps/@?api=1&map_action=pano&viewpoint="&SUBSTITUTE(AF11," ",""),"Abrir Street View"))
S12: =IF(NOT(ISNUMBER(M12)),"",IF(G12="Terreno",IF(AND(ISNUMBER(I12),I12>0),M12/I12,""),IF(AND(ISNUMBER(H12),H12>0),M12/H12,""))) | T12: =IF(AND(ISNUMBER(M12),ISNUMBER(O12)),IF(M12<=O12,"Valor ≤ venal IPTU",""),"") | U12: =IF(AND(ISNUMBER(M12),ISNUMBER(N12)),IF(N12>0,M12/N12,""),"") | V12: =IF(AND(ISNUMBER(M12),ISNUMBER(O12)),IF(O12>0,M12/O12,""),"") | W12: =IF(AND(ISNUMBER(M12),ISNUMBER(R12)),IF(R12>0,M12/R12,""),"") | X12: =IF(AND(ISNUMBER(Q12),ISNUMBER(M12)),IF(M12>0,Q12/M12,""),"") | Y12: =IF(ISNUMBER(Z12),YEAR(Z12),"") | AJ12: =IF(LEN(TRIM(AF12))=0,"",HYPERLINK("https://www.google.com/maps/@?api=1&map_action=pano&viewpoint="&SUBSTITUTE(AF12," ",""),"Abrir Street View"))
S13: =IF(NOT(ISNUMBER(M13)),"",IF(G13="Terreno",IF(AND(ISNUMBER(I13),I13>0),M13/I13,""),IF(AND(ISNUMBER(H13),H13>0),M13/H13,""))) | T13: =IF(AND(ISNUMBER(M13),ISNUMBER(O13)),IF(M13<=O13,"Valor ≤ venal IPTU",""),"") | U13: =IF(AND(ISNUMBER(M13),ISNUMBER(N13)),IF(N13>0,M13/N13,""),"") | V13: =IF(AND(ISNUMBER(M13),ISNUMBER(O13)),IF(O13>0,M13/O13,""),"") | W13: =IF(AND(ISNUMBER(M13),ISNUMBER(R13)),IF(R13>0,M13/R13,""),"") | X13: =IF(AND(ISNUMBER(Q13),ISNUMBER(M13)),IF(M13>0,Q13/M13,""),"") | Y13: =IF(ISNUMBER(Z13),YEAR(Z13),"") | AJ13: =IF(LEN(TRIM(AF13))=0,"",HYPERLINK("https://www.google.com/maps/@?api=1&map_action=pano&viewpoint="&SUBSTITUTE(AF13," ",""),"Abrir Street View"))
... S3001: =IF(NOT(ISNUMBER(M3001)),"",IF(G3001="Terreno",IF(AND(ISNUMBER(I3001),I3001>0),M3001/I3001,""),IF(AND(ISNUMBER(H3001),H3001>0),M3001/H3001,""))) | T3001: =IF(AND(ISNUMBER(M3001),ISNUMBER(O3001)),IF(M3001<=O3001,"Valor ≤ venal IPTU",""),"") | U3001: =IF(AND(ISNUMBER(M3001),ISNUMBER(N3001)),IF(N3001>0,M3001/N3001,""),"") | V3001: =IF(AND(ISNUMBER(M3001),ISNUMBER(O3001)),IF(O3001>0,M3001/O3001,""),"") | W3001: =IF(AND(ISNUMBER(M3001),ISNUMBER(R3001)),IF(R3001>0,M3001/R3001,""),"") | X3001: =IF(AND(ISNUMBER(Q3001),ISNUMBER(M3001)),IF(M3001>0,Q3001/M3001,""),"") | Y3001: =IF(ISNUMBER(Z3001),YEAR(Z3001),"") | AJ3001: =IF(LEN(TRIM(AF3001))=0,"",HYPERLINK("https://www.google.com/maps/@?api=1&map_action=pano&viewpoint="&SUBSTITUTE(AF3001," ",""),"Abrir Street View"))

Sheet Bairros
A1: Bairros oficiais por cidade
A3: São Sebastião | E3: Bertioga
A4: Fonte: IBGE, Censo 2022, malha de bairros SP_bairros_CD2022 — https://geoftp.ibge.gov.br/organizacao_do_territorio/malhas_territoriais/malhas_de_setores_censitarios__divisoes_intramunicipais/censo_2022/bairros/shp/UF/SP_bairros_CD2022.zip (não foi localizada lei municipal de bairros) | E4: Fonte: Lei Complementar nº 99/2013 de Bertioga, Anexo 1 — https://www.bertioga.sp.gov.br/wp/wp-content/uploads/2015/06/Lei-Complementar-99.2013.pdf
A5: Bairro | B5: Código | C5: Observação | E5: Bairro | F5: Código | G5: Observação
A6: Enseada | B6: 3550704001 | C6: Distrito São Francisco da Praia | E6: Caiubura | F6: 01 | G6: RA1 Sul
A7: Jaraguá | B7: 3550704002 | C7: Distrito São Francisco da Praia | E7: São João | F7: 02 | G7: RA1 Sul
A8: Cigarras | B8: 3550704003 | C8: Distrito São Francisco da Praia | E8: Centro | F8: 03 | G8: RA2 Central
A9: São Francisco | B9: 3550704004 | C9: Distrito São Francisco da Praia | E9: Jardim Vicente de Carvalho | F9: 04 | G9: RA2 Central
A10: Morro do Abrigo | B10: 3550704005 | C10: Distrito São Francisco da Praia | E10: Albatróz | F10: 05 | G10: RA2 Central
A11: Olaria | B11: 3550704006 / 3550704036 | C11: O IBGE registra dois setores 'Olaria' (distritos São Francisco da Praia e São Sebastião) | E11: Maitinga | F11: 06 | G11: RA2 Central
A12: Arrastão | B12: 3550704007 | C12: Distrito São Francisco da Praia | E12: Rio da Praia | F12: 07 | G12: RA2 Central
A13: Pontal da Cruz | B13: 3550704008 | C13: Distrito São Sebastião | E13: Buriqui Costa Nativa (Brasfanta) | F13: 08 | G13: RA2 Central
A14: Praia Deserta | B14: 3550704009 | C14: Distrito São Sebastião | E14: Jardim Raphael | F14: 09 | G14: RA2 Central — conhecido popularmente como São Rafael
A15: Porto Grande | B15: 3550704010 | C15: Distrito São Sebastião | E15: Bairro Chácaras | F15: 10 | G15: RA3 Média
A16: Centro | B16: 3550704011 | C16: Distrito São Sebastião | E16: Vista Linda | F16: 11 | G16: RA3 Média
... A24: Calhetas | B24: 3550704019 | C24: Distrito São Sebastião | E24: T.I. (Terras Indígenas do Rio Silveiras) | F24: 19 | G24: RA4 Norte
A25: Toque-Toque Pequeno | B25: 3550704020 | C25: Distrito São Sebastião
A26: Santiago | B26: 3550704021 | C26: Distrito Maresias
A27: Paúba | B27: 3550704022 | C27: Distrito Maresias
A28: Maresias | B28: 3550704023 | C28: Distrito Maresias
A29: Boiçucanga | B29: 3550704024 | C29: Distrito Maresias
A30: Camburi | B30: 3550704025 | C30: Distrito Maresias
A31: Baleia | B31: 3550704026 | C31: Distrito Maresias
A32: Barra do Sahy | B32: 3550704027 | C32: Distrito Maresias
A33: Juqueí | B33: 3550704028 | C33: Distrito Maresias — grafia IBGE (também escrito Juquehy)
A34: Barra do Una | B34: 3550704029 | C34: Distrito Maresias
A35: Boracéia | B35: 3550704030 | C35: Distrito Maresias
A36: Canto do Mar | B36: 3550704031 | C36: Distrito São Francisco da Praia
... A41: Engenho | B41: 3550704039 | C41: Distrito Maresias

Sheet Listas
A1: Cidades | B1: Tipos | C1: Padrões | D1: Origem do padrão | E1: Natureza | F1: Fontes | G1: Origem da foto | H1: Forma de pagamento | I1: Status
A2: São Sebastião | B2: Casa | C2: Baixo | D2: Cadastro municipal (ITBI/IPTU) | E2: Compra e venda | F2: LAI – ITBI Prefeitura | G2: Foto própria no local | H2: Financiado | I2: Validado
A3: Bertioga | B3: Casa em condomínio | C3: Normal | D3: Certidão/memorial/habite-se | F3: Certidão de matrícula (CRI) | G3: Google Street View (link) | H3: À vista | I3: Pendente de conferência
B4: Apartamento | C4: Alto | D4: Vistoria própria (critério NBR 12721) | G4: Foto da certidão/laudo | H4: Não informado | I4: Rejeitado
B5: Terreno | C5: Não informado | D5: Não informado | G5: Sem foto
B6: Sala/Loja comercial
B7: Galpão
B8: Outro

Sheet Resumo
A1: Resumo por cidade e bairro (somente vendas com Status = Validado)
A2: Fórmulas recalculam sozinhas. Bairros sem venda validada mostram '-'. Mediana e R$/m² ignoram linhas sem metragem.
A4: Cidade | B4: Bairro | C4: Nº de vendas | D4: Valor mediano (R$) | E4: Menor valor (R$) | F4: Maior valor (R$) | G4: R$/m² mediano | H4: Nº c/ alerta venal | I4: Venda mais antiga | J4: Venda mais recente
A5: São Sebastião | B5: Enseada | C5: =COUNTIFS(Vendas!$B$2:$B$3001,$A5,Vendas!$C$2:$C$3001,$B5,Vendas!$AK$2:$AK$3001,"Validado") | D5: {=IF(C5=0,"-",MEDIAN(IF((Vendas!$B$2:$B$3001=$A5)*(Vendas!$C$2:$C$3001=$B5)*(Vendas!$AK$2:$AK$3001="Validado")*ISNUMBER(Vendas!$M$2:$M$3001),Vendas!$M$2:$M$3001)))} | E5: =IF(C5=0,"-",_xlfn.MINIFS(Vendas!$M$2:$M$3001,Vendas!$B$2:$B$3001,$A5,Vendas!$C$2:$C$3001,$B5,Vendas!$AK$2:$AK$3001,"Validado")) | F5: =IF(C5=0,"-",_xlfn.MAXIFS(Vendas!$M$2:$M$3001,Vendas!$B$2:$B$3001,$A5,Vendas!$C$2:$C$3001,$B5,Vendas!$AK$2:$AK$3001,"Validado")) | G5: {=IF(SUMPRODUCT((Vendas!$B$2:$B$3001=$A5)*(Vendas!$C$2:$C$3001=$B5)*(Vendas!$AK$2:$AK$3001="Validado")*ISNUMBER(Vendas!$S$2:$S$3001))=0,"-",MEDIAN(IF((Vendas!$B$2:$B$3001=$A5)*(Vendas!$C$2:$C$3001=$B5)*(Vendas!$AK$2:$AK$3001="Validado")*ISNUMBER(Vendas!$S$2:$S$3001),Vendas!$S$2:$S$3001)))} | H5: =COUNTIFS(Vendas!$B$2:$B$3001,$A5,Vendas!$C$2:$C$3001,$B5,Vendas!$AK$2:$AK$3001,"Validado",Vendas!$T$2:$T$3001,"Valor*") | I5: =IF(C5=0,"-",_xlfn.MINIFS(Vendas!$Z$2:$Z$3001,Vendas!$B$2:$B$3001,$A5,Vendas!$C$2:$C$3001,$B5,Vendas!$AK$2:$AK$3001,"Validado")) | J5: =IF(C5=0,"-",_xlfn.MAXIFS(Vendas!$Z$2:$Z$3001,Vendas!$B$2:$B$3001,$A5,Vendas!$C$2:$C$3001,$B5,Vendas!$AK$2:$AK$3001,"Validado"))
A6: São Sebastião | B6: Jaraguá | C6: =COUNTIFS(Vendas!$B$2:$B$3001,$A6,Vendas!$C$2:$C$3001,$B6,Vendas!$AK$2:$AK$3001,"Validado") | D6: {=IF(C6=0,"-",MEDIAN(IF((Vendas!$B$2:$B$3001=$A6)*(Vendas!$C$2:$C$3001=$B6)*(Vendas!$AK$2:$AK$3001="Validado")*ISNUMBER(Vendas!$M$2:$M$3001),Vendas!$M$2:$M$3001)))} | E6: =IF(C6=0,"-",_xlfn.MINIFS(Vendas!$M$2:$M$3001,Vendas!$B$2:$B$3001,$A6,Vendas!$C$2:$C$3001,$B6,Vendas!$AK$2:$AK$3001,"Validado")) | F6: =IF(C6=0,"-",_xlfn.MAXIFS(Vendas!$M$2:$M$3001,Vendas!$B$2:$B$3001,$A6,Vendas!$C$2:$C$3001,$B6,Vendas!$AK$2:$AK$3001,"Validado")) | G6: {=IF(SUMPRODUCT((Vendas!$B$2:$B$3001=$A6)*(Vendas!$C$2:$C$3001=$B6)*(Vendas!$AK$2:$AK$3001="Validado")*ISNUMBER(Vendas!$S$2:$S$3001))=0,"-",MEDIAN(IF((Vendas!$B$2:$B$3001=$A6)*(Vendas!$C$2:$C$3001=$B6)*(Vendas!$AK$2:$AK$3001="Validado")*ISNUMBER(Vendas!$S$2:$S$3001),Vendas!$S$2:$S$3001)))} | H6: =COUNTIFS(Vendas!$B$2:$B$3001,$A6,Vendas!$C$2:$C$3001,$B6,Vendas!$AK$2:$AK$3001,"Validado",Vendas!$T$2:$T$3001,"Valor*") | I6: =IF(C6=0,"-",_xlfn.MINIFS(Vendas!$Z$2:$Z$3001,Vendas!$B$2:$B$3001,$A6,Vendas!$C$2:$C$3001,$B6,Vendas!$AK$2:$AK$3001,"Validado")) | J6: =IF(C6=0,"-",_xlfn.MAXIFS(Vendas!$Z$2:$Z$3001,Vendas!$B$2:$B$3001,$A6,Vendas!$C$2:$C$3001,$B6,Vendas!$AK$2:$AK$3001,"Validado"))
A7: São Sebastião | B7: Cigarras | C7: =COUNTIFS(Vendas!$B$2:$B$3001,$A7,Vendas!$C$2:$C$3001,$B7,Vendas!$AK$2:$AK$3001,"Validado") | D7: {=IF(C7=0,"-",MEDIAN(IF((Vendas!$B$2:$B$3001=$A7)*(Vendas!$C$2:$C$3001=$B7)*(Vendas!$AK$2:$AK$3001="Validado")*ISNUMBER(Vendas!$M$2:$M$3001),Vendas!$M$2:$M$3001)))} | E7: =IF(C7=0,"-",_xlfn.MINIFS(Vendas!$M$2:$M$3001,Vendas!$B$2:$B$3001,$A7,Vendas!$C$2:$C$3001,$B7,Vendas!$AK$2:$AK$3001,"Validado")) | F7: =IF(C7=0,"-",_xlfn.MAXIFS(Vendas!$M$2:$M$3001,Vendas!$B$2:$B$3001,$A7,Vendas!$C$2:$C$3001,$B7,Vendas!$AK$2:$AK$3001,"Validado")) | G7: {=IF(SUMPRODUCT((Vendas!$B$2:$B$3001=$A7)*(Vendas!$C$2:$C$3001=$B7)*(Vendas!$AK$2:$AK$3001="Validado")*ISNUMBER(Vendas!$S$2:$S$3001))=0,"-",MEDIAN(IF((Vendas!$B$2:$B$3001=$A7)*(Vendas!$C$2:$C$3001=$B7)*(Vendas!$AK$2:$AK$3001="Validado")*ISNUMBER(Vendas!$S$2:$S$3001),Vendas!$S$2:$S$3001)))} | H7: =COUNTIFS(Vendas!$B$2:$B$3001,$A7,Vendas!$C$2:$C$3001,$B7,Vendas!$AK$2:$AK$3001,"Validado",Vendas!$T$2:$T$3001,"Valor*") | I7: =IF(C7=0,"-",_xlfn.MINIFS(Vendas!$Z$2:$Z$3001,Vendas!$B$2:$B$3001,$A7,Vendas!$C$2:$C$3001,$B7,Vendas!$AK$2:$AK$3001,"Validado")) | J7: =IF(C7=0,"-",_xlfn.MAXIFS(Vendas!$Z$2:$Z$3001,Vendas!$B$2:$B$3001,$A7,Vendas!$C$2:$C$3001,$B7,Vendas!$AK$2:$AK$3001,"Validado"))
A8: São Sebastião | B8: São Francisco | C8: =COUNTIFS(Vendas!$B$2:$B$3001,$A8,Vendas!$C$2:$C$3001,$B8,Vendas!$AK$2:$AK$3001,"Validado") | D8: {=IF(C8=0,"-",MEDIAN(IF((Vendas!$B$2:$B$3001=$A8)*(Vendas!$C$2:$C$3001=$B8)*(Vendas!$AK$2:$AK$3001="Validado")*ISNUMBER(Vendas!$M$2:$M$3001),Vendas!$M$2:$M$3001)))} | E8: =IF(C8=0,"-",_xlfn.MINIFS(Vendas!$M$2:$M$3001,Vendas!$B$2:$B$3001,$A8,Vendas!$C$2:$C$3001,$B8,Vendas!$AK$2:$AK$3001,"Validado")) | F8: =IF(C8=0,"-",_xlfn.MAXIFS(Vendas!$M$2:$M$3001,Vendas!$B$2:$B$3001,$A8,Vendas!$C$2:$C$3001,$B8,Vendas!$AK$2:$AK$3001,"Validado")) | G8: {=IF(SUMPRODUCT((Vendas!$B$2:$B$3001=$A8)*(Vendas!$C$2:$C$3001=$B8)*(Vendas!$AK$2:$AK$3001="Validado")*ISNUMBER(Vendas!$S$2:$S$3001))=0,"-",MEDIAN(IF((Vendas!$B$2:$B$3001=$A8)*(Vendas!$C$2:$C$3001=$B8)*(Vendas!$AK$2:$AK$3001="Validado")*ISNUMBER(Vendas!$S$2:$S$3001),Vendas!$S$2:$S$3001)))} | H8: =COUNTIFS(Vendas!$B$2:$B$3001,$A8,Vendas!$C$2:$C$3001,$B8,Vendas!$AK$2:$AK$3001,"Validado",Vendas!$T$2:$T$3001,"Valor*") | I8: =IF(C8=0,"-",_xlfn.MINIFS(Vendas!$Z$2:$Z$3001,Vendas!$B$2:$B$3001,$A8,Vendas!$C$2:$C$3001,$B8,Vendas!$AK$2:$AK$3001,"Validado")) | J8: =IF(C8=0,"-",_xlfn.MAXIFS(Vendas!$Z$2:$Z$3001,Vendas!$B$2:$B$3001,$A8,Vendas!$C$2:$C$3001,$B8,Vendas!$AK$2:$AK$3001,"Validado"))
A9: São Sebastião | B9: Morro do Abrigo | C9: =COUNTIFS(Vendas!$B$2:$B$3001,$A9,Vendas!$C$2:$C$3001,$B9,Vendas!$AK$2:$AK$3001,"Validado") | D9: {=IF(C9=0,"-",MEDIAN(IF((Vendas!$B$2:$B$3001=$A9)*(Vendas!$C$2:$C$3001=$B9)*(Vendas!$AK$2:$AK$3001="Validado")*ISNUMBER(Vendas!$M$2:$M$3001),Vendas!$M$2:$M$3001)))} | E9: =IF(C9=0,"-",_xlfn.MINIFS(Vendas!$M$2:$M$3001,Vendas!$B$2:$B$3001,$A9,Vendas!$C$2:$C$3001,$B9,Vendas!$AK$2:$AK$3001,"Validado")) | F9: =IF(C9=0,"-",_xlfn.MAXIFS(Vendas!$M$2:$M$3001,Vendas!$B$2:$B$3001,$A9,Vendas!$C$2:$C$3001,$B9,Vendas!$AK$2:$AK$3001,"Validado")) | G9: {=IF(SUMPRODUCT((Vendas!$B$2:$B$3001=$A9)*(Vendas!$C$2:$C$3001=$B9)*(Vendas!$AK$2:$AK$3001="Validado")*ISNUMBER(Vendas!$S$2:$S$3001))=0,"-",MEDIAN(IF((Vendas!$B$2:$B$3001=$A9)*(Vendas!$C$2:$C$3001=$B9)*(Vendas!$AK$2:$AK$3001="Validado")*ISNUMBER(Vendas!$S$2:$S$3001),Vendas!$S$2:$S$3001)))} | H9: =COUNTIFS(Vendas!$B$2:$B$3001,$A9,Vendas!$C$2:$C$3001,$B9,Vendas!$AK$2:$AK$3001,"Validado",Vendas!$T$2:$T$3001,"Valor*") | I9: =IF(C9=0,"-",_xlfn.MINIFS(Vendas!$Z$2:$Z$3001,Vendas!$B$2:$B$3001,$A9,Vendas!$C$2:$C$3001,$B9,Vendas!$AK$2:$AK$3001,"Validado")) | J9: =IF(C9=0,"-",_xlfn.MAXIFS(Vendas!$Z$2:$Z$3001,Vendas!$B$2:$B$3001,$A9,Vendas!$C$2:$C$3001,$B9,Vendas!$AK$2:$AK$3001,"Validado"))
A10: São Sebastião | B10: Olaria | C10: =COUNTIFS(Vendas!$B$2:$B$3001,$A10,Vendas!$C$2:$C$3001,$B10,Vendas!$AK$2:$AK$3001,"Validado") | D10: {=IF(C10=0,"-",MEDIAN(IF((Vendas!$B$2:$B$3001=$A10)*(Vendas!$C$2:$C$3001=$B10)*(Vendas!$AK$2:$AK$3001="Validado")*ISNUMBER(Vendas!$M$2:$M$3001),Vendas!$M$2:$M$3001)))} | E10: =IF(C10=0,"-",_xlfn.MINIFS(Vendas!$M$2:$M$3001,Vendas!$B$2:$B$3001,$A10,Vendas!$C$2:$C$3001,$B10,Vendas!$AK$2:$AK$3001,"Validado")) | F10: =IF(C10=0,"-",_xlfn.MAXIFS(Vendas!$M$2:$M$3001,Vendas!$B$2:$B$3001,$A10,Vendas!$C$2:$C$3001,$B10,Vendas!$AK$2:$AK$3001,"Validado")) | G10: {=IF(SUMPRODUCT((Vendas!$B$2:$B$3001=$A10)*(Vendas!$C$2:$C$3001=$B10)*(Vendas!$AK$2:$AK$3001="Validado")*ISNUMBER(Vendas!$S$2:$S$3001))=0,"-",MEDIAN(IF((Vendas!$B$2:$B$3001=$A10)*(Vendas!$C$2:$C$3001=$B10)*(Vendas!$AK$2:$AK$3001="Validado")*ISNUMBER(Vendas!$S$2:$S$3001),Vendas!$S$2:$S$3001)))} | H10: =COUNTIFS(Vendas!$B$2:$B$3001,$A10,Vendas!$C$2:$C$3001,$B10,Vendas!$AK$2:$AK$3001,"Validado",Vendas!$T$2:$T$3001,"Valor*") | I10: =IF(C10=0,"-",_xlfn.MINIFS(Vendas!$Z$2:$Z$3001,Vendas!$B$2:$B$3001,$A10,Vendas!$C$2:$C$3001,$B10,Vendas!$AK$2:$AK$3001,"Validado")) | J10: =IF(C10=0,"-",_xlfn.MAXIFS(Vendas!$Z$2:$Z$3001,Vendas!$B$2:$B$3001,$A10,Vendas!$C$2:$C$3001,$B10,Vendas!$AK$2:$AK$3001,"Validado"))
A11: São Sebastião | B11: Arrastão | C11: =COUNTIFS(Vendas!$B$2:$B$3001,$A11,Vendas!$C$2:$C$3001,$B11,Vendas!$AK$2:$AK$3001,"Validado") | D11: {=IF(C11=0,"-",MEDIAN(IF((Vendas!$B$2:$B$3001=$A11)*(Vendas!$C$2:$C$3001=$B11)*(Vendas!$AK$2:$AK$3001="Validado")*ISNUMBER(Vendas!$M$2:$M$3001),Vendas!$M$2:$M$3001)))} | E11: =IF(C11=0,"-",_xlfn.MINIFS(Vendas!$M$2:$M$3001,Vendas!$B$2:$B$3001,$A11,Vendas!$C$2:$C$3001,$B11,Vendas!$AK$2:$AK$3001,"Validado")) | F11: =IF(C11=0,"-",_xlfn.MAXIFS(Vendas!$M$2:$M$3001,Vendas!$B$2:$B$3001,$A11,Vendas!$C$2:$C$3001,$B11,Vendas!$AK$2:$AK$3001,"Validado")) | G11: {=IF(SUMPRODUCT((Vendas!$B$2:$B$3001=$A11)*(Vendas!$C$2:$C$3001=$B11)*(Vendas!$AK$2:$AK$3001="Validado")*ISNUMBER(Vendas!$S$2:$S$3001))=0,"-",MEDIAN(IF((Vendas!$B$2:$B$3001=$A11)*(Vendas!$C$2:$C$3001=$B11)*(Vendas!$AK$2:$AK$3001="Validado")*ISNUMBER(Vendas!$S$2:$S$3001),Vendas!$S$2:$S$3001)))} | H11: =COUNTIFS(Vendas!$B$2:$B$3001,$A11,Vendas!$C$2:$C$3001,$B11,Vendas!$AK$2:$AK$3001,"Validado",Vendas!$T$2:$T$3001,"Valor*") | I11: =IF(C11=0,"-",_xlfn.MINIFS(Vendas!$Z$2:$Z$3001,Vendas!$B$2:$B$3001,$A11,Vendas!$C$2:$C$3001,$B11,Vendas!$AK$2:$AK$3001,"Validado")) | J11: =IF(C11=0,"-",_xlfn.MAXIFS(Vendas!$Z$2:$Z$3001,Vendas!$B$2:$B$3001,$A11,Vendas!$C$2:$C$3001,$B11,Vendas!$AK$2:$AK$3001,"Validado"))
A12: São Sebastião | B12: Pontal da Cruz | C12: =COUNTIFS(Vendas!$B$2:$B$3001,$A12,Vendas!$C$2:$C$3001,$B12,Vendas!$AK$2:$AK$3001,"Validado") | D12: {=IF(C12=0,"-",MEDIAN(IF((Vendas!$B$2:$B$3001=$A12)*(Vendas!$C$2:$C$3001=$B12)*(Vendas!$AK$2:$AK$3001="Validado")*ISNUMBER(Vendas!$M$2:$M$3001),Vendas!$M$2:$M$3001)))} | E12: =IF(C12=0,"-",_xlfn.MINIFS(Vendas!$M$2:$M$3001,Vendas!$B$2:$B$3001,$A12,Vendas!$C$2:$C$3001,$B12,Vendas!$AK$2:$AK$3001,"Validado")) | F12: =IF(C12=0,"-",_xlfn.MAXIFS(Vendas!$M$2:$M$3001,Vendas!$B$2:$B$3001,$A12,Vendas!$C$2:$C$3001,$B12,Vendas!$AK$2:$AK$3001,"Validado")) | G12: {=IF(SUMPRODUCT((Vendas!$B$2:$B$3001=$A12)*(Vendas!$C$2:$C$3001=$B12)*(Vendas!$AK$2:$AK$3001="Validado")*ISNUMBER(Vendas!$S$2:$S$3001))=0,"-",MEDIAN(IF((Vendas!$B$2:$B$3001=$A12)*(Vendas!$C$2:$C$3001=$B12)*(Vendas!$AK$2:$AK$3001="Validado")*ISNUMBER(Vendas!$S$2:$S$3001),Vendas!$S$2:$S$3001)))} | H12: =COUNTIFS(Vendas!$B$2:$B$3001,$A12,Vendas!$C$2:$C$3001,$B12,Vendas!$AK$2:$AK$3001,"Validado",Vendas!$T$2:$T$3001,"Valor*") | I12: =IF(C12=0,"-",_xlfn.MINIFS(Vendas!$Z$2:$Z$3001,Vendas!$B$2:$B$3001,$A12,Vendas!$C$2:$C$3001,$B12,Vendas!$AK$2:$AK$3001,"Validado")) | J12: =IF(C12=0,"-",_xlfn.MAXIFS(Vendas!$Z$2:$Z$3001,Vendas!$B$2:$B$3001,$A12,Vendas!$C$2:$C$3001,$B12,Vendas!$AK$2:$AK$3001,"Validado"))
A13: São Sebastião | B13: Praia Deserta | C13: =COUNTIFS(Vendas!$B$2:$B$3001,$A13,Vendas!$C$2:$C$3001,$B13,Vendas!$AK$2:$AK$3001,"Validado") | D13: {=IF(C13=0,"-",MEDIAN(IF((Vendas!$B$2:$B$3001=$A13)*(Vendas!$C$2:$C$3001=$B13)*(Vendas!$AK$2:$AK$3001="Validado")*ISNUMBER(Vendas!$M$2:$M$3001),Vendas!$M$2:$M$3001)))} | E13: =IF(C13=0,"-",_xlfn.MINIFS(Vendas!$M$2:$M$3001,Vendas!$B$2:$B$3001,$A13,Vendas!$C$2:$C$3001,$B13,Vendas!$AK$2:$AK$3001,"Validado")) | F13: =IF(C13=0,"-",_xlfn.MAXIFS(Vendas!$M$2:$M$3001,Vendas!$B$2:$B$3001,$A13,Vendas!$C$2:$C$3001,$B13,Vendas!$AK$2:$AK$3001,"Validado")) | G13: {=IF(SUMPRODUCT((Vendas!$B$2:$B$3001=$A13)*(Vendas!$C$2:$C$3001=$B13)*(Vendas!$AK$2:$AK$3001="Validado")*ISNUMBER(Vendas!$S$2:$S$3001))=0,"-",MEDIAN(IF((Vendas!$B$2:$B$3001=$A13)*(Vendas!$C$2:$C$3001=$B13)*(Vendas!$AK$2:$AK$3001="Validado")*ISNUMBER(Vendas!$S$2:$S$3001),Vendas!$S$2:$S$3001)))} | H13: =COUNTIFS(Vendas!$B$2:$B$3001,$A13,Vendas!$C$2:$C$3001,$B13,Vendas!$AK$2:$AK$3001,"Validado",Vendas!$T$2:$T$3001,"Valor*") | I13: =IF(C13=0,"-",_xlfn.MINIFS(Vendas!$Z$2:$Z$3001,Vendas!$B$2:$B$3001,$A13,Vendas!$C$2:$C$3001,$B13,Vendas!$AK$2:$AK$3001,"Validado")) | J13: =IF(C13=0,"-",_xlfn.MAXIFS(Vendas!$Z$2:$Z$3001,Vendas!$B$2:$B$3001,$A13,Vendas!$C$2:$C$3001,$B13,Vendas!$AK$2:$AK$3001,"Validado"))
A14: São Sebastião | B14: Porto Grande | C14: =COUNTIFS(Vendas!$B$2:$B$3001,$A14,Vendas!$C$2:$C$3001,$B14,Vendas!$AK$2:$AK$3001,"Validado") | D14: {=IF(C14=0,"-",MEDIAN(IF((Vendas!$B$2:$B$3001=$A14)*(Vendas!$C$2:$C$3001=$B14)*(Vendas!$AK$2:$AK$3001="Validado")*ISNUMBER(Vendas!$M$2:$M$3001),Vendas!$M$2:$M$3001)))} | E14: =IF(C14=0,"-",_xlfn.MINIFS(Vendas!$M$2:$M$3001,Vendas!$B$2:$B$3001,$A14,Vendas!$C$2:$C$3001,$B14,Vendas!$AK$2:$AK$3001,"Validado")) | F14: =IF(C14=0,"-",_xlfn.MAXIFS(Vendas!$M$2:$M$3001,Vendas!$B$2:$B$3001,$A14,Vendas!$C$2:$C$3001,$B14,Vendas!$AK$2:$AK$3001,"Validado")) | G14: {=IF(SUMPRODUCT((Vendas!$B$2:$B$3001=$A14)*(Vendas!$C$2:$C$3001=$B14)*(Vendas!$AK$2:$AK$3001="Validado")*ISNUMBER(Vendas!$S$2:$S$3001))=0,"-",MEDIAN(IF((Vendas!$B$2:$B$3001=$A14)*(Vendas!$C$2:$C$3001=$B14)*(Vendas!$AK$2:$AK$3001="Validado")*ISNUMBER(Vendas!$S$2:$S$3001),Vendas!$S$2:$S$3001)))} | H14: =COUNTIFS(Vendas!$B$2:$B$3001,$A14,Vendas!$C$2:$C$3001,$B14,Vendas!$AK$2:$AK$3001,"Validado",Vendas!$T$2:$T$3001,"Valor*") | I14: =IF(C14=0,"-",_xlfn.MINIFS(Vendas!$Z$2:$Z$3001,Vendas!$B$2:$B$3001,$A14,Vendas!$C$2:$C$3001,$B14,Vendas!$AK$2:$AK$3001,"Validado")) | J14: =IF(C14=0,"-",_xlfn.MAXIFS(Vendas!$Z$2:$Z$3001,Vendas!$B$2:$B$3001,$A14,Vendas!$C$2:$C$3001,$B14,Vendas!$AK$2:$AK$3001,"Validado"))
A15: São Sebastião | B15: Centro | C15: =COUNTIFS(Vendas!$B$2:$B$3001,$A15,Vendas!$C$2:$C$3001,$B15,Vendas!$AK$2:$AK$3001,"Validado") | D15: {=IF(C15=0,"-",MEDIAN(IF((Vendas!$B$2:$B$3001=$A15)*(Vendas!$C$2:$C$3001=$B15)*(Vendas!$AK$2:$AK$3001="Validado")*ISNUMBER(Vendas!$M$2:$M$3001),Vendas!$M$2:$M$3001)))} | E15: =IF(C15=0,"-",_xlfn.MINIFS(Vendas!$M$2:$M$3001,Vendas!$B$2:$B$3001,$A15,Vendas!$C$2:$C$3001,$B15,Vendas!$AK$2:$AK$3001,"Validado")) | F15: =IF(C15=0,"-",_xlfn.MAXIFS(Vendas!$M$2:$M$3001,Vendas!$B$2:$B$3001,$A15,Vendas!$C$2:$C$3001,$B15,Vendas!$AK$2:$AK$3001,"Validado")) | G15: {=IF(SUMPRODUCT((Vendas!$B$2:$B$3001=$A15)*(Vendas!$C$2:$C$3001=$B15)*(Vendas!$AK$2:$AK$3001="Validado")*ISNUMBER(Vendas!$S$2:$S$3001))=0,"-",MEDIAN(IF((Vendas!$B$2:$B$3001=$A15)*(Vendas!$C$2:$C$3001=$B15)*(Vendas!$AK$2:$AK$3001="Validado")*ISNUMBER(Vendas!$S$2:$S$3001),Vendas!$S$2:$S$3001)))} | H15: =COUNTIFS(Vendas!$B$2:$B$3001,$A15,Vendas!$C$2:$C$3001,$B15,Vendas!$AK$2:$AK$3001,"Validado",Vendas!$T$2:$T$3001,"Valor*") | I15: =IF(C15=0,"-",_xlfn.MINIFS(Vendas!$Z$2:$Z$3001,Vendas!$B$2:$B$3001,$A15,Vendas!$C$2:$C$3001,$B15,Vendas!$AK$2:$AK$3001,"Validado")) | J15: =IF(C15=0,"-",_xlfn.MAXIFS(Vendas!$Z$2:$Z$3001,Vendas!$B$2:$B$3001,$A15,Vendas!$C$2:$C$3001,$B15,Vendas!$AK$2:$AK$3001,"Validado"))
A16: São Sebastião | B16: Topolândia | C16: =COUNTIFS(Vendas!$B$2:$B$3001,$A16,Vendas!$C$2:$C$3001,$B16,Vendas!$AK$2:$AK$3001,"Validado") | D16: {=IF(C16=0,"-",MEDIAN(IF((Vendas!$B$2:$B$3001=$A16)*(Vendas!$C$2:$C$3001=$B16)*(Vendas!$AK$2:$AK$3001="Validado")*ISNUMBER(Vendas!$M$2:$M$3001),Vendas!$M$2:$M$3001)))} | E16: =IF(C16=0,"-",_xlfn.MINIFS(Vendas!$M$2:$M$3001,Vendas!$B$2:$B$3001,$A16,Vendas!$C$2:$C$3001,$B16,Vendas!$AK$2:$AK$3001,"Validado")) | F16: =IF(C16=0,"-",_xlfn.MAXIFS(Vendas!$M$2:$M$3001,Vendas!$B$2:$B$3001,$A16,Vendas!$C$2:$C$3001,$B16,Vendas!$AK$2:$AK$3001,"Validado")) | G16: {=IF(SUMPRODUCT((Vendas!$B$2:$B$3001=$A16)*(Vendas!$C$2:$C$3001=$B16)*(Vendas!$AK$2:$AK$3001="Validado")*ISNUMBER(Vendas!$S$2:$S$3001))=0,"-",MEDIAN(IF((Vendas!$B$2:$B$3001=$A16)*(Vendas!$C$2:$C$3001=$B16)*(Vendas!$AK$2:$AK$3001="Validado")*ISNUMBER(Vendas!$S$2:$S$3001),Vendas!$S$2:$S$3001)))} | H16: =COUNTIFS(Vendas!$B$2:$B$3001,$A16,Vendas!$C$2:$C$3001,$B16,Vendas!$AK$2:$AK$3001,"Validado",Vendas!$T$2:$T$3001,"Valor*") | I16: =IF(C16=0,"-",_xlfn.MINIFS(Vendas!$Z$2:$Z$3001,Vendas!$B$2:$B$3001,$A16,Vendas!$C$2:$C$3001,$B16,Vendas!$AK$2:$AK$3001,"Validado")) | J16: =IF(C16=0,"-",_xlfn.MAXIFS(Vendas!$Z$2:$Z$3001,Vendas!$B$2:$B$3001,$A16,Vendas!$C$2:$C$3001,$B16,Vendas!$AK$2:$AK$3001,"Validado"))
... A40: São Sebastião | B40: Engenho | C40: =COUNTIFS(Vendas!$B$2:$B$3001,$A40,Vendas!$C$2:$C$3001,$B40,Vendas!$AK$2:$AK$3001,"Validado") | D40: {=IF(C40=0,"-",MEDIAN(IF((Vendas!$B$2:$B$3001=$A40)*(Vendas!$C$2:$C$3001=$B40)*(Vendas!$AK$2:$AK$3001="Validado")*ISNUMBER(Vendas!$M$2:$M$3001),Vendas!$M$2:$M$3001)))} | E40: =IF(C40=0,"-",_xlfn.MINIFS(Vendas!$M$2:$M$3001,Vendas!$B$2:$B$3001,$A40,Vendas!$C$2:$C$3001,$B40,Vendas!$AK$2:$AK$3001,"Validado")) | F40: =IF(C40=0,"-",_xlfn.MAXIFS(Vendas!$M$2:$M$3001,Vendas!$B$2:$B$3001,$A40,Vendas!$C$2:$C$3001,$B40,Vendas!$AK$2:$AK$3001,"Validado")) | G40: {=IF(SUMPRODUCT((Vendas!$B$2:$B$3001=$A40)*(Vendas!$C$2:$C$3001=$B40)*(Vendas!$AK$2:$AK$3001="Validado")*ISNUMBER(Vendas!$S$2:$S$3001))=0,"-",MEDIAN(IF((Vendas!$B$2:$B$3001=$A40)*(Vendas!$C$2:$C$3001=$B40)*(Vendas!$AK$2:$AK$3001="Validado")*ISNUMBER(Vendas!$S$2:$S$3001),Vendas!$S$2:$S$3001)))} | H40: =COUNTIFS(Vendas!$B$2:$B$3001,$A40,Vendas!$C$2:$C$3001,$B40,Vendas!$AK$2:$AK$3001,"Validado",Vendas!$T$2:$T$3001,"Valor*") | I40: =IF(C40=0,"-",_xlfn.MINIFS(Vendas!$Z$2:$Z$3001,Vendas!$B$2:$B$3001,$A40,Vendas!$C$2:$C$3001,$B40,Vendas!$AK$2:$AK$3001,"Validado")) | J40: =IF(C40=0,"-",_xlfn.MAXIFS(Vendas!$Z$2:$Z$3001,Vendas!$B$2:$B$3001,$A40,Vendas!$C$2:$C$3001,$B40,Vendas!$AK$2:$AK$3001,"Validado"))
A41: São Sebastião | B41: TOTAL DA CIDADE | C41: =COUNTIFS(Vendas!$B$2:$B$3001,$A41,Vendas!$AK$2:$AK$3001,"Validado") | D41: {=IF(C41=0,"-",MEDIAN(IF((Vendas!$B$2:$B$3001=$A41)*(Vendas!$AK$2:$AK$3001="Validado")*ISNUMBER(Vendas!$M$2:$M$3001),Vendas!$M$2:$M$3001)))} | E41: =IF(C41=0,"-",_xlfn.MINIFS(Vendas!$M$2:$M$3001,Vendas!$B$2:$B$3001,$A41,Vendas!$AK$2:$AK$3001,"Validado")) | F41: =IF(C41=0,"-",_xlfn.MAXIFS(Vendas!$M$2:$M$3001,Vendas!$B$2:$B$3001,$A41,Vendas!$AK$2:$AK$3001,"Validado")) | G41: {=IF(SUMPRODUCT((Vendas!$B$2:$B$3001=$A41)*(Vendas!$AK$2:$AK$3001="Validado")*ISNUMBER(Vendas!$S$2:$S$3001))=0,"-",MEDIAN(IF((Vendas!$B$2:$B$3001=$A41)*(Vendas!$AK$2:$AK$3001="Validado")*ISNUMBER(Vendas!$S$2:$S$3001),Vendas!$S$2:$S$3001)))} | H41: =COUNTIFS(Vendas!$B$2:$B$3001,$A41,Vendas!$AK$2:$AK$3001,"Validado",Vendas!$T$2:$T$3001,"Valor*") | I41: =IF(C41=0,"-",_xlfn.MINIFS(Vendas!$Z$2:$Z$3001,Vendas!$B$2:$B$3001,$A41,Vendas!$AK$2:$AK$3001,"Validado")) | J41: =IF(C41=0,"-",_xlfn.MAXIFS(Vendas!$Z$2:$Z$3001,Vendas!$B$2:$B$3001,$A41,Vendas!$AK$2:$AK$3001,"Validado"))
A43: Bertioga | B43: Caiubura | C43: =COUNTIFS(Vendas!$B$2:$B$3001,$A43,Vendas!$C$2:$C$3001,$B43,Vendas!$AK$2:$AK$3001,"Validado") | D43: {=IF(C43=0,"-",MEDIAN(IF((Vendas!$B$2:$B$3001=$A43)*(Vendas!$C$2:$C$3001=$B43)*(Vendas!$AK$2:$AK$3001="Validado")*ISNUMBER(Vendas!$M$2:$M$3001),Vendas!$M$2:$M$3001)))} | E43: =IF(C43=0,"-",_xlfn.MINIFS(Vendas!$M$2:$M$3001,Vendas!$B$2:$B$3001,$A43,Vendas!$C$2:$C$3001,$B43,Vendas!$AK$2:$AK$3001,"Validado")) | F43: =IF(C43=0,"-",_xlfn.MAXIFS(Vendas!$M$2:$M$3001,Vendas!$B$2:$B$3001,$A43,Vendas!$C$2:$C$3001,$B43,Vendas!$AK$2:$AK$3001,"Validado")) | G43: {=IF(SUMPRODUCT((Vendas!$B$2:$B$3001=$A43)*(Vendas!$C$2:$C$3001=$B43)*(Vendas!$AK$2:$AK$3001="Validado")*ISNUMBER(Vendas!$S$2:$S$3001))=0,"-",MEDIAN(IF((Vendas!$B$2:$B$3001=$A43)*(Vendas!$C$2:$C$3001=$B43)*(Vendas!$AK$2:$AK$3001="Validado")*ISNUMBER(Vendas!$S$2:$S$3001),Vendas!$S$2:$S$3001)))} | H43: =COUNTIFS(Vendas!$B$2:$B$3001,$A43,Vendas!$C$2:$C$3001,$B43,Vendas!$AK$2:$AK$3001,"Validado",Vendas!$T$2:$T$3001,"Valor*") | I43: =IF(C43=0,"-",_xlfn.MINIFS(Vendas!$Z$2:$Z$3001,Vendas!$B$2:$B$3001,$A43,Vendas!$C$2:$C$3001,$B43,Vendas!$AK$2:$AK$3001,"Validado")) | J43: =IF(C43=0,"-",_xlfn.MAXIFS(Vendas!$Z$2:$Z$3001,Vendas!$B$2:$B$3001,$A43,Vendas!$C$2:$C$3001,$B43,Vendas!$AK$2:$AK$3001,"Validado"))
A44: Bertioga | B44: São João | C44: =COUNTIFS(Vendas!$B$2:$B$3001,$A44,Vendas!$C$2:$C$3001,$B44,Vendas!$AK$2:$AK$3001,"Validado") | D44: {=IF(C44=0,"-",MEDIAN(IF((Vendas!$B$2:$B$3001=$A44)*(Vendas!$C$2:$C$3001=$B44)*(Vendas!$AK$2:$AK$3001="Validado")*ISNUMBER(Vendas!$M$2:$M$3001),Vendas!$M$2:$M$3001)))} | E44: =IF(C44=0,"-",_xlfn.MINIFS(Vendas!$M$2:$M$3001,Vendas!$B$2:$B$3001,$A44,Vendas!$C$2:$C$3001,$B44,Vendas!$AK$2:$AK$3001,"Validado")) | F44: =IF(C44=0,"-",_xlfn.MAXIFS(Vendas!$M$2:$M$3001,Vendas!$B$2:$B$3001,$A44,Vendas!$C$2:$C$3001,$B44,Vendas!$AK$2:$AK$3001,"Validado")) | G44: {=IF(SUMPRODUCT((Vendas!$B$2:$B$3001=$A44)*(Vendas!$C$2:$C$3001=$B44)*(Vendas!$AK$2:$AK$3001="Validado")*ISNUMBER(Vendas!$S$2:$S$3001))=0,"-",MEDIAN(IF((Vendas!$B$2:$B$3001=$A44)*(Vendas!$C$2:$C$3001=$B44)*(Vendas!$AK$2:$AK$3001="Validado")*ISNUMBER(Vendas!$S$2:$S$3001),Vendas!$S$2:$S$3001)))} | H44: =COUNTIFS(Vendas!$B$2:$B$3001,$A44,Vendas!$C$2:$C$3001,$B44,Vendas!$AK$2:$AK$3001,"Validado",Vendas!$T$2:$T$3001,"Valor*") | I44: =IF(C44=0,"-",_xlfn.MINIFS(Vendas!$Z$2:$Z$3001,Vendas!$B$2:$B$3001,$A44,Vendas!$C$2:$C$3001,$B44,Vendas!$AK$2:$AK$3001,"Validado")) | J44: =IF(C44=0,"-",_xlfn.MAXIFS(Vendas!$Z$2:$Z$3001,Vendas!$B$2:$B$3001,$A44,Vendas!$C$2:$C$3001,$B44,Vendas!$AK$2:$AK$3001,"Validado"))
A45: Bertioga | B45: Centro | C45: =COUNTIFS(Vendas!$B$2:$B$3001,$A45,Vendas!$C$2:$C$3001,$B45,Vendas!$AK$2:$AK$3001,"Validado") | D45: {=IF(C45=0,"-",MEDIAN(IF((Vendas!$B$2:$B$3001=$A45)*(Vendas!$C$2:$C$3001=$B45)*(Vendas!$AK$2:$AK$3001="Validado")*ISNUMBER(Vendas!$M$2:$M$3001),Vendas!$M$2:$M$3001)))} | E45: =IF(C45=0,"-",_xlfn.MINIFS(Vendas!$M$2:$M$3001,Vendas!$B$2:$B$3001,$A45,Vendas!$C$2:$C$3001,$B45,Vendas!$AK$2:$AK$3001,"Validado")) | F45: =IF(C45=0,"-",_xlfn.MAXIFS(Vendas!$M$2:$M$3001,Vendas!$B$2:$B$3001,$A45,Vendas!$C$2:$C$3001,$B45,Vendas!$AK$2:$AK$3001,"Validado")) | G45: {=IF(SUMPRODUCT((Vendas!$B$2:$B$3001=$A45)*(Vendas!$C$2:$C$3001=$B45)*(Vendas!$AK$2:$AK$3001="Validado")*ISNUMBER(Vendas!$S$2:$S$3001))=0,"-",MEDIAN(IF((Vendas!$B$2:$B$3001=$A45)*(Vendas!$C$2:$C$3001=$B45)*(Vendas!$AK$2:$AK$3001="Validado")*ISNUMBER(Vendas!$S$2:$S$3001),Vendas!$S$2:$S$3001)))} | H45: =COUNTIFS(Vendas!$B$2:$B$3001,$A45,Vendas!$C$2:$C$3001,$B45,Vendas!$AK$2:$AK$3001,"Validado",Vendas!$T$2:$T$3001,"Valor*") | I45: =IF(C45=0,"-",_xlfn.MINIFS(Vendas!$Z$2:$Z$3001,Vendas!$B$2:$B$3001,$A45,Vendas!$C$2:$C$3001,$B45,Vendas!$AK$2:$AK$3001,"Validado")) | J45: =IF(C45=0,"-",_xlfn.MAXIFS(Vendas!$Z$2:$Z$3001,Vendas!$B$2:$B$3001,$A45,Vendas!$C$2:$C$3001,$B45,Vendas!$AK$2:$AK$3001,"Validado"))
A46: Bertioga | B46: Jardim Vicente de Carvalho | C46: =COUNTIFS(Vendas!$B$2:$B$3001,$A46,Vendas!$C$2:$C$3001,$B46,Vendas!$AK$2:$AK$3001,"Validado") | D46: {=IF(C46=0,"-",MEDIAN(IF((Vendas!$B$2:$B$3001=$A46)*(Vendas!$C$2:$C$3001=$B46)*(Vendas!$AK$2:$AK$3001="Validado")*ISNUMBER(Vendas!$M$2:$M$3001),Vendas!$M$2:$M$3001)))} | E46: =IF(C46=0,"-",_xlfn.MINIFS(Vendas!$M$2:$M$3001,Vendas!$B$2:$B$3001,$A46,Vendas!$C$2:$C$3001,$B46,Vendas!$AK$2:$AK$3001,"Validado")) | F46: =IF(C46=0,"-",_xlfn.MAXIFS(Vendas!$M$2:$M$3001,Vendas!$B$2:$B$3001,$A46,Vendas!$C$2:$C$3001,$B46,Vendas!$AK$2:$AK$3001,"Validado")) | G46: {=IF(SUMPRODUCT((Vendas!$B$2:$B$3001=$A46)*(Vendas!$C$2:$C$3001=$B46)*(Vendas!$AK$2:$AK$3001="Validado")*ISNUMBER(Vendas!$S$2:$S$3001))=0,"-",MEDIAN(IF((Vendas!$B$2:$B$3001=$A46)*(Vendas!$C$2:$C$3001=$B46)*(Vendas!$AK$2:$AK$3001="Validado")*ISNUMBER(Vendas!$S$2:$S$3001),Vendas!$S$2:$S$3001)))} | H46: =COUNTIFS(Vendas!$B$2:$B$3001,$A46,Vendas!$C$2:$C$3001,$B46,Vendas!$AK$2:$AK$3001,"Validado",Vendas!$T$2:$T$3001,"Valor*") | I46: =IF(C46=0,"-",_xlfn.MINIFS(Vendas!$Z$2:$Z$3001,Vendas!$B$2:$B$3001,$A46,Vendas!$C$2:$C$3001,$B46,Vendas!$AK$2:$AK$3001,"Validado")) | J46: =IF(C46=0,"-",_xlfn.MAXIFS(Vendas!$Z$2:$Z$3001,Vendas!$B$2:$B$3001,$A46,Vendas!$C$2:$C$3001,$B46,Vendas!$AK$2:$AK$3001,"Validado"))
A47: Bertioga | B47: Albatróz | C47: =COUNTIFS(Vendas!$B$2:$B$3001,$A47,Vendas!$C$2:$C$3001,$B47,Vendas!$AK$2:$AK$3001,"Validado") | D47: {=IF(C47=0,"-",MEDIAN(IF((Vendas!$B$2:$B$3001=$A47)*(Vendas!$C$2:$C$3001=$B47)*(Vendas!$AK$2:$AK$3001="Validado")*ISNUMBER(Vendas!$M$2:$M$3001),Vendas!$M$2:$M$3001)))} | E47: =IF(C47=0,"-",_xlfn.MINIFS(Vendas!$M$2:$M$3001,Vendas!$B$2:$B$3001,$A47,Vendas!$C$2:$C$3001,$B47,Vendas!$AK$2:$AK$3001,"Validado")) | F47: =IF(C47=0,"-",_xlfn.MAXIFS(Vendas!$M$2:$M$3001,Vendas!$B$2:$B$3001,$A47,Vendas!$C$2:$C$3001,$B47,Vendas!$AK$2:$AK$3001,"Validado")) | G47: {=IF(SUMPRODUCT((Vendas!$B$2:$B$3001=$A47)*(Vendas!$C$2:$C$3001=$B47)*(Vendas!$AK$2:$AK$3001="Validado")*ISNUMBER(Vendas!$S$2:$S$3001))=0,"-",MEDIAN(IF((Vendas!$B$2:$B$3001=$A47)*(Vendas!$C$2:$C$3001=$B47)*(Vendas!$AK$2:$AK$3001="Validado")*ISNUMBER(Vendas!$S$2:$S$3001),Vendas!$S$2:$S$3001)))} | H47: =COUNTIFS(Vendas!$B$2:$B$3001,$A47,Vendas!$C$2:$C$3001,$B47,Vendas!$AK$2:$AK$3001,"Validado",Vendas!$T$2:$T$3001,"Valor*") | I47: =IF(C47=0,"-",_xlfn.MINIFS(Vendas!$Z$2:$Z$3001,Vendas!$B$2:$B$3001,$A47,Vendas!$C$2:$C$3001,$B47,Vendas!$AK$2:$AK$3001,"Validado")) | J47: =IF(C47=0,"-",_xlfn.MAXIFS(Vendas!$Z$2:$Z$3001,Vendas!$B$2:$B$3001,$A47,Vendas!$C$2:$C$3001,$B47,Vendas!$AK$2:$AK$3001,"Validado"))
A48: Bertioga | B48: Maitinga | C48: =COUNTIFS(Vendas!$B$2:$B$3001,$A48,Vendas!$C$2:$C$3001,$B48,Vendas!$AK$2:$AK$3001,"Validado") | D48: {=IF(C48=0,"-",MEDIAN(IF((Vendas!$B$2:$B$3001=$A48)*(Vendas!$C$2:$C$3001=$B48)*(Vendas!$AK$2:$AK$3001="Validado")*ISNUMBER(Vendas!$M$2:$M$3001),Vendas!$M$2:$M$3001)))} | E48: =IF(C48=0,"-",_xlfn.MINIFS(Vendas!$M$2:$M$3001,Vendas!$B$2:$B$3001,$A48,Vendas!$C$2:$C$3001,$B48,Vendas!$AK$2:$AK$3001,"Validado")) | F48: =IF(C48=0,"-",_xlfn.MAXIFS(Vendas!$M$2:$M$3001,Vendas!$B$2:$B$3001,$A48,Vendas!$C$2:$C$3001,$B48,Vendas!$AK$2:$AK$3001,"Validado")) | G48: {=IF(SUMPRODUCT((Vendas!$B$2:$B$3001=$A48)*(Vendas!$C$2:$C$3001=$B48)*(Vendas!$AK$2:$AK$3001="Validado")*ISNUMBER(Vendas!$S$2:$S$3001))=0,"-",MEDIAN(IF((Vendas!$B$2:$B$3001=$A48)*(Vendas!$C$2:$C$3001=$B48)*(Vendas!$AK$2:$AK$3001="Validado")*ISNUMBER(Vendas!$S$2:$S$3001),Vendas!$S$2:$S$3001)))} | H48: =COUNTIFS(Vendas!$B$2:$B$3001,$A48,Vendas!$C$2:$C$3001,$B48,Vendas!$AK$2:$AK$3001,"Validado",Vendas!$T$2:$T$3001,"Valor*") | I48: =IF(C48=0,"-",_xlfn.MINIFS(Vendas!$Z$2:$Z$3001,Vendas!$B$2:$B$3001,$A48,Vendas!$C$2:$C$3001,$B48,Vendas!$AK$2:$AK$3001,"Validado")) | J48: =IF(C48=0,"-",_xlfn.MAXIFS(Vendas!$Z$2:$Z$3001,Vendas!$B$2:$B$3001,$A48,Vendas!$C$2:$C$3001,$B48,Vendas!$AK$2:$AK$3001,"Validado"))
A49: Bertioga | B49: Rio da Praia | C49: =COUNTIFS(Vendas!$B$2:$B$3001,$A49,Vendas!$C$2:$C$3001,$B49,Vendas!$AK$2:$AK$3001,"Validado") | D49: {=IF(C49=0,"-",MEDIAN(IF((Vendas!$B$2:$B$3001=$A49)*(Vendas!$C$2:$C$3001=$B49)*(Vendas!$AK$2:$AK$3001="Validado")*ISNUMBER(Vendas!$M$2:$M$3001),Vendas!$M$2:$M$3001)))} | E49: =IF(C49=0,"-",_xlfn.MINIFS(Vendas!$M$2:$M$3001,Vendas!$B$2:$B$3001,$A49,Vendas!$C$2:$C$3001,$B49,Vendas!$AK$2:$AK$3001,"Validado")) | F49: =IF(C49=0,"-",_xlfn.MAXIFS(Vendas!$M$2:$M$3001,Vendas!$B$2:$B$3001,$A49,Vendas!$C$2:$C$3001,$B49,Vendas!$AK$2:$AK$3001,"Validado")) | G49: {=IF(SUMPRODUCT((Vendas!$B$2:$B$3001=$A49)*(Vendas!$C$2:$C$3001=$B49)*(Vendas!$AK$2:$AK$3001="Validado")*ISNUMBER(Vendas!$S$2:$S$3001))=0,"-",MEDIAN(IF((Vendas!$B$2:$B$3001=$A49)*(Vendas!$C$2:$C$3001=$B49)*(Vendas!$AK$2:$AK$3001="Validado")*ISNUMBER(Vendas!$S$2:$S$3001),Vendas!$S$2:$S$3001)))} | H49: =COUNTIFS(Vendas!$B$2:$B$3001,$A49,Vendas!$C$2:$C$3001,$B49,Vendas!$AK$2:$AK$3001,"Validado",Vendas!$T$2:$T$3001,"Valor*") | I49: =IF(C49=0,"-",_xlfn.MINIFS(Vendas!$Z$2:$Z$3001,Vendas!$B$2:$B$3001,$A49,Vendas!$C$2:$C$3001,$B49,Vendas!$AK$2:$AK$3001,"Validado")) | J49: =IF(C49=0,"-",_xlfn.MAXIFS(Vendas!$Z$2:$Z$3001,Vendas!$B$2:$B$3001,$A49,Vendas!$C$2:$C$3001,$B49,Vendas!$AK$2:$AK$3001,"Validado"))
A50: Bertioga | B50: Buriqui Costa Nativa (Brasfanta) | C50: =COUNTIFS(Vendas!$B$2:$B$3001,$A50,Vendas!$C$2:$C$3001,$B50,Vendas!$AK$2:$AK$3001,"Validado") | D50: {=IF(C50=0,"-",MEDIAN(IF((Vendas!$B$2:$B$3001=$A50)*(Vendas!$C$2:$C$3001=$B50)*(Vendas!$AK$2:$AK$3001="Validado")*ISNUMBER(Vendas!$M$2:$M$3001),Vendas!$M$2:$M$3001)))} | E50: =IF(C50=0,"-",_xlfn.MINIFS(Vendas!$M$2:$M$3001,Vendas!$B$2:$B$3001,$A50,Vendas!$C$2:$C$3001,$B50,Vendas!$AK$2:$AK$3001,"Validado")) | F50: =IF(C50=0,"-",_xlfn.MAXIFS(Vendas!$M$2:$M$3001,Vendas!$B$2:$B$3001,$A50,Vendas!$C$2:$C$3001,$B50,Vendas!$AK$2:$AK$3001,"Validado")) | G50: {=IF(SUMPRODUCT((Vendas!$B$2:$B$3001=$A50)*(Vendas!$C$2:$C$3001=$B50)*(Vendas!$AK$2:$AK$3001="Validado")*ISNUMBER(Vendas!$S$2:$S$3001))=0,"-",MEDIAN(IF((Vendas!$B$2:$B$3001=$A50)*(Vendas!$C$2:$C$3001=$B50)*(Vendas!$AK$2:$AK$3001="Validado")*ISNUMBER(Vendas!$S$2:$S$3001),Vendas!$S$2:$S$3001)))} | H50: =COUNTIFS(Vendas!$B$2:$B$3001,$A50,Vendas!$C$2:$C$3001,$B50,Vendas!$AK$2:$AK$3001,"Validado",Vendas!$T$2:$T$3001,"Valor*") | I50: =IF(C50=0,"-",_xlfn.MINIFS(Vendas!$Z$2:$Z$3001,Vendas!$B$2:$B$3001,$A50,Vendas!$C$2:$C$3001,$B50,Vendas!$AK$2:$AK$3001,"Validado")) | J50: =IF(C50=0,"-",_xlfn.MAXIFS(Vendas!$Z$2:$Z$3001,Vendas!$B$2:$B$3001,$A50,Vendas!$C$2:$C$3001,$B50,Vendas!$AK$2:$AK$3001,"Validado"))
A51: Bertioga | B51: Jardim Raphael | C51: =COUNTIFS(Vendas!$B$2:$B$3001,$A51,Vendas!$C$2:$C$3001,$B51,Vendas!$AK$2:$AK$3001,"Validado") | D51: {=IF(C51=0,"-",MEDIAN(IF((Vendas!$B$2:$B$3001=$A51)*(Vendas!$C$2:$C$3001=$B51)*(Vendas!$AK$2:$AK$3001="Validado")*ISNUMBER(Vendas!$M$2:$M$3001),Vendas!$M$2:$M$3001)))} | E51: =IF(C51=0,"-",_xlfn.MINIFS(Vendas!$M$2:$M$3001,Vendas!$B$2:$B$3001,$A51,Vendas!$C$2:$C$3001,$B51,Vendas!$AK$2:$AK$3001,"Validado")) | F51: =IF(C51=0,"-",_xlfn.MAXIFS(Vendas!$M$2:$M$3001,Vendas!$B$2:$B$3001,$A51,Vendas!$C$2:$C$3001,$B51,Vendas!$AK$2:$AK$3001,"Validado")) | G51: {=IF(SUMPRODUCT((Vendas!$B$2:$B$3001=$A51)*(Vendas!$C$2:$C$3001=$B51)*(Vendas!$AK$2:$AK$3001="Validado")*ISNUMBER(Vendas!$S$2:$S$3001))=0,"-",MEDIAN(IF((Vendas!$B$2:$B$3001=$A51)*(Vendas!$C$2:$C$3001=$B51)*(Vendas!$AK$2:$AK$3001="Validado")*ISNUMBER(Vendas!$S$2:$S$3001),Vendas!$S$2:$S$3001)))} | H51: =COUNTIFS(Vendas!$B$2:$B$3001,$A51,Vendas!$C$2:$C$3001,$B51,Vendas!$AK$2:$AK$3001,"Validado",Vendas!$T$2:$T$3001,"Valor*") | I51: =IF(C51=0,"-",_xlfn.MINIFS(Vendas!$Z$2:$Z$3001,Vendas!$B$2:$B$3001,$A51,Vendas!$C$2:$C$3001,$B51,Vendas!$AK$2:$AK$3001,"Validado")) | J51: =IF(C51=0,"-",_xlfn.MAXIFS(Vendas!$Z$2:$Z$3001,Vendas!$B$2:$B$3001,$A51,Vendas!$C$2:$C$3001,$B51,Vendas!$AK$2:$AK$3001,"Validado"))
A52: Bertioga | B52: Bairro Chácaras | C52: =COUNTIFS(Vendas!$B$2:$B$3001,$A52,Vendas!$C$2:$C$3001,$B52,Vendas!$AK$2:$AK$3001,"Validado") | D52: {=IF(C52=0,"-",MEDIAN(IF((Vendas!$B$2:$B$3001=$A52)*(Vendas!$C$2:$C$3001=$B52)*(Vendas!$AK$2:$AK$3001="Validado")*ISNUMBER(Vendas!$M$2:$M$3001),Vendas!$M$2:$M$3001)))} | E52: =IF(C52=0,"-",_xlfn.MINIFS(Vendas!$M$2:$M$3001,Vendas!$B$2:$B$3001,$A52,Vendas!$C$2:$C$3001,$B52,Vendas!$AK$2:$AK$3001,"Validado")) | F52: =IF(C52=0,"-",_xlfn.MAXIFS(Vendas!$M$2:$M$3001,Vendas!$B$2:$B$3001,$A52,Vendas!$C$2:$C$3001,$B52,Vendas!$AK$2:$AK$3001,"Validado")) | G52: {=IF(SUMPRODUCT((Vendas!$B$2:$B$3001=$A52)*(Vendas!$C$2:$C$3001=$B52)*(Vendas!$AK$2:$AK$3001="Validado")*ISNUMBER(Vendas!$S$2:$S$3001))=0,"-",MEDIAN(IF((Vendas!$B$2:$B$3001=$A52)*(Vendas!$C$2:$C$3001=$B52)*(Vendas!$AK$2:$AK$3001="Validado")*ISNUMBER(Vendas!$S$2:$S$3001),Vendas!$S$2:$S$3001)))} | H52: =COUNTIFS(Vendas!$B$2:$B$3001,$A52,Vendas!$C$2:$C$3001,$B52,Vendas!$AK$2:$AK$3001,"Validado",Vendas!$T$2:$T$3001,"Valor*") | I52: =IF(C52=0,"-",_xlfn.MINIFS(Vendas!$Z$2:$Z$3001,Vendas!$B$2:$B$3001,$A52,Vendas!$C$2:$C$3001,$B52,Vendas!$AK$2:$AK$3001,"Validado")) | J52: =IF(C52=0,"-",_xlfn.MAXIFS(Vendas!$Z$2:$Z$3001,Vendas!$B$2:$B$3001,$A52,Vendas!$C$2:$C$3001,$B52,Vendas!$AK$2:$AK$3001,"Validado"))
A53: Bertioga | B53: Vista Linda | C53: =COUNTIFS(Vendas!$B$2:$B$3001,$A53,Vendas!$C$2:$C$3001,$B53,Vendas!$AK$2:$AK$3001,"Validado") | D53: {=IF(C53=0,"-",MEDIAN(IF((Vendas!$B$2:$B$3001=$A53)*(Vendas!$C$2:$C$3001=$B53)*(Vendas!$AK$2:$AK$3001="Validado")*ISNUMBER(Vendas!$M$2:$M$3001),Vendas!$M$2:$M$3001)))} | E53: =IF(C53=0,"-",_xlfn.MINIFS(Vendas!$M$2:$M$3001,Vendas!$B$2:$B$3001,$A53,Vendas!$C$2:$C$3001,$B53,Vendas!$AK$2:$AK$3001,"Validado")) | F53: =IF(C53=0,"-",_xlfn.MAXIFS(Vendas!$M$2:$M$3001,Vendas!$B$2:$B$3001,$A53,Vendas!$C$2:$C$3001,$B53,Vendas!$AK$2:$AK$3001,"Validado")) | G53: {=IF(SUMPRODUCT((Vendas!$B$2:$B$3001=$A53)*(Vendas!$C$2:$C$3001=$B53)*(Vendas!$AK$2:$AK$3001="Validado")*ISNUMBER(Vendas!$S$2:$S$3001))=0,"-",MEDIAN(IF((Vendas!$B$2:$B$3001=$A53)*(Vendas!$C$2:$C$3001=$B53)*(Vendas!$AK$2:$AK$3001="Validado")*ISNUMBER(Vendas!$S$2:$S$3001),Vendas!$S$2:$S$3001)))} | H53: =COUNTIFS(Vendas!$B$2:$B$3001,$A53,Vendas!$C$2:$C$3001,$B53,Vendas!$AK$2:$AK$3001,"Validado",Vendas!$T$2:$T$3001,"Valor*") | I53: =IF(C53=0,"-",_xlfn.MINIFS(Vendas!$Z$2:$Z$3001,Vendas!$B$2:$B$3001,$A53,Vendas!$C$2:$C$3001,$B53,Vendas!$AK$2:$AK$3001,"Validado")) | J53: =IF(C53=0,"-",_xlfn.MAXIFS(Vendas!$Z$2:$Z$3001,Vendas!$B$2:$B$3001,$A53,Vendas!$C$2:$C$3001,$B53,Vendas!$AK$2:$AK$3001,"Validado"))
A54: Bertioga | B54: Indaiá | C54: =COUNTIFS(Vendas!$B$2:$B$3001,$A54,Vendas!$C$2:$C$3001,$B54,Vendas!$AK$2:$AK$3001,"Validado") | D54: {=IF(C54=0,"-",MEDIAN(IF((Vendas!$B$2:$B$3001=$A54)*(Vendas!$C$2:$C$3001=$B54)*(Vendas!$AK$2:$AK$3001="Validado")*ISNUMBER(Vendas!$M$2:$M$3001),Vendas!$M$2:$M$3001)))} | E54: =IF(C54=0,"-",_xlfn.MINIFS(Vendas!$M$2:$M$3001,Vendas!$B$2:$B$3001,$A54,Vendas!$C$2:$C$3001,$B54,Vendas!$AK$2:$AK$3001,"Validado")) | F54: =IF(C54=0,"-",_xlfn.MAXIFS(Vendas!$M$2:$M$3001,Vendas!$B$2:$B$3001,$A54,Vendas!$C$2:$C$3001,$B54,Vendas!$AK$2:$AK$3001,"Validado")) | G54: {=IF(SUMPRODUCT((Vendas!$B$2:$B$3001=$A54)*(Vendas!$C$2:$C$3001=$B54)*(Vendas!$AK$2:$AK$3001="Validado")*ISNUMBER(Vendas!$S$2:$S$3001))=0,"-",MEDIAN(IF((Vendas!$B$2:$B$3001=$A54)*(Vendas!$C$2:$C$3001=$B54)*(Vendas!$AK$2:$AK$3001="Validado")*ISNUMBER(Vendas!$S$2:$S$3001),Vendas!$S$2:$S$3001)))} | H54: =COUNTIFS(Vendas!$B$2:$B$3001,$A54,Vendas!$C$2:$C$3001,$B54,Vendas!$AK$2:$AK$3001,"Validado",Vendas!$T$2:$T$3001,"Valor*") | I54: =IF(C54=0,"-",_xlfn.MINIFS(Vendas!$Z$2:$Z$3001,Vendas!$B$2:$B$3001,$A54,Vendas!$C$2:$C$3001,$B54,Vendas!$AK$2:$AK$3001,"Validado")) | J54: =IF(C54=0,"-",_xlfn.MAXIFS(Vendas!$Z$2:$Z$3001,Vendas!$B$2:$B$3001,$A54,Vendas!$C$2:$C$3001,$B54,Vendas!$AK$2:$AK$3001,"Validado"))
... A61: Bertioga | B61: T.I. (Terras Indígenas do Rio Silveiras) | C61: =COUNTIFS(Vendas!$B$2:$B$3001,$A61,Vendas!$C$2:$C$3001,$B61,Vendas!$AK$2:$AK$3001,"Validado") | D61: {=IF(C61=0,"-",MEDIAN(IF((Vendas!$B$2:$B$3001=$A61)*(Vendas!$C$2:$C$3001=$B61)*(Vendas!$AK$2:$AK$3001="Validado")*ISNUMBER(Vendas!$M$2:$M$3001),Vendas!$M$2:$M$3001)))} | E61: =IF(C61=0,"-",_xlfn.MINIFS(Vendas!$M$2:$M$3001,Vendas!$B$2:$B$3001,$A61,Vendas!$C$2:$C$3001,$B61,Vendas!$AK$2:$AK$3001,"Validado")) | F61: =IF(C61=0,"-",_xlfn.MAXIFS(Vendas!$M$2:$M$3001,Vendas!$B$2:$B$3001,$A61,Vendas!$C$2:$C$3001,$B61,Vendas!$AK$2:$AK$3001,"Validado")) | G61: {=IF(SUMPRODUCT((Vendas!$B$2:$B$3001=$A61)*(Vendas!$C$2:$C$3001=$B61)*(Vendas!$AK$2:$AK$3001="Validado")*ISNUMBER(Vendas!$S$2:$S$3001))=0,"-",MEDIAN(IF((Vendas!$B$2:$B$3001=$A61)*(Vendas!$C$2:$C$3001=$B61)*(Vendas!$AK$2:$AK$3001="Validado")*ISNUMBER(Vendas!$S$2:$S$3001),Vendas!$S$2:$S$3001)))} | H61: =COUNTIFS(Vendas!$B$2:$B$3001,$A61,Vendas!$C$2:$C$3001,$B61,Vendas!$AK$2:$AK$3001,"Validado",Vendas!$T$2:$T$3001,"Valor*") | I61: =IF(C61=0,"-",_xlfn.MINIFS(Vendas!$Z$2:$Z$3001,Vendas!$B$2:$B$3001,$A61,Vendas!$C$2:$C$3001,$B61,Vendas!$AK$2:$AK$3001,"Validado")) | J61: =IF(C61=0,"-",_xlfn.MAXIFS(Vendas!$Z$2:$Z$3001,Vendas!$B$2:$B$3001,$A61,Vendas!$C$2:$C$3001,$B61,Vendas!$AK$2:$AK$3001,"Validado"))
A62: Bertioga | B62: TOTAL DA CIDADE | C62: =COUNTIFS(Vendas!$B$2:$B$3001,$A62,Vendas!$AK$2:$AK$3001,"Validado") | D62: {=IF(C62=0,"-",MEDIAN(IF((Vendas!$B$2:$B$3001=$A62)*(Vendas!$AK$2:$AK$3001="Validado")*ISNUMBER(Vendas!$M$2:$M$3001),Vendas!$M$2:$M$3001)))} | E62: =IF(C62=0,"-",_xlfn.MINIFS(Vendas!$M$2:$M$3001,Vendas!$B$2:$B$3001,$A62,Vendas!$AK$2:$AK$3001,"Validado")) | F62: =IF(C62=0,"-",_xlfn.MAXIFS(Vendas!$M$2:$M$3001,Vendas!$B$2:$B$3001,$A62,Vendas!$AK$2:$AK$3001,"Validado")) | G62: {=IF(SUMPRODUCT((Vendas!$B$2:$B$3001=$A62)*(Vendas!$AK$2:$AK$3001="Validado")*ISNUMBER(Vendas!$S$2:$S$3001))=0,"-",MEDIAN(IF((Vendas!$B$2:$B$3001=$A62)*(Vendas!$AK$2:$AK$3001="Validado")*ISNUMBER(Vendas!$S$2:$S$3001),Vendas!$S$2:$S$3001)))} | H62: =COUNTIFS(Vendas!$B$2:$B$3001,$A62,Vendas!$AK$2:$AK$3001,"Validado",Vendas!$T$2:$T$3001,"Valor*") | I62: =IF(C62=0,"-",_xlfn.MINIFS(Vendas!$Z$2:$Z$3001,Vendas!$B$2:$B$3001,$A62,Vendas!$AK$2:$AK$3001,"Validado")) | J62: =IF(C62=0,"-",_xlfn.MAXIFS(Vendas!$Z$2:$Z$3001,Vendas!$B$2:$B$3001,$A62,Vendas!$AK$2:$AK$3001,"Validado"))
A65: Resumo por cidade e padrão
A66: Cidade | B66: Padrão | C66: Nº de vendas | D66: Valor mediano (R$) | E66: Menor valor (R$) | F66: Maior valor (R$) | G66: R$/m² mediano
A67: São Sebastião | B67: Baixo | C67: =COUNTIFS(Vendas!$B$2:$B$3001,$A67,Vendas!$J$2:$J$3001,$B67,Vendas!$AK$2:$AK$3001,"Validado") | D67: {=IF(C67=0,"-",MEDIAN(IF((Vendas!$B$2:$B$3001=$A67)*(Vendas!$J$2:$J$3001=$B67)*(Vendas!$AK$2:$AK$3001="Validado")*ISNUMBER(Vendas!$M$2:$M$3001),Vendas!$M$2:$M$3001)))} | E67: =IF(C67=0,"-",_xlfn.MINIFS(Vendas!$M$2:$M$3001,Vendas!$B$2:$B$3001,$A67,Vendas!$J$2:$J$3001,$B67,Vendas!$AK$2:$AK$3001,"Validado")) | F67: =IF(C67=0,"-",_xlfn.MAXIFS(Vendas!$M$2:$M$3001,Vendas!$B$2:$B$3001,$A67,Vendas!$J$2:$J$3001,$B67,Vendas!$AK$2:$AK$3001,"Validado")) | G67: {=IF(SUMPRODUCT((Vendas!$B$2:$B$3001=$A67)*(Vendas!$J$2:$J$3001=$B67)*(Vendas!$AK$2:$AK$3001="Validado")*ISNUMBER(Vendas!$S$2:$S$3001))=0,"-",MEDIAN(IF((Vendas!$B$2:$B$3001=$A67)*(Vendas!$J$2:$J$3001=$B67)*(Vendas!$AK$2:$AK$3001="Validado")*ISNUMBER(Vendas!$S$2:$S$3001),Vendas!$S$2:$S$3001)))}
A68: São Sebastião | B68: Normal | C68: =COUNTIFS(Vendas!$B$2:$B$3001,$A68,Vendas!$J$2:$J$3001,$B68,Vendas!$AK$2:$AK$3001,"Validado") | D68: {=IF(C68=0,"-",MEDIAN(IF((Vendas!$B$2:$B$3001=$A68)*(Vendas!$J$2:$J$3001=$B68)*(Vendas!$AK$2:$AK$3001="Validado")*ISNUMBER(Vendas!$M$2:$M$3001),Vendas!$M$2:$M$3001)))} | E68: =IF(C68=0,"-",_xlfn.MINIFS(Vendas!$M$2:$M$3001,Vendas!$B$2:$B$3001,$A68,Vendas!$J$2:$J$3001,$B68,Vendas!$AK$2:$AK$3001,"Validado")) | F68: =IF(C68=0,"-",_xlfn.MAXIFS(Vendas!$M$2:$M$3001,Vendas!$B$2:$B$3001,$A68,Vendas!$J$2:$J$3001,$B68,Vendas!$AK$2:$AK$3001,"Validado")) | G68: {=IF(SUMPRODUCT((Vendas!$B$2:$B$3001=$A68)*(Vendas!$J$2:$J$3001=$B68)*(Vendas!$AK$2:$AK$3001="Validado")*ISNUMBER(Vendas!$S$2:$S$3001))=0,"-",MEDIAN(IF((Vendas!$B$2:$B$3001=$A68)*(Vendas!$J$2:$J$3001=$B68)*(Vendas!$AK$2:$AK$3001="Validado")*ISNUMBER(Vendas!$S$2:$S$3001),Vendas!$S$2:$S$3001)))}
A69: São Sebastião | B69: Alto | C69: =COUNTIFS(Vendas!$B$2:$B$3001,$A69,Vendas!$J$2:$J$3001,$B69,Vendas!$AK$2:$AK$3001,"Validado") | D69: {=IF(C69=0,"-",MEDIAN(IF((Vendas!$B$2:$B$3001=$A69)*(Vendas!$J$2:$J$3001=$B69)*(Vendas!$AK$2:$AK$3001="Validado")*ISNUMBER(Vendas!$M$2:$M$3001),Vendas!$M$2:$M$3001)))} | E69: =IF(C69=0,"-",_xlfn.MINIFS(Vendas!$M$2:$M$3001,Vendas!$B$2:$B$3001,$A69,Vendas!$J$2:$J$3001,$B69,Vendas!$AK$2:$AK$3001,"Validado")) | F69: =IF(C69=0,"-",_xlfn.MAXIFS(Vendas!$M$2:$M$3001,Vendas!$B$2:$B$3001,$A69,Vendas!$J$2:$J$3001,$B69,Vendas!$AK$2:$AK$3001,"Validado")) | G69: {=IF(SUMPRODUCT((Vendas!$B$2:$B$3001=$A69)*(Vendas!$J$2:$J$3001=$B69)*(Vendas!$AK$2:$AK$3001="Validado")*ISNUMBER(Vendas!$S$2:$S$3001))=0,"-",MEDIAN(IF((Vendas!$B$2:$B$3001=$A69)*(Vendas!$J$2:$J$3001=$B69)*(Vendas!$AK$2:$AK$3001="Validado")*ISNUMBER(Vendas!$S$2:$S$3001),Vendas!$S$2:$S$3001)))}
A70: São Sebastião | B70: Não informado | C70: =COUNTIFS(Vendas!$B$2:$B$3001,$A70,Vendas!$J$2:$J$3001,$B70,Vendas!$AK$2:$AK$3001,"Validado") | D70: {=IF(C70=0,"-",MEDIAN(IF((Vendas!$B$2:$B$3001=$A70)*(Vendas!$J$2:$J$3001=$B70)*(Vendas!$AK$2:$AK$3001="Validado")*ISNUMBER(Vendas!$M$2:$M$3001),Vendas!$M$2:$M$3001)))} | E70: =IF(C70=0,"-",_xlfn.MINIFS(Vendas!$M$2:$M$3001,Vendas!$B$2:$B$3001,$A70,Vendas!$J$2:$J$3001,$B70,Vendas!$AK$2:$AK$3001,"Validado")) | F70: =IF(C70=0,"-",_xlfn.MAXIFS(Vendas!$M$2:$M$3001,Vendas!$B$2:$B$3001,$A70,Vendas!$J$2:$J$3001,$B70,Vendas!$AK$2:$AK$3001,"Validado")) | G70: {=IF(SUMPRODUCT((Vendas!$B$2:$B$3001=$A70)*(Vendas!$J$2:$J$3001=$B70)*(Vendas!$AK$2:$AK$3001="Validado")*ISNUMBER(Vendas!$S$2:$S$3001))=0,"-",MEDIAN(IF((Vendas!$B$2:$B$3001=$A70)*(Vendas!$J$2:$J$3001=$B70)*(Vendas!$AK$2:$AK$3001="Validado")*ISNUMBER(Vendas!$S$2:$S$3001),Vendas!$S$2:$S$3001)))}
A71: Bertioga | B71: Baixo | C71: =COUNTIFS(Vendas!$B$2:$B$3001,$A71,Vendas!$J$2:$J$3001,$B71,Vendas!$AK$2:$AK$3001,"Validado") | D71: {=IF(C71=0,"-",MEDIAN(IF((Vendas!$B$2:$B$3001=$A71)*(Vendas!$J$2:$J$3001=$B71)*(Vendas!$AK$2:$AK$3001="Validado")*ISNUMBER(Vendas!$M$2:$M$3001),Vendas!$M$2:$M$3001)))} | E71: =IF(C71=0,"-",_xlfn.MINIFS(Vendas!$M$2:$M$3001,Vendas!$B$2:$B$3001,$A71,Vendas!$J$2:$J$3001,$B71,Vendas!$AK$2:$AK$3001,"Validado")) | F71: =IF(C71=0,"-",_xlfn.MAXIFS(Vendas!$M$2:$M$3001,Vendas!$B$2:$B$3001,$A71,Vendas!$J$2:$J$3001,$B71,Vendas!$AK$2:$AK$3001,"Validado")) | G71: {=IF(SUMPRODUCT((Vendas!$B$2:$B$3001=$A71)*(Vendas!$J$2:$J$3001=$B71)*(Vendas!$AK$2:$AK$3001="Validado")*ISNUMBER(Vendas!$S$2:$S$3001))=0,"-",MEDIAN(IF((Vendas!$B$2:$B$3001=$A71)*(Vendas!$J$2:$J$3001=$B71)*(Vendas!$AK$2:$AK$3001="Validado")*ISNUMBER(Vendas!$S$2:$S$3001),Vendas!$S$2:$S$3001)))}
A72: Bertioga | B72: Normal | C72: =COUNTIFS(Vendas!$B$2:$B$3001,$A72,Vendas!$J$2:$J$3001,$B72,Vendas!$AK$2:$AK$3001,"Validado") | D72: {=IF(C72=0,"-",MEDIAN(IF((Vendas!$B$2:$B$3001=$A72)*(Vendas!$J$2:$J$3001=$B72)*(Vendas!$AK$2:$AK$3001="Validado")*ISNUMBER(Vendas!$M$2:$M$3001),Vendas!$M$2:$M$3001)))} | E72: =IF(C72=0,"-",_xlfn.MINIFS(Vendas!$M$2:$M$3001,Vendas!$B$2:$B$3001,$A72,Vendas!$J$2:$J$3001,$B72,Vendas!$AK$2:$AK$3001,"Validado")) | F72: =IF(C72=0,"-",_xlfn.MAXIFS(Vendas!$M$2:$M$3001,Vendas!$B$2:$B$3001,$A72,Vendas!$J$2:$J$3001,$B72,Vendas!$AK$2:$AK$3001,"Validado")) | G72: {=IF(SUMPRODUCT((Vendas!$B$2:$B$3001=$A72)*(Vendas!$J$2:$J$3001=$B72)*(Vendas!$AK$2:$AK$3001="Validado")*ISNUMBER(Vendas!$S$2:$S$3001))=0,"-",MEDIAN(IF((Vendas!$B$2:$B$3001=$A72)*(Vendas!$J$2:$J$3001=$B72)*(Vendas!$AK$2:$AK$3001="Validado")*ISNUMBER(Vendas!$S$2:$S$3001),Vendas!$S$2:$S$3001)))}
A73: Bertioga | B73: Alto | C73: =COUNTIFS(Vendas!$B$2:$B$3001,$A73,Vendas!$J$2:$J$3001,$B73,Vendas!$AK$2:$AK$3001,"Validado") | D73: {=IF(C73=0,"-",MEDIAN(IF((Vendas!$B$2:$B$3001=$A73)*(Vendas!$J$2:$J$3001=$B73)*(Vendas!$AK$2:$AK$3001="Validado")*ISNUMBER(Vendas!$M$2:$M$3001),Vendas!$M$2:$M$3001)))} | E73: =IF(C73=0,"-",_xlfn.MINIFS(Vendas!$M$2:$M$3001,Vendas!$B$2:$B$3001,$A73,Vendas!$J$2:$J$3001,$B73,Vendas!$AK$2:$AK$3001,"Validado")) | F73: =IF(C73=0,"-",_xlfn.MAXIFS(Vendas!$M$2:$M$3001,Vendas!$B$2:$B$3001,$A73,Vendas!$J$2:$J$3001,$B73,Vendas!$AK$2:$AK$3001,"Validado")) | G73: {=IF(SUMPRODUCT((Vendas!$B$2:$B$3001=$A73)*(Vendas!$J$2:$J$3001=$B73)*(Vendas!$AK$2:$AK$3001="Validado")*ISNUMBER(Vendas!$S$2:$S$3001))=0,"-",MEDIAN(IF((Vendas!$B$2:$B$3001=$A73)*(Vendas!$J$2:$J$3001=$B73)*(Vendas!$AK$2:$AK$3001="Validado")*ISNUMBER(Vendas!$S$2:$S$3001),Vendas!$S$2:$S$3001)))}
A74: Bertioga | B74: Não informado | C74: =COUNTIFS(Vendas!$B$2:$B$3001,$A74,Vendas!$J$2:$J$3001,$B74,Vendas!$AK$2:$AK$3001,"Validado") | D74: {=IF(C74=0,"-",MEDIAN(IF((Vendas!$B$2:$B$3001=$A74)*(Vendas!$J$2:$J$3001=$B74)*(Vendas!$AK$2:$AK$3001="Validado")*ISNUMBER(Vendas!$M$2:$M$3001),Vendas!$M$2:$M$3001)))} | E74: =IF(C74=0,"-",_xlfn.MINIFS(Vendas!$M$2:$M$3001,Vendas!$B$2:$B$3001,$A74,Vendas!$J$2:$J$3001,$B74,Vendas!$AK$2:$AK$3001,"Validado")) | F74: =IF(C74=0,"-",_xlfn.MAXIFS(Vendas!$M$2:$M$3001,Vendas!$B$2:$B$3001,$A74,Vendas!$J$2:$J$3001,$B74,Vendas!$AK$2:$AK$3001,"Validado")) | G74: {=IF(SUMPRODUCT((Vendas!$B$2:$B$3001=$A74)*(Vendas!$J$2:$J$3001=$B74)*(Vendas!$AK$2:$AK$3001="Validado")*ISNUMBER(Vendas!$S$2:$S$3001))=0,"-",MEDIAN(IF((Vendas!$B$2:$B$3001=$A74)*(Vendas!$J$2:$J$3001=$B74)*(Vendas!$AK$2:$AK$3001="Validado")*ISNUMBER(Vendas!$S$2:$S$3001),Vendas!$S$2:$S$3001)))}

Sheet Análise ITBI
A1: Análise de subdeclaração do valor de venda no ITBI
A2: Usa só vendas com Status = Validado. Nenhum número é estimado: cada indicador sai dos documentos lançados na aba Vendas. Recortes com menos vendas que a amostra mínima mostram 'n<mín'.
A4: Amostra mínima (n) | B4: 5
A5: Método e leitura: ver docs/analise_subdeclaracao_ITBI.md. Passe o mouse nos cabeçalhos para a definição de cada indicador.
A7: Por cidade
A8: Cidade | B8: Recorte | C8: Nº vendas validadas | D8: Nº c/ base ITBI | E8: Mediana Declarado ÷ Base ITBI | F8: % c/ base > declarado | G8: COD Declarado ÷ Base | H8: Nº c/ venal IPTU | I8: Mediana Declarado ÷ Venal | J8: % declarado ≤ venal | K8: Nº financiadas (c/ m²) | L8: Nº à vista (c/ m²) | M8: R$/m² mediano financiadas | N8: R$/m² mediano à vista | O8: Dif. à vista vs financiada | P8: Nº c/ valor leilão | Q8: Mediana Declarado ÷ Leilão | R8: % declarado < leilão | S8: Nº c/ valor financiado | T8: % financiado ≥ declarado
A9: São Sebastião | B9: Todas | C9: =SUMPRODUCT((Vendas!$AK$2:$AK$3001="Validado")*(Vendas!$B$2:$B$3001=$A9)) | D9: =SUMPRODUCT((Vendas!$AK$2:$AK$3001="Validado")*(Vendas!$B$2:$B$3001=$A9)*ISNUMBER(Vendas!$U$2:$U$3001)) | E9: {=IF(D9<AMOSTRA_MIN,"n<mín",MEDIAN(IF((Vendas!$AK$2:$AK$3001="Validado")*(Vendas!$B$2:$B$3001=$A9)*ISNUMBER(Vendas!$U$2:$U$3001),Vendas!$U$2:$U$3001)))} | F9: =IF(D9=0,"-",SUMPRODUCT((Vendas!$AK$2:$AK$3001="Validado")*(Vendas!$B$2:$B$3001=$A9)*ISNUMBER(Vendas!$U$2:$U$3001)*(Vendas!$U$2:$U$3001<1))/D9) | G9: {=IF(D9<AMOSTRA_MIN,"n<mín",100*AVERAGE(IF((Vendas!$AK$2:$AK$3001="Validado")*(Vendas!$B$2:$B$3001=$A9)*ISNUMBER(Vendas!$U$2:$U$3001),ABS(Vendas!$U$2:$U$3001-E9)))/E9)} | H9: =SUMPRODUCT((Vendas!$AK$2:$AK$3001="Validado")*(Vendas!$B$2:$B$3001=$A9)*ISNUMBER(Vendas!$V$2:$V$3001)) | I9: {=IF(H9<AMOSTRA_MIN,"n<mín",MEDIAN(IF((Vendas!$AK$2:$AK$3001="Validado")*(Vendas!$B$2:$B$3001=$A9)*ISNUMBER(Vendas!$V$2:$V$3001),Vendas!$V$2:$V$3001)))} | J9: =IF(H9=0,"-",SUMPRODUCT((Vendas!$AK$2:$AK$3001="Validado")*(Vendas!$B$2:$B$3001=$A9)*ISNUMBER(Vendas!$V$2:$V$3001)*(Vendas!$V$2:$V$3001<=1))/H9) | K9: =SUMPRODUCT((Vendas!$AK$2:$AK$3001="Validado")*(Vendas!$B$2:$B$3001=$A9)*(Vendas!$P$2:$P$3001="Financiado")*ISNUMBER(Vendas!$S$2:$S$3001)) | L9: =SUMPRODUCT((Vendas!$AK$2:$AK$3001="Validado")*(Vendas!$B$2:$B$3001=$A9)*(Vendas!$P$2:$P$3001="À vista")*ISNUMBER(Vendas!$S$2:$S$3001)) | M9: {=IF(K9<AMOSTRA_MIN,"n<mín",MEDIAN(IF((Vendas!$AK$2:$AK$3001="Validado")*(Vendas!$B$2:$B$3001=$A9)*(Vendas!$P$2:$P$3001="Financiado")*ISNUMBER(Vendas!$S$2:$S$3001),Vendas!$S$2:$S$3001)))} | N9: {=IF(L9<AMOSTRA_MIN,"n<mín",MEDIAN(IF((Vendas!$AK$2:$AK$3001="Validado")*(Vendas!$B$2:$B$3001=$A9)*(Vendas!$P$2:$P$3001="À vista")*ISNUMBER(Vendas!$S$2:$S$3001),Vendas!$S$2:$S$3001)))} | O9: =IF(OR(K9<AMOSTRA_MIN,L9<AMOSTRA_MIN),"n<mín",N9/M9-1) | P9: =SUMPRODUCT((Vendas!$AK$2:$AK$3001="Validado")*(Vendas!$B$2:$B$3001=$A9)*ISNUMBER(Vendas!$W$2:$W$3001)) | Q9: {=IF(P9<AMOSTRA_MIN,"n<mín",MEDIAN(IF((Vendas!$AK$2:$AK$3001="Validado")*(Vendas!$B$2:$B$3001=$A9)*ISNUMBER(Vendas!$W$2:$W$3001),Vendas!$W$2:$W$3001)))} | R9: =IF(P9=0,"-",SUMPRODUCT((Vendas!$AK$2:$AK$3001="Validado")*(Vendas!$B$2:$B$3001=$A9)*ISNUMBER(Vendas!$W$2:$W$3001)*(Vendas!$W$2:$W$3001<1))/P9) | S9: =SUMPRODUCT((Vendas!$AK$2:$AK$3001="Validado")*(Vendas!$B$2:$B$3001=$A9)*ISNUMBER(Vendas!$X$2:$X$3001)) | T9: =IF(S9=0,"-",SUMPRODUCT((Vendas!$AK$2:$AK$3001="Validado")*(Vendas!$B$2:$B$3001=$A9)*ISNUMBER(Vendas!$X$2:$X$3001)*(Vendas!$X$2:$X$3001>=1))/S9)
A10: Bertioga | B10: Todas | C10: =SUMPRODUCT((Vendas!$AK$2:$AK$3001="Validado")*(Vendas!$B$2:$B$3001=$A10)) | D10: =SUMPRODUCT((Vendas!$AK$2:$AK$3001="Validado")*(Vendas!$B$2:$B$3001=$A10)*ISNUMBER(Vendas!$U$2:$U$3001)) | E10: {=IF(D10<AMOSTRA_MIN,"n<mín",MEDIAN(IF((Vendas!$AK$2:$AK$3001="Validado")*(Vendas!$B$2:$B$3001=$A10)*ISNUMBER(Vendas!$U$2:$U$3001),Vendas!$U$2:$U$3001)))} | F10: =IF(D10=0,"-",SUMPRODUCT((Vendas!$AK$2:$AK$3001="Validado")*(Vendas!$B$2:$B$3001=$A10)*ISNUMBER(Vendas!$U$2:$U$3001)*(Vendas!$U$2:$U$3001<1))/D10) | G10: {=IF(D10<AMOSTRA_MIN,"n<mín",100*AVERAGE(IF((Vendas!$AK$2:$AK$3001="Validado")*(Vendas!$B$2:$B$3001=$A10)*ISNUMBER(Vendas!$U$2:$U$3001),ABS(Vendas!$U$2:$U$3001-E10)))/E10)} | H10: =SUMPRODUCT((Vendas!$AK$2:$AK$3001="Validado")*(Vendas!$B$2:$B$3001=$A10)*ISNUMBER(Vendas!$V$2:$V$3001)) | I10: {=IF(H10<AMOSTRA_MIN,"n<mín",MEDIAN(IF((Vendas!$AK$2:$AK$3001="Validado")*(Vendas!$B$2:$B$3001=$A10)*ISNUMBER(Vendas!$V$2:$V$3001),Vendas!$V$2:$V$3001)))} | J10: =IF(H10=0,"-",SUMPRODUCT((Vendas!$AK$2:$AK$3001="Validado")*(Vendas!$B$2:$B$3001=$A10)*ISNUMBER(Vendas!$V$2:$V$3001)*(Vendas!$V$2:$V$3001<=1))/H10) | K10: =SUMPRODUCT((Vendas!$AK$2:$AK$3001="Validado")*(Vendas!$B$2:$B$3001=$A10)*(Vendas!$P$2:$P$3001="Financiado")*ISNUMBER(Vendas!$S$2:$S$3001)) | L10: =SUMPRODUCT((Vendas!$AK$2:$AK$3001="Validado")*(Vendas!$B$2:$B$3001=$A10)*(Vendas!$P$2:$P$3001="À vista")*ISNUMBER(Vendas!$S$2:$S$3001)) | M10: {=IF(K10<AMOSTRA_MIN,"n<mín",MEDIAN(IF((Vendas!$AK$2:$AK$3001="Validado")*(Vendas!$B$2:$B$3001=$A10)*(Vendas!$P$2:$P$3001="Financiado")*ISNUMBER(Vendas!$S$2:$S$3001),Vendas!$S$2:$S$3001)))} | N10: {=IF(L10<AMOSTRA_MIN,"n<mín",MEDIAN(IF((Vendas!$AK$2:$AK$3001="Validado")*(Vendas!$B$2:$B$3001=$A10)*(Vendas!$P$2:$P$3001="À vista")*ISNUMBER(Vendas!$S$2:$S$3001),Vendas!$S$2:$S$3001)))} | O10: =IF(OR(K10<AMOSTRA_MIN,L10<AMOSTRA_MIN),"n<mín",N10/M10-1) | P10: =SUMPRODUCT((Vendas!$AK$2:$AK$3001="Validado")*(Vendas!$B$2:$B$3001=$A10)*ISNUMBER(Vendas!$W$2:$W$3001)) | Q10: {=IF(P10<AMOSTRA_MIN,"n<mín",MEDIAN(IF((Vendas!$AK$2:$AK$3001="Validado")*(Vendas!$B$2:$B$3001=$A10)*ISNUMBER(Vendas!$W$2:$W$3001),Vendas!$W$2:$W$3001)))} | R10: =IF(P10=0,"-",SUMPRODUCT((Vendas!$AK$2:$AK$3001="Validado")*(Vendas!$B$2:$B$3001=$A10)*ISNUMBER(Vendas!$W$2:$W$3001)*(Vendas!$W$2:$W$3001<1))/P10) | S10: =SUMPRODUCT((Vendas!$AK$2:$AK$3001="Validado")*(Vendas!$B$2:$B$3001=$A10)*ISNUMBER(Vendas!$X$2:$X$3001)) | T10: =IF(S10=0,"-",SUMPRODUCT((Vendas!$AK$2:$AK$3001="Validado")*(Vendas!$B$2:$B$3001=$A10)*ISNUMBER(Vendas!$X$2:$X$3001)*(Vendas!$X$2:$X$3001>=1))/S10)
A13: Por cidade e ano da escritura
A14: Cidade | B14: Ano | C14: Nº vendas validadas | D14: Nº c/ base ITBI | E14: Mediana Declarado ÷ Base ITBI | F14: % c/ base > declarado | G14: COD Declarado ÷ Base | H14: Nº c/ venal IPTU | I14: Mediana Declarado ÷ Venal | J14: % declarado ≤ venal | K14: Nº financiadas (c/ m²) | L14: Nº à vista (c/ m²) | M14: R$/m² mediano financiadas | N14: R$/m² mediano à vista | O14: Dif. à vista vs financiada | P14: Nº c/ valor leilão | Q14: Mediana Declarado ÷ Leilão | R14: % declarado < leilão | S14: Nº c/ valor financiado | T14: % financiado ≥ declarado
A15: São Sebastião | B15: 2021 | C15: =SUMPRODUCT((Vendas!$AK$2:$AK$3001="Validado")*(Vendas!$B$2:$B$3001=$A15)*(Vendas!$Y$2:$Y$3001=$B15)) | D15: =SUMPRODUCT((Vendas!$AK$2:$AK$3001="Validado")*(Vendas!$B$2:$B$3001=$A15)*(Vendas!$Y$2:$Y$3001=$B15)*ISNUMBER(Vendas!$U$2:$U$3001)) | E15: {=IF(D15<AMOSTRA_MIN,"n<mín",MEDIAN(IF((Vendas!$AK$2:$AK$3001="Validado")*(Vendas!$B$2:$B$3001=$A15)*(Vendas!$Y$2:$Y$3001=$B15)*ISNUMBER(Vendas!$U$2:$U$3001),Vendas!$U$2:$U$3001)))} | F15: =IF(D15=0,"-",SUMPRODUCT((Vendas!$AK$2:$AK$3001="Validado")*(Vendas!$B$2:$B$3001=$A15)*(Vendas!$Y$2:$Y$3001=$B15)*ISNUMBER(Vendas!$U$2:$U$3001)*(Vendas!$U$2:$U$3001<1))/D15) | G15: {=IF(D15<AMOSTRA_MIN,"n<mín",100*AVERAGE(IF((Vendas!$AK$2:$AK$3001="Validado")*(Vendas!$B$2:$B$3001=$A15)*(Vendas!$Y$2:$Y$3001=$B15)*ISNUMBER(Vendas!$U$2:$U$3001),ABS(Vendas!$U$2:$U$3001-E15)))/E15)} | H15: =SUMPRODUCT((Vendas!$AK$2:$AK$3001="Validado")*(Vendas!$B$2:$B$3001=$A15)*(Vendas!$Y$2:$Y$3001=$B15)*ISNUMBER(Vendas!$V$2:$V$3001)) | I15: {=IF(H15<AMOSTRA_MIN,"n<mín",MEDIAN(IF((Vendas!$AK$2:$AK$3001="Validado")*(Vendas!$B$2:$B$3001=$A15)*(Vendas!$Y$2:$Y$3001=$B15)*ISNUMBER(Vendas!$V$2:$V$3001),Vendas!$V$2:$V$3001)))} | J15: =IF(H15=0,"-",SUMPRODUCT((Vendas!$AK$2:$AK$3001="Validado")*(Vendas!$B$2:$B$3001=$A15)*(Vendas!$Y$2:$Y$3001=$B15)*ISNUMBER(Vendas!$V$2:$V$3001)*(Vendas!$V$2:$V$3001<=1))/H15) | K15: =SUMPRODUCT((Vendas!$AK$2:$AK$3001="Validado")*(Vendas!$B$2:$B$3001=$A15)*(Vendas!$Y$2:$Y$3001=$B15)*(Vendas!$P$2:$P$3001="Financiado")*ISNUMBER(Vendas!$S$2:$S$3001)) | L15: =SUMPRODUCT((Vendas!$AK$2:$AK$3001="Validado")*(Vendas!$B$2:$B$3001=$A15)*(Vendas!$Y$2:$Y$3001=$B15)*(Vendas!$P$2:$P$3001="À vista")*ISNUMBER(Vendas!$S$2:$S$3001)) | M15: {=IF(K15<AMOSTRA_MIN,"n<mín",MEDIAN(IF((Vendas!$AK$2:$AK$3001="Validado")*(Vendas!$B$2:$B$3001=$A15)*(Vendas!$Y$2:$Y$3001=$B15)*(Vendas!$P$2:$P$3001="Financiado")*ISNUMBER(Vendas!$S$2:$S$3001),Vendas!$S$2:$S$3001)))} | N15: {=IF(L15<AMOSTRA_MIN,"n<mín",MEDIAN(IF((Vendas!$AK$2:$AK$3001="Validado")*(Vendas!$B$2:$B$3001=$A15)*(Vendas!$Y$2:$Y$3001=$B15)*(Vendas!$P$2:$P$3001="À vista")*ISNUMBER(Vendas!$S$2:$S$3001),Vendas!$S$2:$S$3001)))} | O15: =IF(OR(K15<AMOSTRA_MIN,L15<AMOSTRA_MIN),"n<mín",N15/M15-1) | P15: =SUMPRODUCT((Vendas!$AK$2:$AK$3001="Validado")*(Vendas!$B$2:$B$3001=$A15)*(Vendas!$Y$2:$Y$3001=$B15)*ISNUMBER(Vendas!$W$2:$W$3001)) | Q15: {=IF(P15<AMOSTRA_MIN,"n<mín",MEDIAN(IF((Vendas!$AK$2:$AK$3001="Validado")*(Vendas!$B$2:$B$3001=$A15)*(Vendas!$Y$2:$Y$3001=$B15)*ISNUMBER(Vendas!$W$2:$W$3001),Vendas!$W$2:$W$3001)))} | R15: =IF(P15=0,"-",SUMPRODUCT((Vendas!$AK$2:$AK$3001="Validado")*(Vendas!$B$2:$B$3001=$A15)*(Vendas!$Y$2:$Y$3001=$B15)*ISNUMBER(Vendas!$W$2:$W$3001)*(Vendas!$W$2:$W$3001<1))/P15) | S15: =SUMPRODUCT((Vendas!$AK$2:$AK$3001="Validado")*(Vendas!$B$2:$B$3001=$A15)*(Vendas!$Y$2:$Y$3001=$B15)*ISNUMBER(Vendas!$X$2:$X$3001)) | T15: =IF(S15=0,"-",SUMPRODUCT((Vendas!$AK$2:$AK$3001="Validado")*(Vendas!$B$2:$B$3001=$A15)*(Vendas!$Y$2:$Y$3001=$B15)*ISNUMBER(Vendas!$X$2:$X$3001)*(Vendas!$X$2:$X$3001>=1))/S15)
A16: São Sebastião | B16: 2022 | C16: =SUMPRODUCT((Vendas!$AK$2:$AK$3001="Validado")*(Vendas!$B$2:$B$3001=$A16)*(Vendas!$Y$2:$Y$3001=$B16)) | D16: =SUMPRODUCT((Vendas!$AK$2:$AK$3001="Validado")*(Vendas!$B$2:$B$3001=$A16)*(Vendas!$Y$2:$Y$3001=$B16)*ISNUMBER(Vendas!$U$2:$U$3001)) | E16: {=IF(D16<AMOSTRA_MIN,"n<mín",MEDIAN(IF((Vendas!$AK$2:$AK$3001="Validado")*(Vendas!$B$2:$B$3001=$A16)*(Vendas!$Y$2:$Y$3001=$B16)*ISNUMBER(Vendas!$U$2:$U$3001),Vendas!$U$2:$U$3001)))} | F16: =IF(D16=0,"-",SUMPRODUCT((Vendas!$AK$2:$AK$3001="Validado")*(Vendas!$B$2:$B$3001=$A16)*(Vendas!$Y$2:$Y$3001=$B16)*ISNUMBER(Vendas!$U$2:$U$3001)*(Vendas!$U$2:$U$3001<1))/D16) | G16: {=IF(D16<AMOSTRA_MIN,"n<mín",100*AVERAGE(IF((Vendas!$AK$2:$AK$3001="Validado")*(Vendas!$B$2:$B$3001=$A16)*(Vendas!$Y$2:$Y$3001=$B16)*ISNUMBER(Vendas!$U$2:$U$3001),ABS(Vendas!$U$2:$U$3001-E16)))/E16)} | H16: =SUMPRODUCT((Vendas!$AK$2:$AK$3001="Validado")*(Vendas!$B$2:$B$3001=$A16)*(Vendas!$Y$2:$Y$3001=$B16)*ISNUMBER(Vendas!$V$2:$V$3001)) | I16: {=IF(H16<AMOSTRA_MIN,"n<mín",MEDIAN(IF((Vendas!$AK$2:$AK$3001="Validado")*(Vendas!$B$2:$B$3001=$A16)*(Vendas!$Y$2:$Y$3001=$B16)*ISNUMBER(Vendas!$V$2:$V$3001),Vendas!$V$2:$V$3001)))} | J16: =IF(H16=0,"-",SUMPRODUCT((Vendas!$AK$2:$AK$3001="Validado")*(Vendas!$B$2:$B$3001=$A16)*(Vendas!$Y$2:$Y$3001=$B16)*ISNUMBER(Vendas!$V$2:$V$3001)*(Vendas!$V$2:$V$3001<=1))/H16) | K16: =SUMPRODUCT((Vendas!$AK$2:$AK$3001="Validado")*(Vendas!$B$2:$B$3001=$A16)*(Vendas!$Y$2:$Y$3001=$B16)*(Vendas!$P$2:$P$3001="Financiado")*ISNUMBER(Vendas!$S$2:$S$3001)) | L16: =SUMPRODUCT((Vendas!$AK$2:$AK$3001="Validado")*(Vendas!$B$2:$B$3001=$A16)*(Vendas!$Y$2:$Y$3001=$B16)*(Vendas!$P$2:$P$3001="À vista")*ISNUMBER(Vendas!$S$2:$S$3001)) | M16: {=IF(K16<AMOSTRA_MIN,"n<mín",MEDIAN(IF((Vendas!$AK$2:$AK$3001="Validado")*(Vendas!$B$2:$B$3001=$A16)*(Vendas!$Y$2:$Y$3001=$B16)*(Vendas!$P$2:$P$3001="Financiado")*ISNUMBER(Vendas!$S$2:$S$3001),Vendas!$S$2:$S$3001)))} | N16: {=IF(L16<AMOSTRA_MIN,"n<mín",MEDIAN(IF((Vendas!$AK$2:$AK$3001="Validado")*(Vendas!$B$2:$B$3001=$A16)*(Vendas!$Y$2:$Y$3001=$B16)*(Vendas!$P$2:$P$3001="À vista")*ISNUMBER(Vendas!$S$2:$S$3001),Vendas!$S$2:$S$3001)))} | O16: =IF(OR(K16<AMOSTRA_MIN,L16<AMOSTRA_MIN),"n<mín",N16/M16-1) | P16: =SUMPRODUCT((Vendas!$AK$2:$AK$3001="Validado")*(Vendas!$B$2:$B$3001=$A16)*(Vendas!$Y$2:$Y$3001=$B16)*ISNUMBER(Vendas!$W$2:$W$3001)) | Q16: {=IF(P16<AMOSTRA_MIN,"n<mín",MEDIAN(IF((Vendas!$AK$2:$AK$3001="Validado")*(Vendas!$B$2:$B$3001=$A16)*(Vendas!$Y$2:$Y$3001=$B16)*ISNUMBER(Vendas!$W$2:$W$3001),Vendas!$W$2:$W$3001)))} | R16: =IF(P16=0,"-",SUMPRODUCT((Vendas!$AK$2:$AK$3001="Validado")*(Vendas!$B$2:$B$3001=$A16)*(Vendas!$Y$2:$Y$3001=$B16)*ISNUMBER(Vendas!$W$2:$W$3001)*(Vendas!$W$2:$W$3001<1))/P16) | S16: =SUMPRODUCT((Vendas!$AK$2:$AK$3001="Validado")*(Vendas!$B$2:$B$3001=$A16)*(Vendas!$Y$2:$Y$3001=$B16)*ISNUMBER(Vendas!$X$2:$X$3001)) | T16: =IF(S16=0,"-",SUMPRODUCT((Vendas!$AK$2:$AK$3001="Validado")*(Vendas!$B$2:$B$3001=$A16)*(Vendas!$Y$2:$Y$3001=$B16)*ISNUMBER(Vendas!$X$2:$X$3001)*(Vendas!$X$2:$X$3001>=1))/S16)
A17: São Sebastião | B17: 2023 | C17: =SUMPRODUCT((Vendas!$AK$2:$AK$3001="Validado")*(Vendas!$B$2:$B$3001=$A17)*(Vendas!$Y$2:$Y$3001=$B17)) | D17: =SUMPRODUCT((Vendas!$AK$2:$AK$3001="Validado")*(Vendas!$B$2:$B$3001=$A17)*(Vendas!$Y$2:$Y$3001=$B17)*ISNUMBER(Vendas!$U$2:$U$3001)) | E17: {=IF(D17<AMOSTRA_MIN,"n<mín",MEDIAN(IF((Vendas!$AK$2:$AK$3001="Validado")*(Vendas!$B$2:$B$3001=$A17)*(Vendas!$Y$2:$Y$3001=$B17)*ISNUMBER(Vendas!$U$2:$U$3001),Vendas!$U$2:$U$3001)))} | F17: =IF(D17=0,"-",SUMPRODUCT((Vendas!$AK$2:$AK$3001="Validado")*(Vendas!$B$2:$B$3001=$A17)*(Vendas!$Y$2:$Y$3001=$B17)*ISNUMBER(Vendas!$U$2:$U$3001)*(Vendas!$U$2:$U$3001<1))/D17) | G17: {=IF(D17<AMOSTRA_MIN,"n<mín",100*AVERAGE(IF((Vendas!$AK$2:$AK$3001="Validado")*(Vendas!$B$2:$B$3001=$A17)*(Vendas!$Y$2:$Y$3001=$B17)*ISNUMBER(Vendas!$U$2:$U$3001),ABS(Vendas!$U$2:$U$3001-E17)))/E17)} | H17: =SUMPRODUCT((Vendas!$AK$2:$AK$3001="Validado")*(Vendas!$B$2:$B$3001=$A17)*(Vendas!$Y$2:$Y$3001=$B17)*ISNUMBER(Vendas!$V$2:$V$3001)) | I17: {=IF(H17<AMOSTRA_MIN,"n<mín",MEDIAN(IF((Vendas!$AK$2:$AK$3001="Validado")*(Vendas!$B$2:$B$3001=$A17)*(Vendas!$Y$2:$Y$3001=$B17)*ISNUMBER(Vendas!$V$2:$V$3001),Vendas!$V$2:$V$3001)))} | J17: =IF(H17=0,"-",SUMPRODUCT((Vendas!$AK$2:$AK$3001="Validado")*(Vendas!$B$2:$B$3001=$A17)*(Vendas!$Y$2:$Y$3001=$B17)*ISNUMBER(Vendas!$V$2:$V$3001)*(Vendas!$V$2:$V$3001<=1))/H17) | K17: =SUMPRODUCT((Vendas!$AK$2:$AK$3001="Validado")*(Vendas!$B$2:$B$3001=$A17)*(Vendas!$Y$2:$Y$3001=$B17)*(Vendas!$P$2:$P$3001="Financiado")*ISNUMBER(Vendas!$S$2:$S$3001)) | L17: =SUMPRODUCT((Vendas!$AK$2:$AK$3001="Validado")*(Vendas!$B$2:$B$3001=$A17)*(Vendas!$Y$2:$Y$3001=$B17)*(Vendas!$P$2:$P$3001="À vista")*ISNUMBER(Vendas!$S$2:$S$3001)) | M17: {=IF(K17<AMOSTRA_MIN,"n<mín",MEDIAN(IF((Vendas!$AK$2:$AK$3001="Validado")*(Vendas!$B$2:$B$3001=$A17)*(Vendas!$Y$2:$Y$3001=$B17)*(Vendas!$P$2:$P$3001="Financiado")*ISNUMBER(Vendas!$S$2:$S$3001),Vendas!$S$2:$S$3001)))} | N17: {=IF(L17<AMOSTRA_MIN,"n<mín",MEDIAN(IF((Vendas!$AK$2:$AK$3001="Validado")*(Vendas!$B$2:$B$3001=$A17)*(Vendas!$Y$2:$Y$3001=$B17)*(Vendas!$P$2:$P$3001="À vista")*ISNUMBER(Vendas!$S$2:$S$3001),Vendas!$S$2:$S$3001)))} | O17: =IF(OR(K17<AMOSTRA_MIN,L17<AMOSTRA_MIN),"n<mín",N17/M17-1) | P17: =SUMPRODUCT((Vendas!$AK$2:$AK$3001="Validado")*(Vendas!$B$2:$B$3001=$A17)*(Vendas!$Y$2:$Y$3001=$B17)*ISNUMBER(Vendas!$W$2:$W$3001)) | Q17: {=IF(P17<AMOSTRA_MIN,"n<mín",MEDIAN(IF((Vendas!$AK$2:$AK$3001="Validado")*(Vendas!$B$2:$B$3001=$A17)*(Vendas!$Y$2:$Y$3001=$B17)*ISNUMBER(Vendas!$W$2:$W$3001),Vendas!$W$2:$W$3001)))} | R17: =IF(P17=0,"-",SUMPRODUCT((Vendas!$AK$2:$AK$3001="Validado")*(Vendas!$B$2:$B$3001=$A17)*(Vendas!$Y$2:$Y$3001=$B17)*ISNUMBER(Vendas!$W$2:$W$3001)*(Vendas!$W$2:$W$3001<1))/P17) | S17: =SUMPRODUCT((Vendas!$AK$2:$AK$3001="Validado")*(Vendas!$B$2:$B$3001=$A17)*(Vendas!$Y$2:$Y$3001=$B17)*ISNUMBER(Vendas!$X$2:$X$3001)) | T17: =IF(S17=0,"-",SUMPRODUCT((Vendas!$AK$2:$AK$3001="Validado")*(Vendas!$B$2:$B$3001=$A17)*(Vendas!$Y$2:$Y$3001=$B17)*ISNUMBER(Vendas!$X$2:$X$3001)*(Vendas!$X$2:$X$3001>=1))/S17)
A18: São Sebastião | B18: 2024 | C18: =SUMPRODUCT((Vendas!$AK$2:$AK$3001="Validado")*(Vendas!$B$2:$B$3001=$A18)*(Vendas!$Y$2:$Y$3001=$B18)) | D18: =SUMPRODUCT((Vendas!$AK$2:$AK$3001="Validado")*(Vendas!$B$2:$B$3001=$A18)*(Vendas!$Y$2:$Y$3001=$B18)*ISNUMBER(Vendas!$U$2:$U$3001)) | E18: {=IF(D18<AMOSTRA_MIN,"n<mín",MEDIAN(IF((Vendas!$AK$2:$AK$3001="Validado")*(Vendas!$B$2:$B$3001=$A18)*(Vendas!$Y$2:$Y$3001=$B18)*ISNUMBER(Vendas!$U$2:$U$3001),Vendas!$U$2:$U$3001)))} | F18: =IF(D18=0,"-",SUMPRODUCT((Vendas!$AK$2:$AK$3001="Validado")*(Vendas!$B$2:$B$3001=$A18)*(Vendas!$Y$2:$Y$3001=$B18)*ISNUMBER(Vendas!$U$2:$U$3001)*(Vendas!$U$2:$U$3001<1))/D18) | G18: {=IF(D18<AMOSTRA_MIN,"n<mín",100*AVERAGE(IF((Vendas!$AK$2:$AK$3001="Validado")*(Vendas!$B$2:$B$3001=$A18)*(Vendas!$Y$2:$Y$3001=$B18)*ISNUMBER(Vendas!$U$2:$U$3001),ABS(Vendas!$U$2:$U$3001-E18)))/E18)} | H18: =SUMPRODUCT((Vendas!$AK$2:$AK$3001="Validado")*(Vendas!$B$2:$B$3001=$A18)*(Vendas!$Y$2:$Y$3001=$B18)*ISNUMBER(Vendas!$V$2:$V$3001)) | I18: {=IF(H18<AMOSTRA_MIN,"n<mín",MEDIAN(IF((Vendas!$AK$2:$AK$3001="Validado")*(Vendas!$B$2:$B$3001=$A18)*(Vendas!$Y$2:$Y$3001=$B18)*ISNUMBER(Vendas!$V$2:$V$3001),Vendas!$V$2:$V$3001)))} | J18: =IF(H18=0,"-",SUMPRODUCT((Vendas!$AK$2:$AK$3001="Validado")*(Vendas!$B$2:$B$3001=$A18)*(Vendas!$Y$2:$Y$3001=$B18)*ISNUMBER(Vendas!$V$2:$V$3001)*(Vendas!$V$2:$V$3001<=1))/H18) | K18: =SUMPRODUCT((Vendas!$AK$2:$AK$3001="Validado")*(Vendas!$B$2:$B$3001=$A18)*(Vendas!$Y$2:$Y$3001=$B18)*(Vendas!$P$2:$P$3001="Financiado")*ISNUMBER(Vendas!$S$2:$S$3001)) | L18: =SUMPRODUCT((Vendas!$AK$2:$AK$3001="Validado")*(Vendas!$B$2:$B$3001=$A18)*(Vendas!$Y$2:$Y$3001=$B18)*(Vendas!$P$2:$P$3001="À vista")*ISNUMBER(Vendas!$S$2:$S$3001)) | M18: {=IF(K18<AMOSTRA_MIN,"n<mín",MEDIAN(IF((Vendas!$AK$2:$AK$3001="Validado")*(Vendas!$B$2:$B$3001=$A18)*(Vendas!$Y$2:$Y$3001=$B18)*(Vendas!$P$2:$P$3001="Financiado")*ISNUMBER(Vendas!$S$2:$S$3001),Vendas!$S$2:$S$3001)))} | N18: {=IF(L18<AMOSTRA_MIN,"n<mín",MEDIAN(IF((Vendas!$AK$2:$AK$3001="Validado")*(Vendas!$B$2:$B$3001=$A18)*(Vendas!$Y$2:$Y$3001=$B18)*(Vendas!$P$2:$P$3001="À vista")*ISNUMBER(Vendas!$S$2:$S$3001),Vendas!$S$2:$S$3001)))} | O18: =IF(OR(K18<AMOSTRA_MIN,L18<AMOSTRA_MIN),"n<mín",N18/M18-1) | P18: =SUMPRODUCT((Vendas!$AK$2:$AK$3001="Validado")*(Vendas!$B$2:$B$3001=$A18)*(Vendas!$Y$2:$Y$3001=$B18)*ISNUMBER(Vendas!$W$2:$W$3001)) | Q18: {=IF(P18<AMOSTRA_MIN,"n<mín",MEDIAN(IF((Vendas!$AK$2:$AK$3001="Validado")*(Vendas!$B$2:$B$3001=$A18)*(Vendas!$Y$2:$Y$3001=$B18)*ISNUMBER(Vendas!$W$2:$W$3001),Vendas!$W$2:$W$3001)))} | R18: =IF(P18=0,"-",SUMPRODUCT((Vendas!$AK$2:$AK$3001="Validado")*(Vendas!$B$2:$B$3001=$A18)*(Vendas!$Y$2:$Y$3001=$B18)*ISNUMBER(Vendas!$W$2:$W$3001)*(Vendas!$W$2:$W$3001<1))/P18) | S18: =SUMPRODUCT((Vendas!$AK$2:$AK$3001="Validado")*(Vendas!$B$2:$B$3001=$A18)*(Vendas!$Y$2:$Y$3001=$B18)*ISNUMBER(Vendas!$X$2:$X$3001)) | T18: =IF(S18=0,"-",SUMPRODUCT((Vendas!$AK$2:$AK$3001="Validado")*(Vendas!$B$2:$B$3001=$A18)*(Vendas!$Y$2:$Y$3001=$B18)*ISNUMBER(Vendas!$X$2:$X$3001)*(Vendas!$X$2:$X$3001>=1))/S18)
A19: São Sebastião | B19: 2025 | C19: =SUMPRODUCT((Vendas!$AK$2:$AK$3001="Validado")*(Vendas!$B$2:$B$3001=$A19)*(Vendas!$Y$2:$Y$3001=$B19)) | D19: =SUMPRODUCT((Vendas!$AK$2:$AK$3001="Validado")*(Vendas!$B$2:$B$3001=$A19)*(Vendas!$Y$2:$Y$3001=$B19)*ISNUMBER(Vendas!$U$2:$U$3001)) | E19: {=IF(D19<AMOSTRA_MIN,"n<mín",MEDIAN(IF((Vendas!$AK$2:$AK$3001="Validado")*(Vendas!$B$2:$B$3001=$A19)*(Vendas!$Y$2:$Y$3001=$B19)*ISNUMBER(Vendas!$U$2:$U$3001),Vendas!$U$2:$U$3001)))} | F19: =IF(D19=0,"-",SUMPRODUCT((Vendas!$AK$2:$AK$3001="Validado")*(Vendas!$B$2:$B$3001=$A19)*(Vendas!$Y$2:$Y$3001=$B19)*ISNUMBER(Vendas!$U$2:$U$3001)*(Vendas!$U$2:$U$3001<1))/D19) | G19: {=IF(D19<AMOSTRA_MIN,"n<mín",100*AVERAGE(IF((Vendas!$AK$2:$AK$3001="Validado")*(Vendas!$B$2:$B$3001=$A19)*(Vendas!$Y$2:$Y$3001=$B19)*ISNUMBER(Vendas!$U$2:$U$3001),ABS(Vendas!$U$2:$U$3001-E19)))/E19)} | H19: =SUMPRODUCT((Vendas!$AK$2:$AK$3001="Validado")*(Vendas!$B$2:$B$3001=$A19)*(Vendas!$Y$2:$Y$3001=$B19)*ISNUMBER(Vendas!$V$2:$V$3001)) | I19: {=IF(H19<AMOSTRA_MIN,"n<mín",MEDIAN(IF((Vendas!$AK$2:$AK$3001="Validado")*(Vendas!$B$2:$B$3001=$A19)*(Vendas!$Y$2:$Y$3001=$B19)*ISNUMBER(Vendas!$V$2:$V$3001),Vendas!$V$2:$V$3001)))} | J19: =IF(H19=0,"-",SUMPRODUCT((Vendas!$AK$2:$AK$3001="Validado")*(Vendas!$B$2:$B$3001=$A19)*(Vendas!$Y$2:$Y$3001=$B19)*ISNUMBER(Vendas!$V$2:$V$3001)*(Vendas!$V$2:$V$3001<=1))/H19) | K19: =SUMPRODUCT((Vendas!$AK$2:$AK$3001="Validado")*(Vendas!$B$2:$B$3001=$A19)*(Vendas!$Y$2:$Y$3001=$B19)*(Vendas!$P$2:$P$3001="Financiado")*ISNUMBER(Vendas!$S$2:$S$3001)) | L19: =SUMPRODUCT((Vendas!$AK$2:$AK$3001="Validado")*(Vendas!$B$2:$B$3001=$A19)*(Vendas!$Y$2:$Y$3001=$B19)*(Vendas!$P$2:$P$3001="À vista")*ISNUMBER(Vendas!$S$2:$S$3001)) | M19: {=IF(K19<AMOSTRA_MIN,"n<mín",MEDIAN(IF((Vendas!$AK$2:$AK$3001="Validado")*(Vendas!$B$2:$B$3001=$A19)*(Vendas!$Y$2:$Y$3001=$B19)*(Vendas!$P$2:$P$3001="Financiado")*ISNUMBER(Vendas!$S$2:$S$3001),Vendas!$S$2:$S$3001)))} | N19: {=IF(L19<AMOSTRA_MIN,"n<mín",MEDIAN(IF((Vendas!$AK$2:$AK$3001="Validado")*(Vendas!$B$2:$B$3001=$A19)*(Vendas!$Y$2:$Y$3001=$B19)*(Vendas!$P$2:$P$3001="À vista")*ISNUMBER(Vendas!$S$2:$S$3001),Vendas!$S$2:$S$3001)))} | O19: =IF(OR(K19<AMOSTRA_MIN,L19<AMOSTRA_MIN),"n<mín",N19/M19-1) | P19: =SUMPRODUCT((Vendas!$AK$2:$AK$3001="Validado")*(Vendas!$B$2:$B$3001=$A19)*(Vendas!$Y$2:$Y$3001=$B19)*ISNUMBER(Vendas!$W$2:$W$3001)) | Q19: {=IF(P19<AMOSTRA_MIN,"n<mín",MEDIAN(IF((Vendas!$AK$2:$AK$3001="Validado")*(Vendas!$B$2:$B$3001=$A19)*(Vendas!$Y$2:$Y$3001=$B19)*ISNUMBER(Vendas!$W$2:$W$3001),Vendas!$W$2:$W$3001)))} | R19: =IF(P19=0,"-",SUMPRODUCT((Vendas!$AK$2:$AK$3001="Validado")*(Vendas!$B$2:$B$3001=$A19)*(Vendas!$Y$2:$Y$3001=$B19)*ISNUMBER(Vendas!$W$2:$W$3001)*(Vendas!$W$2:$W$3001<1))/P19) | S19: =SUMPRODUCT((Vendas!$AK$2:$AK$3001="Validado")*(Vendas!$B$2:$B$3001=$A19)*(Vendas!$Y$2:$Y$3001=$B19)*ISNUMBER(Vendas!$X$2:$X$3001)) | T19: =IF(S19=0,"-",SUMPRODUCT((Vendas!$AK$2:$AK$3001="Validado")*(Vendas!$B$2:$B$3001=$A19)*(Vendas!$Y$2:$Y$3001=$B19)*ISNUMBER(Vendas!$X$2:$X$3001)*(Vendas!$X$2:$X$3001>=1))/S19)
A20: São Sebastião | B20: 2026 | C20: =SUMPRODUCT((Vendas!$AK$2:$AK$3001="Validado")*(Vendas!$B$2:$B$3001=$A20)*(Vendas!$Y$2:$Y$3001=$B20)) | D20: =SUMPRODUCT((Vendas!$AK$2:$AK$3001="Validado")*(Vendas!$B$2:$B$3001=$A20)*(Vendas!$Y$2:$Y$3001=$B20)*ISNUMBER(Vendas!$U$2:$U$3001)) | E20: {=IF(D20<AMOSTRA_MIN,"n<mín",MEDIAN(IF((Vendas!$AK$2:$AK$3001="Validado")*(Vendas!$B$2:$B$3001=$A20)*(Vendas!$Y$2:$Y$3001=$B20)*ISNUMBER(Vendas!$U$2:$U$3001),Vendas!$U$2:$U$3001)))} | F20: =IF(D20=0,"-",SUMPRODUCT((Vendas!$AK$2:$AK$3001="Validado")*(Vendas!$B$2:$B$3001=$A20)*(Vendas!$Y$2:$Y$3001=$B20)*ISNUMBER(Vendas!$U$2:$U$3001)*(Vendas!$U$2:$U$3001<1))/D20) | G20: {=IF(D20<AMOSTRA_MIN,"n<mín",100*AVERAGE(IF((Vendas!$AK$2:$AK$3001="Validado")*(Vendas!$B$2:$B$3001=$A20)*(Vendas!$Y$2:$Y$3001=$B20)*ISNUMBER(Vendas!$U$2:$U$3001),ABS(Vendas!$U$2:$U$3001-E20)))/E20)} | H20: =SUMPRODUCT((Vendas!$AK$2:$AK$3001="Validado")*(Vendas!$B$2:$B$3001=$A20)*(Vendas!$Y$2:$Y$3001=$B20)*ISNUMBER(Vendas!$V$2:$V$3001)) | I20: {=IF(H20<AMOSTRA_MIN,"n<mín",MEDIAN(IF((Vendas!$AK$2:$AK$3001="Validado")*(Vendas!$B$2:$B$3001=$A20)*(Vendas!$Y$2:$Y$3001=$B20)*ISNUMBER(Vendas!$V$2:$V$3001),Vendas!$V$2:$V$3001)))} | J20: =IF(H20=0,"-",SUMPRODUCT((Vendas!$AK$2:$AK$3001="Validado")*(Vendas!$B$2:$B$3001=$A20)*(Vendas!$Y$2:$Y$3001=$B20)*ISNUMBER(Vendas!$V$2:$V$3001)*(Vendas!$V$2:$V$3001<=1))/H20) | K20: =SUMPRODUCT((Vendas!$AK$2:$AK$3001="Validado")*(Vendas!$B$2:$B$3001=$A20)*(Vendas!$Y$2:$Y$3001=$B20)*(Vendas!$P$2:$P$3001="Financiado")*ISNUMBER(Vendas!$S$2:$S$3001)) | L20: =SUMPRODUCT((Vendas!$AK$2:$AK$3001="Validado")*(Vendas!$B$2:$B$3001=$A20)*(Vendas!$Y$2:$Y$3001=$B20)*(Vendas!$P$2:$P$3001="À vista")*ISNUMBER(Vendas!$S$2:$S$3001)) | M20: {=IF(K20<AMOSTRA_MIN,"n<mín",MEDIAN(IF((Vendas!$AK$2:$AK$3001="Validado")*(Vendas!$B$2:$B$3001=$A20)*(Vendas!$Y$2:$Y$3001=$B20)*(Vendas!$P$2:$P$3001="Financiado")*ISNUMBER(Vendas!$S$2:$S$3001),Vendas!$S$2:$S$3001)))} | N20: {=IF(L20<AMOSTRA_MIN,"n<mín",MEDIAN(IF((Vendas!$AK$2:$AK$3001="Validado")*(Vendas!$B$2:$B$3001=$A20)*(Vendas!$Y$2:$Y$3001=$B20)*(Vendas!$P$2:$P$3001="À vista")*ISNUMBER(Vendas!$S$2:$S$3001),Vendas!$S$2:$S$3001)))} | O20: =IF(OR(K20<AMOSTRA_MIN,L20<AMOSTRA_MIN),"n<mín",N20/M20-1) | P20: =SUMPRODUCT((Vendas!$AK$2:$AK$3001="Validado")*(Vendas!$B$2:$B$3001=$A20)*(Vendas!$Y$2:$Y$3001=$B20)*ISNUMBER(Vendas!$W$2:$W$3001)) | Q20: {=IF(P20<AMOSTRA_MIN,"n<mín",MEDIAN(IF((Vendas!$AK$2:$AK$3001="Validado")*(Vendas!$B$2:$B$3001=$A20)*(Vendas!$Y$2:$Y$3001=$B20)*ISNUMBER(Vendas!$W$2:$W$3001),Vendas!$W$2:$W$3001)))} | R20: =IF(P20=0,"-",SUMPRODUCT((Vendas!$AK$2:$AK$3001="Validado")*(Vendas!$B$2:$B$3001=$A20)*(Vendas!$Y$2:$Y$3001=$B20)*ISNUMBER(Vendas!$W$2:$W$3001)*(Vendas!$W$2:$W$3001<1))/P20) | S20: =SUMPRODUCT((Vendas!$AK$2:$AK$3001="Validado")*(Vendas!$B$2:$B$3001=$A20)*(Vendas!$Y$2:$Y$3001=$B20)*ISNUMBER(Vendas!$X$2:$X$3001)) | T20: =IF(S20=0,"-",SUMPRODUCT((Vendas!$AK$2:$AK$3001="Validado")*(Vendas!$B$2:$B$3001=$A20)*(Vendas!$Y$2:$Y$3001=$B20)*ISNUMBER(Vendas!$X$2:$X$3001)*(Vendas!$X$2:$X$3001>=1))/S20)
A21: Bertioga | B21: 2021 | C21: =SUMPRODUCT((Vendas!$AK$2:$AK$3001="Validado")*(Vendas!$B$2:$B$3001=$A21)*(Vendas!$Y$2:$Y$3001=$B21)) | D21: =SUMPRODUCT((Vendas!$AK$2:$AK$3001="Validado")*(Vendas!$B$2:$B$3001=$A21)*(Vendas!$Y$2:$Y$3001=$B21)*ISNUMBER(Vendas!$U$2:$U$3001)) | E21: {=IF(D21<AMOSTRA_MIN,"n<mín",MEDIAN(IF((Vendas!$AK$2:$AK$3001="Validado")*(Vendas!$B$2:$B$3001=$A21)*(Vendas!$Y$2:$Y$3001=$B21)*ISNUMBER(Vendas!$U$2:$U$3001),Vendas!$U$2:$U$3001)))} | F21: =IF(D21=0,"-",SUMPRODUCT((Vendas!$AK$2:$AK$3001="Validado")*(Vendas!$B$2:$B$3001=$A21)*(Vendas!$Y$2:$Y$3001=$B21)*ISNUMBER(Vendas!$U$2:$U$3001)*(Vendas!$U$2:$U$3001<1))/D21) | G21: {=IF(D21<AMOSTRA_MIN,"n<mín",100*AVERAGE(IF((Vendas!$AK$2:$AK$3001="Validado")*(Vendas!$B$2:$B$3001=$A21)*(Vendas!$Y$2:$Y$3001=$B21)*ISNUMBER(Vendas!$U$2:$U$3001),ABS(Vendas!$U$2:$U$3001-E21)))/E21)} | H21: =SUMPRODUCT((Vendas!$AK$2:$AK$3001="Validado")*(Vendas!$B$2:$B$3001=$A21)*(Vendas!$Y$2:$Y$3001=$B21)*ISNUMBER(Vendas!$V$2:$V$3001)) | I21: {=IF(H21<AMOSTRA_MIN,"n<mín",MEDIAN(IF((Vendas!$AK$2:$AK$3001="Validado")*(Vendas!$B$2:$B$3001=$A21)*(Vendas!$Y$2:$Y$3001=$B21)*ISNUMBER(Vendas!$V$2:$V$3001),Vendas!$V$2:$V$3001)))} | J21: =IF(H21=0,"-",SUMPRODUCT((Vendas!$AK$2:$AK$3001="Validado")*(Vendas!$B$2:$B$3001=$A21)*(Vendas!$Y$2:$Y$3001=$B21)*ISNUMBER(Vendas!$V$2:$V$3001)*(Vendas!$V$2:$V$3001<=1))/H21) | K21: =SUMPRODUCT((Vendas!$AK$2:$AK$3001="Validado")*(Vendas!$B$2:$B$3001=$A21)*(Vendas!$Y$2:$Y$3001=$B21)*(Vendas!$P$2:$P$3001="Financiado")*ISNUMBER(Vendas!$S$2:$S$3001)) | L21: =SUMPRODUCT((Vendas!$AK$2:$AK$3001="Validado")*(Vendas!$B$2:$B$3001=$A21)*(Vendas!$Y$2:$Y$3001=$B21)*(Vendas!$P$2:$P$3001="À vista")*ISNUMBER(Vendas!$S$2:$S$3001)) | M21: {=IF(K21<AMOSTRA_MIN,"n<mín",MEDIAN(IF((Vendas!$AK$2:$AK$3001="Validado")*(Vendas!$B$2:$B$3001=$A21)*(Vendas!$Y$2:$Y$3001=$B21)*(Vendas!$P$2:$P$3001="Financiado")*ISNUMBER(Vendas!$S$2:$S$3001),Vendas!$S$2:$S$3001)))} | N21: {=IF(L21<AMOSTRA_MIN,"n<mín",MEDIAN(IF((Vendas!$AK$2:$AK$3001="Validado")*(Vendas!$B$2:$B$3001=$A21)*(Vendas!$Y$2:$Y$3001=$B21)*(Vendas!$P$2:$P$3001="À vista")*ISNUMBER(Vendas!$S$2:$S$3001),Vendas!$S$2:$S$3001)))} | O21: =IF(OR(K21<AMOSTRA_MIN,L21<AMOSTRA_MIN),"n<mín",N21/M21-1) | P21: =SUMPRODUCT((Vendas!$AK$2:$AK$3001="Validado")*(Vendas!$B$2:$B$3001=$A21)*(Vendas!$Y$2:$Y$3001=$B21)*ISNUMBER(Vendas!$W$2:$W$3001)) | Q21: {=IF(P21<AMOSTRA_MIN,"n<mín",MEDIAN(IF((Vendas!$AK$2:$AK$3001="Validado")*(Vendas!$B$2:$B$3001=$A21)*(Vendas!$Y$2:$Y$3001=$B21)*ISNUMBER(Vendas!$W$2:$W$3001),Vendas!$W$2:$W$3001)))} | R21: =IF(P21=0,"-",SUMPRODUCT((Vendas!$AK$2:$AK$3001="Validado")*(Vendas!$B$2:$B$3001=$A21)*(Vendas!$Y$2:$Y$3001=$B21)*ISNUMBER(Vendas!$W$2:$W$3001)*(Vendas!$W$2:$W$3001<1))/P21) | S21: =SUMPRODUCT((Vendas!$AK$2:$AK$3001="Validado")*(Vendas!$B$2:$B$3001=$A21)*(Vendas!$Y$2:$Y$3001=$B21)*ISNUMBER(Vendas!$X$2:$X$3001)) | T21: =IF(S21=0,"-",SUMPRODUCT((Vendas!$AK$2:$AK$3001="Validado")*(Vendas!$B$2:$B$3001=$A21)*(Vendas!$Y$2:$Y$3001=$B21)*ISNUMBER(Vendas!$X$2:$X$3001)*(Vendas!$X$2:$X$3001>=1))/S21)
A22: Bertioga | B22: 2022 | C22: =SUMPRODUCT((Vendas!$AK$2:$AK$3001="Validado")*(Vendas!$B$2:$B$3001=$A22)*(Vendas!$Y$2:$Y$3001=$B22)) | D22: =SUMPRODUCT((Vendas!$AK$2:$AK$3001="Validado")*(Vendas!$B$2:$B$3001=$A22)*(Vendas!$Y$2:$Y$3001=$B22)*ISNUMBER(Vendas!$U$2:$U$3001)) | E22: {=IF(D22<AMOSTRA_MIN,"n<mín",MEDIAN(IF((Vendas!$AK$2:$AK$3001="Validado")*(Vendas!$B$2:$B$3001=$A22)*(Vendas!$Y$2:$Y$3001=$B22)*ISNUMBER(Vendas!$U$2:$U$3001),Vendas!$U$2:$U$3001)))} | F22: =IF(D22=0,"-",SUMPRODUCT((Vendas!$AK$2:$AK$3001="Validado")*(Vendas!$B$2:$B$3001=$A22)*(Vendas!$Y$2:$Y$3001=$B22)*ISNUMBER(Vendas!$U$2:$U$3001)*(Vendas!$U$2:$U$3001<1))/D22) | G22: {=IF(D22<AMOSTRA_MIN,"n<mín",100*AVERAGE(IF((Vendas!$AK$2:$AK$3001="Validado")*(Vendas!$B$2:$B$3001=$A22)*(Vendas!$Y$2:$Y$3001=$B22)*ISNUMBER(Vendas!$U$2:$U$3001),ABS(Vendas!$U$2:$U$3001-E22)))/E22)} | H22: =SUMPRODUCT((Vendas!$AK$2:$AK$3001="Validado")*(Vendas!$B$2:$B$3001=$A22)*(Vendas!$Y$2:$Y$3001=$B22)*ISNUMBER(Vendas!$V$2:$V$3001)) | I22: {=IF(H22<AMOSTRA_MIN,"n<mín",MEDIAN(IF((Vendas!$AK$2:$AK$3001="Validado")*(Vendas!$B$2:$B$3001=$A22)*(Vendas!$Y$2:$Y$3001=$B22)*ISNUMBER(Vendas!$V$2:$V$3001),Vendas!$V$2:$V$3001)))} | J22: =IF(H22=0,"-",SUMPRODUCT((Vendas!$AK$2:$AK$3001="Validado")*(Vendas!$B$2:$B$3001=$A22)*(Vendas!$Y$2:$Y$3001=$B22)*ISNUMBER(Vendas!$V$2:$V$3001)*(Vendas!$V$2:$V$3001<=1))/H22) | K22: =SUMPRODUCT((Vendas!$AK$2:$AK$3001="Validado")*(Vendas!$B$2:$B$3001=$A22)*(Vendas!$Y$2:$Y$3001=$B22)*(Vendas!$P$2:$P$3001="Financiado")*ISNUMBER(Vendas!$S$2:$S$3001)) | L22: =SUMPRODUCT((Vendas!$AK$2:$AK$3001="Validado")*(Vendas!$B$2:$B$3001=$A22)*(Vendas!$Y$2:$Y$3001=$B22)*(Vendas!$P$2:$P$3001="À vista")*ISNUMBER(Vendas!$S$2:$S$3001)) | M22: {=IF(K22<AMOSTRA_MIN,"n<mín",MEDIAN(IF((Vendas!$AK$2:$AK$3001="Validado")*(Vendas!$B$2:$B$3001=$A22)*(Vendas!$Y$2:$Y$3001=$B22)*(Vendas!$P$2:$P$3001="Financiado")*ISNUMBER(Vendas!$S$2:$S$3001),Vendas!$S$2:$S$3001)))} | N22: {=IF(L22<AMOSTRA_MIN,"n<mín",MEDIAN(IF((Vendas!$AK$2:$AK$3001="Validado")*(Vendas!$B$2:$B$3001=$A22)*(Vendas!$Y$2:$Y$3001=$B22)*(Vendas!$P$2:$P$3001="À vista")*ISNUMBER(Vendas!$S$2:$S$3001),Vendas!$S$2:$S$3001)))} | O22: =IF(OR(K22<AMOSTRA_MIN,L22<AMOSTRA_MIN),"n<mín",N22/M22-1) | P22: =SUMPRODUCT((Vendas!$AK$2:$AK$3001="Validado")*(Vendas!$B$2:$B$3001=$A22)*(Vendas!$Y$2:$Y$3001=$B22)*ISNUMBER(Vendas!$W$2:$W$3001)) | Q22: {=IF(P22<AMOSTRA_MIN,"n<mín",MEDIAN(IF((Vendas!$AK$2:$AK$3001="Validado")*(Vendas!$B$2:$B$3001=$A22)*(Vendas!$Y$2:$Y$3001=$B22)*ISNUMBER(Vendas!$W$2:$W$3001),Vendas!$W$2:$W$3001)))} | R22: =IF(P22=0,"-",SUMPRODUCT((Vendas!$AK$2:$AK$3001="Validado")*(Vendas!$B$2:$B$3001=$A22)*(Vendas!$Y$2:$Y$3001=$B22)*ISNUMBER(Vendas!$W$2:$W$3001)*(Vendas!$W$2:$W$3001<1))/P22) | S22: =SUMPRODUCT((Vendas!$AK$2:$AK$3001="Validado")*(Vendas!$B$2:$B$3001=$A22)*(Vendas!$Y$2:$Y$3001=$B22)*ISNUMBER(Vendas!$X$2:$X$3001)) | T22: =IF(S22=0,"-",SUMPRODUCT((Vendas!$AK$2:$AK$3001="Validado")*(Vendas!$B$2:$B$3001=$A22)*(Vendas!$Y$2:$Y$3001=$B22)*ISNUMBER(Vendas!$X$2:$X$3001)*(Vendas!$X$2:$X$3001>=1))/S22)
A23: Bertioga | B23: 2023 | C23: =SUMPRODUCT((Vendas!$AK$2:$AK$3001="Validado")*(Vendas!$B$2:$B$3001=$A23)*(Vendas!$Y$2:$Y$3001=$B23)) | D23: =SUMPRODUCT((Vendas!$AK$2:$AK$3001="Validado")*(Vendas!$B$2:$B$3001=$A23)*(Vendas!$Y$2:$Y$3001=$B23)*ISNUMBER(Vendas!$U$2:$U$3001)) | E23: {=IF(D23<AMOSTRA_MIN,"n<mín",MEDIAN(IF((Vendas!$AK$2:$AK$3001="Validado")*(Vendas!$B$2:$B$3001=$A23)*(Vendas!$Y$2:$Y$3001=$B23)*ISNUMBER(Vendas!$U$2:$U$3001),Vendas!$U$2:$U$3001)))} | F23: =IF(D23=0,"-",SUMPRODUCT((Vendas!$AK$2:$AK$3001="Validado")*(Vendas!$B$2:$B$3001=$A23)*(Vendas!$Y$2:$Y$3001=$B23)*ISNUMBER(Vendas!$U$2:$U$3001)*(Vendas!$U$2:$U$3001<1))/D23) | G23: {=IF(D23<AMOSTRA_MIN,"n<mín",100*AVERAGE(IF((Vendas!$AK$2:$AK$3001="Validado")*(Vendas!$B$2:$B$3001=$A23)*(Vendas!$Y$2:$Y$3001=$B23)*ISNUMBER(Vendas!$U$2:$U$3001),ABS(Vendas!$U$2:$U$3001-E23)))/E23)} | H23: =SUMPRODUCT((Vendas!$AK$2:$AK$3001="Validado")*(Vendas!$B$2:$B$3001=$A23)*(Vendas!$Y$2:$Y$3001=$B23)*ISNUMBER(Vendas!$V$2:$V$3001)) | I23: {=IF(H23<AMOSTRA_MIN,"n<mín",MEDIAN(IF((Vendas!$AK$2:$AK$3001="Validado")*(Vendas!$B$2:$B$3001=$A23)*(Vendas!$Y$2:$Y$3001=$B23)*ISNUMBER(Vendas!$V$2:$V$3001),Vendas!$V$2:$V$3001)))} | J23: =IF(H23=0,"-",SUMPRODUCT((Vendas!$AK$2:$AK$3001="Validado")*(Vendas!$B$2:$B$3001=$A23)*(Vendas!$Y$2:$Y$3001=$B23)*ISNUMBER(Vendas!$V$2:$V$3001)*(Vendas!$V$2:$V$3001<=1))/H23) | K23: =SUMPRODUCT((Vendas!$AK$2:$AK$3001="Validado")*(Vendas!$B$2:$B$3001=$A23)*(Vendas!$Y$2:$Y$3001=$B23)*(Vendas!$P$2:$P$3001="Financiado")*ISNUMBER(Vendas!$S$2:$S$3001)) | L23: =SUMPRODUCT((Vendas!$AK$2:$AK$3001="Validado")*(Vendas!$B$2:$B$3001=$A23)*(Vendas!$Y$2:$Y$3001=$B23)*(Vendas!$P$2:$P$3001="À vista")*ISNUMBER(Vendas!$S$2:$S$3001)) | M23: {=IF(K23<AMOSTRA_MIN,"n<mín",MEDIAN(IF((Vendas!$AK$2:$AK$3001="Validado")*(Vendas!$B$2:$B$3001=$A23)*(Vendas!$Y$2:$Y$3001=$B23)*(Vendas!$P$2:$P$3001="Financiado")*ISNUMBER(Vendas!$S$2:$S$3001),Vendas!$S$2:$S$3001)))} | N23: {=IF(L23<AMOSTRA_MIN,"n<mín",MEDIAN(IF((Vendas!$AK$2:$AK$3001="Validado")*(Vendas!$B$2:$B$3001=$A23)*(Vendas!$Y$2:$Y$3001=$B23)*(Vendas!$P$2:$P$3001="À vista")*ISNUMBER(Vendas!$S$2:$S$3001),Vendas!$S$2:$S$3001)))} | O23: =IF(OR(K23<AMOSTRA_MIN,L23<AMOSTRA_MIN),"n<mín",N23/M23-1) | P23: =SUMPRODUCT((Vendas!$AK$2:$AK$3001="Validado")*(Vendas!$B$2:$B$3001=$A23)*(Vendas!$Y$2:$Y$3001=$B23)*ISNUMBER(Vendas!$W$2:$W$3001)) | Q23: {=IF(P23<AMOSTRA_MIN,"n<mín",MEDIAN(IF((Vendas!$AK$2:$AK$3001="Validado")*(Vendas!$B$2:$B$3001=$A23)*(Vendas!$Y$2:$Y$3001=$B23)*ISNUMBER(Vendas!$W$2:$W$3001),Vendas!$W$2:$W$3001)))} | R23: =IF(P23=0,"-",SUMPRODUCT((Vendas!$AK$2:$AK$3001="Validado")*(Vendas!$B$2:$B$3001=$A23)*(Vendas!$Y$2:$Y$3001=$B23)*ISNUMBER(Vendas!$W$2:$W$3001)*(Vendas!$W$2:$W$3001<1))/P23) | S23: =SUMPRODUCT((Vendas!$AK$2:$AK$3001="Validado")*(Vendas!$B$2:$B$3001=$A23)*(Vendas!$Y$2:$Y$3001=$B23)*ISNUMBER(Vendas!$X$2:$X$3001)) | T23: =IF(S23=0,"-",SUMPRODUCT((Vendas!$AK$2:$AK$3001="Validado")*(Vendas!$B$2:$B$3001=$A23)*(Vendas!$Y$2:$Y$3001=$B23)*ISNUMBER(Vendas!$X$2:$X$3001)*(Vendas!$X$2:$X$3001>=1))/S23)
A24: Bertioga | B24: 2024 | C24: =SUMPRODUCT((Vendas!$AK$2:$AK$3001="Validado")*(Vendas!$B$2:$B$3001=$A24)*(Vendas!$Y$2:$Y$3001=$B24)) | D24: =SUMPRODUCT((Vendas!$AK$2:$AK$3001="Validado")*(Vendas!$B$2:$B$3001=$A24)*(Vendas!$Y$2:$Y$3001=$B24)*ISNUMBER(Vendas!$U$2:$U$3001)) | E24: {=IF(D24<AMOSTRA_MIN,"n<mín",MEDIAN(IF((Vendas!$AK$2:$AK$3001="Validado")*(Vendas!$B$2:$B$3001=$A24)*(Vendas!$Y$2:$Y$3001=$B24)*ISNUMBER(Vendas!$U$2:$U$3001),Vendas!$U$2:$U$3001)))} | F24: =IF(D24=0,"-",SUMPRODUCT((Vendas!$AK$2:$AK$3001="Validado")*(Vendas!$B$2:$B$3001=$A24)*(Vendas!$Y$2:$Y$3001=$B24)*ISNUMBER(Vendas!$U$2:$U$3001)*(Vendas!$U$2:$U$3001<1))/D24) | G24: {=IF(D24<AMOSTRA_MIN,"n<mín",100*AVERAGE(IF((Vendas!$AK$2:$AK$3001="Validado")*(Vendas!$B$2:$B$3001=$A24)*(Vendas!$Y$2:$Y$3001=$B24)*ISNUMBER(Vendas!$U$2:$U$3001),ABS(Vendas!$U$2:$U$3001-E24)))/E24)} | H24: =SUMPRODUCT((Vendas!$AK$2:$AK$3001="Validado")*(Vendas!$B$2:$B$3001=$A24)*(Vendas!$Y$2:$Y$3001=$B24)*ISNUMBER(Vendas!$V$2:$V$3001)) | I24: {=IF(H24<AMOSTRA_MIN,"n<mín",MEDIAN(IF((Vendas!$AK$2:$AK$3001="Validado")*(Vendas!$B$2:$B$3001=$A24)*(Vendas!$Y$2:$Y$3001=$B24)*ISNUMBER(Vendas!$V$2:$V$3001),Vendas!$V$2:$V$3001)))} | J24: =IF(H24=0,"-",SUMPRODUCT((Vendas!$AK$2:$AK$3001="Validado")*(Vendas!$B$2:$B$3001=$A24)*(Vendas!$Y$2:$Y$3001=$B24)*ISNUMBER(Vendas!$V$2:$V$3001)*(Vendas!$V$2:$V$3001<=1))/H24) | K24: =SUMPRODUCT((Vendas!$AK$2:$AK$3001="Validado")*(Vendas!$B$2:$B$3001=$A24)*(Vendas!$Y$2:$Y$3001=$B24)*(Vendas!$P$2:$P$3001="Financiado")*ISNUMBER(Vendas!$S$2:$S$3001)) | L24: =SUMPRODUCT((Vendas!$AK$2:$AK$3001="Validado")*(Vendas!$B$2:$B$3001=$A24)*(Vendas!$Y$2:$Y$3001=$B24)*(Vendas!$P$2:$P$3001="À vista")*ISNUMBER(Vendas!$S$2:$S$3001)) | M24: {=IF(K24<AMOSTRA_MIN,"n<mín",MEDIAN(IF((Vendas!$AK$2:$AK$3001="Validado")*(Vendas!$B$2:$B$3001=$A24)*(Vendas!$Y$2:$Y$3001=$B24)*(Vendas!$P$2:$P$3001="Financiado")*ISNUMBER(Vendas!$S$2:$S$3001),Vendas!$S$2:$S$3001)))} | N24: {=IF(L24<AMOSTRA_MIN,"n<mín",MEDIAN(IF((Vendas!$AK$2:$AK$3001="Validado")*(Vendas!$B$2:$B$3001=$A24)*(Vendas!$Y$2:$Y$3001=$B24)*(Vendas!$P$2:$P$3001="À vista")*ISNUMBER(Vendas!$S$2:$S$3001),Vendas!$S$2:$S$3001)))} | O24: =IF(OR(K24<AMOSTRA_MIN,L24<AMOSTRA_MIN),"n<mín",N24/M24-1) | P24: =SUMPRODUCT((Vendas!$AK$2:$AK$3001="Validado")*(Vendas!$B$2:$B$3001=$A24)*(Vendas!$Y$2:$Y$3001=$B24)*ISNUMBER(Vendas!$W$2:$W$3001)) | Q24: {=IF(P24<AMOSTRA_MIN,"n<mín",MEDIAN(IF((Vendas!$AK$2:$AK$3001="Validado")*(Vendas!$B$2:$B$3001=$A24)*(Vendas!$Y$2:$Y$3001=$B24)*ISNUMBER(Vendas!$W$2:$W$3001),Vendas!$W$2:$W$3001)))} | R24: =IF(P24=0,"-",SUMPRODUCT((Vendas!$AK$2:$AK$3001="Validado")*(Vendas!$B$2:$B$3001=$A24)*(Vendas!$Y$2:$Y$3001=$B24)*ISNUMBER(Vendas!$W$2:$W$3001)*(Vendas!$W$2:$W$3001<1))/P24) | S24: =SUMPRODUCT((Vendas!$AK$2:$AK$3001="Validado")*(Vendas!$B$2:$B$3001=$A24)*(Vendas!$Y$2:$Y$3001=$B24)*ISNUMBER(Vendas!$X$2:$X$3001)) | T24: =IF(S24=0,"-",SUMPRODUCT((Vendas!$AK$2:$AK$3001="Validado")*(Vendas!$B$2:$B$3001=$A24)*(Vendas!$Y$2:$Y$3001=$B24)*ISNUMBER(Vendas!$X$2:$X$3001)*(Vendas!$X$2:$X$3001>=1))/S24)
A25: Bertioga | B25: 2025 | C25: =SUMPRODUCT((Vendas!$AK$2:$AK$3001="Validado")*(Vendas!$B$2:$B$3001=$A25)*(Vendas!$Y$2:$Y$3001=$B25)) | D25: =SUMPRODUCT((Vendas!$AK$2:$AK$3001="Validado")*(Vendas!$B$2:$B$3001=$A25)*(Vendas!$Y$2:$Y$3001=$B25)*ISNUMBER(Vendas!$U$2:$U$3001)) | E25: {=IF(D25<AMOSTRA_MIN,"n<mín",MEDIAN(IF((Vendas!$AK$2:$AK$3001="Validado")*(Vendas!$B$2:$B$3001=$A25)*(Vendas!$Y$2:$Y$3001=$B25)*ISNUMBER(Vendas!$U$2:$U$3001),Vendas!$U$2:$U$3001)))} | F25: =IF(D25=0,"-",SUMPRODUCT((Vendas!$AK$2:$AK$3001="Validado")*(Vendas!$B$2:$B$3001=$A25)*(Vendas!$Y$2:$Y$3001=$B25)*ISNUMBER(Vendas!$U$2:$U$3001)*(Vendas!$U$2:$U$3001<1))/D25) | G25: {=IF(D25<AMOSTRA_MIN,"n<mín",100*AVERAGE(IF((Vendas!$AK$2:$AK$3001="Validado")*(Vendas!$B$2:$B$3001=$A25)*(Vendas!$Y$2:$Y$3001=$B25)*ISNUMBER(Vendas!$U$2:$U$3001),ABS(Vendas!$U$2:$U$3001-E25)))/E25)} | H25: =SUMPRODUCT((Vendas!$AK$2:$AK$3001="Validado")*(Vendas!$B$2:$B$3001=$A25)*(Vendas!$Y$2:$Y$3001=$B25)*ISNUMBER(Vendas!$V$2:$V$3001)) | I25: {=IF(H25<AMOSTRA_MIN,"n<mín",MEDIAN(IF((Vendas!$AK$2:$AK$3001="Validado")*(Vendas!$B$2:$B$3001=$A25)*(Vendas!$Y$2:$Y$3001=$B25)*ISNUMBER(Vendas!$V$2:$V$3001),Vendas!$V$2:$V$3001)))} | J25: =IF(H25=0,"-",SUMPRODUCT((Vendas!$AK$2:$AK$3001="Validado")*(Vendas!$B$2:$B$3001=$A25)*(Vendas!$Y$2:$Y$3001=$B25)*ISNUMBER(Vendas!$V$2:$V$3001)*(Vendas!$V$2:$V$3001<=1))/H25) | K25: =SUMPRODUCT((Vendas!$AK$2:$AK$3001="Validado")*(Vendas!$B$2:$B$3001=$A25)*(Vendas!$Y$2:$Y$3001=$B25)*(Vendas!$P$2:$P$3001="Financiado")*ISNUMBER(Vendas!$S$2:$S$3001)) | L25: =SUMPRODUCT((Vendas!$AK$2:$AK$3001="Validado")*(Vendas!$B$2:$B$3001=$A25)*(Vendas!$Y$2:$Y$3001=$B25)*(Vendas!$P$2:$P$3001="À vista")*ISNUMBER(Vendas!$S$2:$S$3001)) | M25: {=IF(K25<AMOSTRA_MIN,"n<mín",MEDIAN(IF((Vendas!$AK$2:$AK$3001="Validado")*(Vendas!$B$2:$B$3001=$A25)*(Vendas!$Y$2:$Y$3001=$B25)*(Vendas!$P$2:$P$3001="Financiado")*ISNUMBER(Vendas!$S$2:$S$3001),Vendas!$S$2:$S$3001)))} | N25: {=IF(L25<AMOSTRA_MIN,"n<mín",MEDIAN(IF((Vendas!$AK$2:$AK$3001="Validado")*(Vendas!$B$2:$B$3001=$A25)*(Vendas!$Y$2:$Y$3001=$B25)*(Vendas!$P$2:$P$3001="À vista")*ISNUMBER(Vendas!$S$2:$S$3001),Vendas!$S$2:$S$3001)))} | O25: =IF(OR(K25<AMOSTRA_MIN,L25<AMOSTRA_MIN),"n<mín",N25/M25-1) | P25: =SUMPRODUCT((Vendas!$AK$2:$AK$3001="Validado")*(Vendas!$B$2:$B$3001=$A25)*(Vendas!$Y$2:$Y$3001=$B25)*ISNUMBER(Vendas!$W$2:$W$3001)) | Q25: {=IF(P25<AMOSTRA_MIN,"n<mín",MEDIAN(IF((Vendas!$AK$2:$AK$3001="Validado")*(Vendas!$B$2:$B$3001=$A25)*(Vendas!$Y$2:$Y$3001=$B25)*ISNUMBER(Vendas!$W$2:$W$3001),Vendas!$W$2:$W$3001)))} | R25: =IF(P25=0,"-",SUMPRODUCT((Vendas!$AK$2:$AK$3001="Validado")*(Vendas!$B$2:$B$3001=$A25)*(Vendas!$Y$2:$Y$3001=$B25)*ISNUMBER(Vendas!$W$2:$W$3001)*(Vendas!$W$2:$W$3001<1))/P25) | S25: =SUMPRODUCT((Vendas!$AK$2:$AK$3001="Validado")*(Vendas!$B$2:$B$3001=$A25)*(Vendas!$Y$2:$Y$3001=$B25)*ISNUMBER(Vendas!$X$2:$X$3001)) | T25: =IF(S25=0,"-",SUMPRODUCT((Vendas!$AK$2:$AK$3001="Validado")*(Vendas!$B$2:$B$3001=$A25)*(Vendas!$Y$2:$Y$3001=$B25)*ISNUMBER(Vendas!$X$2:$X$3001)*(Vendas!$X$2:$X$3001>=1))/S25)
A26: Bertioga | B26: 2026 | C26: =SUMPRODUCT((Vendas!$AK$2:$AK$3001="Validado")*(Vendas!$B$2:$B$3001=$A26)*(Vendas!$Y$2:$Y$3001=$B26)) | D26: =SUMPRODUCT((Vendas!$AK$2:$AK$3001="Validado")*(Vendas!$B$2:$B$3001=$A26)*(Vendas!$Y$2:$Y$3001=$B26)*ISNUMBER(Vendas!$U$2:$U$3001)) | E26: {=IF(D26<AMOSTRA_MIN,"n<mín",MEDIAN(IF((Vendas!$AK$2:$AK$3001="Validado")*(Vendas!$B$2:$B$3001=$A26)*(Vendas!$Y$2:$Y$3001=$B26)*ISNUMBER(Vendas!$U$2:$U$3001),Vendas!$U$2:$U$3001)))} | F26: =IF(D26=0,"-",SUMPRODUCT((Vendas!$AK$2:$AK$3001="Validado")*(Vendas!$B$2:$B$3001=$A26)*(Vendas!$Y$2:$Y$3001=$B26)*ISNUMBER(Vendas!$U$2:$U$3001)*(Vendas!$U$2:$U$3001<1))/D26) | G26: {=IF(D26<AMOSTRA_MIN,"n<mín",100*AVERAGE(IF((Vendas!$AK$2:$AK$3001="Validado")*(Vendas!$B$2:$B$3001=$A26)*(Vendas!$Y$2:$Y$3001=$B26)*ISNUMBER(Vendas!$U$2:$U$3001),ABS(Vendas!$U$2:$U$3001-E26)))/E26)} | H26: =SUMPRODUCT((Vendas!$AK$2:$AK$3001="Validado")*(Vendas!$B$2:$B$3001=$A26)*(Vendas!$Y$2:$Y$3001=$B26)*ISNUMBER(Vendas!$V$2:$V$3001)) | I26: {=IF(H26<AMOSTRA_MIN,"n<mín",MEDIAN(IF((Vendas!$AK$2:$AK$3001="Validado")*(Vendas!$B$2:$B$3001=$A26)*(Vendas!$Y$2:$Y$3001=$B26)*ISNUMBER(Vendas!$V$2:$V$3001),Vendas!$V$2:$V$3001)))} | J26: =IF(H26=0,"-",SUMPRODUCT((Vendas!$AK$2:$AK$3001="Validado")*(Vendas!$B$2:$B$3001=$A26)*(Vendas!$Y$2:$Y$3001=$B26)*ISNUMBER(Vendas!$V$2:$V$3001)*(Vendas!$V$2:$V$3001<=1))/H26) | K26: =SUMPRODUCT((Vendas!$AK$2:$AK$3001="Validado")*(Vendas!$B$2:$B$3001=$A26)*(Vendas!$Y$2:$Y$3001=$B26)*(Vendas!$P$2:$P$3001="Financiado")*ISNUMBER(Vendas!$S$2:$S$3001)) | L26: =SUMPRODUCT((Vendas!$AK$2:$AK$3001="Validado")*(Vendas!$B$2:$B$3001=$A26)*(Vendas!$Y$2:$Y$3001=$B26)*(Vendas!$P$2:$P$3001="À vista")*ISNUMBER(Vendas!$S$2:$S$3001)) | M26: {=IF(K26<AMOSTRA_MIN,"n<mín",MEDIAN(IF((Vendas!$AK$2:$AK$3001="Validado")*(Vendas!$B$2:$B$3001=$A26)*(Vendas!$Y$2:$Y$3001=$B26)*(Vendas!$P$2:$P$3001="Financiado")*ISNUMBER(Vendas!$S$2:$S$3001),Vendas!$S$2:$S$3001)))} | N26: {=IF(L26<AMOSTRA_MIN,"n<mín",MEDIAN(IF((Vendas!$AK$2:$AK$3001="Validado")*(Vendas!$B$2:$B$3001=$A26)*(Vendas!$Y$2:$Y$3001=$B26)*(Vendas!$P$2:$P$3001="À vista")*ISNUMBER(Vendas!$S$2:$S$3001),Vendas!$S$2:$S$3001)))} | O26: =IF(OR(K26<AMOSTRA_MIN,L26<AMOSTRA_MIN),"n<mín",N26/M26-1) | P26: =SUMPRODUCT((Vendas!$AK$2:$AK$3001="Validado")*(Vendas!$B$2:$B$3001=$A26)*(Vendas!$Y$2:$Y$3001=$B26)*ISNUMBER(Vendas!$W$2:$W$3001)) | Q26: {=IF(P26<AMOSTRA_MIN,"n<mín",MEDIAN(IF((Vendas!$AK$2:$AK$3001="Validado")*(Vendas!$B$2:$B$3001=$A26)*(Vendas!$Y$2:$Y$3001=$B26)*ISNUMBER(Vendas!$W$2:$W$3001),Vendas!$W$2:$W$3001)))} | R26: =IF(P26=0,"-",SUMPRODUCT((Vendas!$AK$2:$AK$3001="Validado")*(Vendas!$B$2:$B$3001=$A26)*(Vendas!$Y$2:$Y$3001=$B26)*ISNUMBER(Vendas!$W$2:$W$3001)*(Vendas!$W$2:$W$3001<1))/P26) | S26: =SUMPRODUCT((Vendas!$AK$2:$AK$3001="Validado")*(Vendas!$B$2:$B$3001=$A26)*(Vendas!$Y$2:$Y$3001=$B26)*ISNUMBER(Vendas!$X$2:$X$3001)) | T26: =IF(S26=0,"-",SUMPRODUCT((Vendas!$AK$2:$AK$3001="Validado")*(Vendas!$B$2:$B$3001=$A26)*(Vendas!$Y$2:$Y$3001=$B26)*ISNUMBER(Vendas!$X$2:$X$3001)*(Vendas!$X$2:$X$3001>=1))/S26)
A29: Por cidade e padrão
A30: Cidade | B30: Padrão | C30: Nº vendas validadas | D30: Nº c/ base ITBI | E30: Mediana Declarado ÷ Base ITBI | F30: % c/ base > declarado | G30: COD Declarado ÷ Base | H30: Nº c/ venal IPTU | I30: Mediana Declarado ÷ Venal | J30: % declarado ≤ venal | K30: Nº financiadas (c/ m²) | L30: Nº à vista (c/ m²) | M30: R$/m² mediano financiadas | N30: R$/m² mediano à vista | O30: Dif. à vista vs financiada | P30: Nº c/ valor leilão | Q30: Mediana Declarado ÷ Leilão | R30: % declarado < leilão | S30: Nº c/ valor financiado | T30: % financiado ≥ declarado
A31: São Sebastião | B31: Baixo | C31: =SUMPRODUCT((Vendas!$AK$2:$AK$3001="Validado")*(Vendas!$B$2:$B$3001=$A31)*(Vendas!$J$2:$J$3001=$B31)) | D31: =SUMPRODUCT((Vendas!$AK$2:$AK$3001="Validado")*(Vendas!$B$2:$B$3001=$A31)*(Vendas!$J$2:$J$3001=$B31)*ISNUMBER(Vendas!$U$2:$U$3001)) | E31: {=IF(D31<AMOSTRA_MIN,"n<mín",MEDIAN(IF((Vendas!$AK$2:$AK$3001="Validado")*(Vendas!$B$2:$B$3001=$A31)*(Vendas!$J$2:$J$3001=$B31)*ISNUMBER(Vendas!$U$2:$U$3001),Vendas!$U$2:$U$3001)))} | F31: =IF(D31=0,"-",SUMPRODUCT((Vendas!$AK$2:$AK$3001="Validado")*(Vendas!$B$2:$B$3001=$A31)*(Vendas!$J$2:$J$3001=$B31)*ISNUMBER(Vendas!$U$2:$U$3001)*(Vendas!$U$2:$U$3001<1))/D31) | G31: {=IF(D31<AMOSTRA_MIN,"n<mín",100*AVERAGE(IF((Vendas!$AK$2:$AK$3001="Validado")*(Vendas!$B$2:$B$3001=$A31)*(Vendas!$J$2:$J$3001=$B31)*ISNUMBER(Vendas!$U$2:$U$3001),ABS(Vendas!$U$2:$U$3001-E31)))/E31)} | H31: =SUMPRODUCT((Vendas!$AK$2:$AK$3001="Validado")*(Vendas!$B$2:$B$3001=$A31)*(Vendas!$J$2:$J$3001=$B31)*ISNUMBER(Vendas!$V$2:$V$3001)) | I31: {=IF(H31<AMOSTRA_MIN,"n<mín",MEDIAN(IF((Vendas!$AK$2:$AK$3001="Validado")*(Vendas!$B$2:$B$3001=$A31)*(Vendas!$J$2:$J$3001=$B31)*ISNUMBER(Vendas!$V$2:$V$3001),Vendas!$V$2:$V$3001)))} | J31: =IF(H31=0,"-",SUMPRODUCT((Vendas!$AK$2:$AK$3001="Validado")*(Vendas!$B$2:$B$3001=$A31)*(Vendas!$J$2:$J$3001=$B31)*ISNUMBER(Vendas!$V$2:$V$3001)*(Vendas!$V$2:$V$3001<=1))/H31) | K31: =SUMPRODUCT((Vendas!$AK$2:$AK$3001="Validado")*(Vendas!$B$2:$B$3001=$A31)*(Vendas!$J$2:$J$3001=$B31)*(Vendas!$P$2:$P$3001="Financiado")*ISNUMBER(Vendas!$S$2:$S$3001)) | L31: =SUMPRODUCT((Vendas!$AK$2:$AK$3001="Validado")*(Vendas!$B$2:$B$3001=$A31)*(Vendas!$J$2:$J$3001=$B31)*(Vendas!$P$2:$P$3001="À vista")*ISNUMBER(Vendas!$S$2:$S$3001)) | M31: {=IF(K31<AMOSTRA_MIN,"n<mín",MEDIAN(IF((Vendas!$AK$2:$AK$3001="Validado")*(Vendas!$B$2:$B$3001=$A31)*(Vendas!$J$2:$J$3001=$B31)*(Vendas!$P$2:$P$3001="Financiado")*ISNUMBER(Vendas!$S$2:$S$3001),Vendas!$S$2:$S$3001)))} | N31: {=IF(L31<AMOSTRA_MIN,"n<mín",MEDIAN(IF((Vendas!$AK$2:$AK$3001="Validado")*(Vendas!$B$2:$B$3001=$A31)*(Vendas!$J$2:$J$3001=$B31)*(Vendas!$P$2:$P$3001="À vista")*ISNUMBER(Vendas!$S$2:$S$3001),Vendas!$S$2:$S$3001)))} | O31: =IF(OR(K31<AMOSTRA_MIN,L31<AMOSTRA_MIN),"n<mín",N31/M31-1) | P31: =SUMPRODUCT((Vendas!$AK$2:$AK$3001="Validado")*(Vendas!$B$2:$B$3001=$A31)*(Vendas!$J$2:$J$3001=$B31)*ISNUMBER(Vendas!$W$2:$W$3001)) | Q31: {=IF(P31<AMOSTRA_MIN,"n<mín",MEDIAN(IF((Vendas!$AK$2:$AK$3001="Validado")*(Vendas!$B$2:$B$3001=$A31)*(Vendas!$J$2:$J$3001=$B31)*ISNUMBER(Vendas!$W$2:$W$3001),Vendas!$W$2:$W$3001)))} | R31: =IF(P31=0,"-",SUMPRODUCT((Vendas!$AK$2:$AK$3001="Validado")*(Vendas!$B$2:$B$3001=$A31)*(Vendas!$J$2:$J$3001=$B31)*ISNUMBER(Vendas!$W$2:$W$3001)*(Vendas!$W$2:$W$3001<1))/P31) | S31: =SUMPRODUCT((Vendas!$AK$2:$AK$3001="Validado")*(Vendas!$B$2:$B$3001=$A31)*(Vendas!$J$2:$J$3001=$B31)*ISNUMBER(Vendas!$X$2:$X$3001)) | T31: =IF(S31=0,"-",SUMPRODUCT((Vendas!$AK$2:$AK$3001="Validado")*(Vendas!$B$2:$B$3001=$A31)*(Vendas!$J$2:$J$3001=$B31)*ISNUMBER(Vendas!$X$2:$X$3001)*(Vendas!$X$2:$X$3001>=1))/S31)
A32: São Sebastião | B32: Normal | C32: =SUMPRODUCT((Vendas!$AK$2:$AK$3001="Validado")*(Vendas!$B$2:$B$3001=$A32)*(Vendas!$J$2:$J$3001=$B32)) | D32: =SUMPRODUCT((Vendas!$AK$2:$AK$3001="Validado")*(Vendas!$B$2:$B$3001=$A32)*(Vendas!$J$2:$J$3001=$B32)*ISNUMBER(Vendas!$U$2:$U$3001)) | E32: {=IF(D32<AMOSTRA_MIN,"n<mín",MEDIAN(IF((Vendas!$AK$2:$AK$3001="Validado")*(Vendas!$B$2:$B$3001=$A32)*(Vendas!$J$2:$J$3001=$B32)*ISNUMBER(Vendas!$U$2:$U$3001),Vendas!$U$2:$U$3001)))} | F32: =IF(D32=0,"-",SUMPRODUCT((Vendas!$AK$2:$AK$3001="Validado")*(Vendas!$B$2:$B$3001=$A32)*(Vendas!$J$2:$J$3001=$B32)*ISNUMBER(Vendas!$U$2:$U$3001)*(Vendas!$U$2:$U$3001<1))/D32) | G32: {=IF(D32<AMOSTRA_MIN,"n<mín",100*AVERAGE(IF((Vendas!$AK$2:$AK$3001="Validado")*(Vendas!$B$2:$B$3001=$A32)*(Vendas!$J$2:$J$3001=$B32)*ISNUMBER(Vendas!$U$2:$U$3001),ABS(Vendas!$U$2:$U$3001-E32)))/E32)} | H32: =SUMPRODUCT((Vendas!$AK$2:$AK$3001="Validado")*(Vendas!$B$2:$B$3001=$A32)*(Vendas!$J$2:$J$3001=$B32)*ISNUMBER(Vendas!$V$2:$V$3001)) | I32: {=IF(H32<AMOSTRA_MIN,"n<mín",MEDIAN(IF((Vendas!$AK$2:$AK$3001="Validado")*(Vendas!$B$2:$B$3001=$A32)*(Vendas!$J$2:$J$3001=$B32)*ISNUMBER(Vendas!$V$2:$V$3001),Vendas!$V$2:$V$3001)))} | J32: =IF(H32=0,"-",SUMPRODUCT((Vendas!$AK$2:$AK$3001="Validado")*(Vendas!$B$2:$B$3001=$A32)*(Vendas!$J$2:$J$3001=$B32)*ISNUMBER(Vendas!$V$2:$V$3001)*(Vendas!$V$2:$V$3001<=1))/H32) | K32: =SUMPRODUCT((Vendas!$AK$2:$AK$3001="Validado")*(Vendas!$B$2:$B$3001=$A32)*(Vendas!$J$2:$J$3001=$B32)*(Vendas!$P$2:$P$3001="Financiado")*ISNUMBER(Vendas!$S$2:$S$3001)) | L32: =SUMPRODUCT((Vendas!$AK$2:$AK$3001="Validado")*(Vendas!$B$2:$B$3001=$A32)*(Vendas!$J$2:$J$3001=$B32)*(Vendas!$P$2:$P$3001="À vista")*ISNUMBER(Vendas!$S$2:$S$3001)) | M32: {=IF(K32<AMOSTRA_MIN,"n<mín",MEDIAN(IF((Vendas!$AK$2:$AK$3001="Validado")*(Vendas!$B$2:$B$3001=$A32)*(Vendas!$J$2:$J$3001=$B32)*(Vendas!$P$2:$P$3001="Financiado")*ISNUMBER(Vendas!$S$2:$S$3001),Vendas!$S$2:$S$3001)))} | N32: {=IF(L32<AMOSTRA_MIN,"n<mín",MEDIAN(IF((Vendas!$AK$2:$AK$3001="Validado")*(Vendas!$B$2:$B$3001=$A32)*(Vendas!$J$2:$J$3001=$B32)*(Vendas!$P$2:$P$3001="À vista")*ISNUMBER(Vendas!$S$2:$S$3001),Vendas!$S$2:$S$3001)))} | O32: =IF(OR(K32<AMOSTRA_MIN,L32<AMOSTRA_MIN),"n<mín",N32/M32-1) | P32: =SUMPRODUCT((Vendas!$AK$2:$AK$3001="Validado")*(Vendas!$B$2:$B$3001=$A32)*(Vendas!$J$2:$J$3001=$B32)*ISNUMBER(Vendas!$W$2:$W$3001)) | Q32: {=IF(P32<AMOSTRA_MIN,"n<mín",MEDIAN(IF((Vendas!$AK$2:$AK$3001="Validado")*(Vendas!$B$2:$B$3001=$A32)*(Vendas!$J$2:$J$3001=$B32)*ISNUMBER(Vendas!$W$2:$W$3001),Vendas!$W$2:$W$3001)))} | R32: =IF(P32=0,"-",SUMPRODUCT((Vendas!$AK$2:$AK$3001="Validado")*(Vendas!$B$2:$B$3001=$A32)*(Vendas!$J$2:$J$3001=$B32)*ISNUMBER(Vendas!$W$2:$W$3001)*(Vendas!$W$2:$W$3001<1))/P32) | S32: =SUMPRODUCT((Vendas!$AK$2:$AK$3001="Validado")*(Vendas!$B$2:$B$3001=$A32)*(Vendas!$J$2:$J$3001=$B32)*ISNUMBER(Vendas!$X$2:$X$3001)) | T32: =IF(S32=0,"-",SUMPRODUCT((Vendas!$AK$2:$AK$3001="Validado")*(Vendas!$B$2:$B$3001=$A32)*(Vendas!$J$2:$J$3001=$B32)*ISNUMBER(Vendas!$X$2:$X$3001)*(Vendas!$X$2:$X$3001>=1))/S32)
A33: São Sebastião | B33: Alto | C33: =SUMPRODUCT((Vendas!$AK$2:$AK$3001="Validado")*(Vendas!$B$2:$B$3001=$A33)*(Vendas!$J$2:$J$3001=$B33)) | D33: =SUMPRODUCT((Vendas!$AK$2:$AK$3001="Validado")*(Vendas!$B$2:$B$3001=$A33)*(Vendas!$J$2:$J$3001=$B33)*ISNUMBER(Vendas!$U$2:$U$3001)) | E33: {=IF(D33<AMOSTRA_MIN,"n<mín",MEDIAN(IF((Vendas!$AK$2:$AK$3001="Validado")*(Vendas!$B$2:$B$3001=$A33)*(Vendas!$J$2:$J$3001=$B33)*ISNUMBER(Vendas!$U$2:$U$3001),Vendas!$U$2:$U$3001)))} | F33: =IF(D33=0,"-",SUMPRODUCT((Vendas!$AK$2:$AK$3001="Validado")*(Vendas!$B$2:$B$3001=$A33)*(Vendas!$J$2:$J$3001=$B33)*ISNUMBER(Vendas!$U$2:$U$3001)*(Vendas!$U$2:$U$3001<1))/D33) | G33: {=IF(D33<AMOSTRA_MIN,"n<mín",100*AVERAGE(IF((Vendas!$AK$2:$AK$3001="Validado")*(Vendas!$B$2:$B$3001=$A33)*(Vendas!$J$2:$J$3001=$B33)*ISNUMBER(Vendas!$U$2:$U$3001),ABS(Vendas!$U$2:$U$3001-E33)))/E33)} | H33: =SUMPRODUCT((Vendas!$AK$2:$AK$3001="Validado")*(Vendas!$B$2:$B$3001=$A33)*(Vendas!$J$2:$J$3001=$B33)*ISNUMBER(Vendas!$V$2:$V$3001)) | I33: {=IF(H33<AMOSTRA_MIN,"n<mín",MEDIAN(IF((Vendas!$AK$2:$AK$3001="Validado")*(Vendas!$B$2:$B$3001=$A33)*(Vendas!$J$2:$J$3001=$B33)*ISNUMBER(Vendas!$V$2:$V$3001),Vendas!$V$2:$V$3001)))} | J33: =IF(H33=0,"-",SUMPRODUCT((Vendas!$AK$2:$AK$3001="Validado")*(Vendas!$B$2:$B$3001=$A33)*(Vendas!$J$2:$J$3001=$B33)*ISNUMBER(Vendas!$V$2:$V$3001)*(Vendas!$V$2:$V$3001<=1))/H33) | K33: =SUMPRODUCT((Vendas!$AK$2:$AK$3001="Validado")*(Vendas!$B$2:$B$3001=$A33)*(Vendas!$J$2:$J$3001=$B33)*(Vendas!$P$2:$P$3001="Financiado")*ISNUMBER(Vendas!$S$2:$S$3001)) | L33: =SUMPRODUCT((Vendas!$AK$2:$AK$3001="Validado")*(Vendas!$B$2:$B$3001=$A33)*(Vendas!$J$2:$J$3001=$B33)*(Vendas!$P$2:$P$3001="À vista")*ISNUMBER(Vendas!$S$2:$S$3001)) | M33: {=IF(K33<AMOSTRA_MIN,"n<mín",MEDIAN(IF((Vendas!$AK$2:$AK$3001="Validado")*(Vendas!$B$2:$B$3001=$A33)*(Vendas!$J$2:$J$3001=$B33)*(Vendas!$P$2:$P$3001="Financiado")*ISNUMBER(Vendas!$S$2:$S$3001),Vendas!$S$2:$S$3001)))} | N33: {=IF(L33<AMOSTRA_MIN,"n<mín",MEDIAN(IF((Vendas!$AK$2:$AK$3001="Validado")*(Vendas!$B$2:$B$3001=$A33)*(Vendas!$J$2:$J$3001=$B33)*(Vendas!$P$2:$P$3001="À vista")*ISNUMBER(Vendas!$S$2:$S$3001),Vendas!$S$2:$S$3001)))} | O33: =IF(OR(K33<AMOSTRA_MIN,L33<AMOSTRA_MIN),"n<mín",N33/M33-1) | P33: =SUMPRODUCT((Vendas!$AK$2:$AK$3001="Validado")*(Vendas!$B$2:$B$3001=$A33)*(Vendas!$J$2:$J$3001=$B33)*ISNUMBER(Vendas!$W$2:$W$3001)) | Q33: {=IF(P33<AMOSTRA_MIN,"n<mín",MEDIAN(IF((Vendas!$AK$2:$AK$3001="Validado")*(Vendas!$B$2:$B$3001=$A33)*(Vendas!$J$2:$J$3001=$B33)*ISNUMBER(Vendas!$W$2:$W$3001),Vendas!$W$2:$W$3001)))} | R33: =IF(P33=0,"-",SUMPRODUCT((Vendas!$AK$2:$AK$3001="Validado")*(Vendas!$B$2:$B$3001=$A33)*(Vendas!$J$2:$J$3001=$B33)*ISNUMBER(Vendas!$W$2:$W$3001)*(Vendas!$W$2:$W$3001<1))/P33) | S33: =SUMPRODUCT((Vendas!$AK$2:$AK$3001="Validado")*(Vendas!$B$2:$B$3001=$A33)*(Vendas!$J$2:$J$3001=$B33)*ISNUMBER(Vendas!$X$2:$X$3001)) | T33: =IF(S33=0,"-",SUMPRODUCT((Vendas!$AK$2:$AK$3001="Validado")*(Vendas!$B$2:$B$3001=$A33)*(Vendas!$J$2:$J$3001=$B33)*ISNUMBER(Vendas!$X$2:$X$3001)*(Vendas!$X$2:$X$3001>=1))/S33)
A34: São Sebastião | B34: Não informado | C34: =SUMPRODUCT((Vendas!$AK$2:$AK$3001="Validado")*(Vendas!$B$2:$B$3001=$A34)*(Vendas!$J$2:$J$3001=$B34)) | D34: =SUMPRODUCT((Vendas!$AK$2:$AK$3001="Validado")*(Vendas!$B$2:$B$3001=$A34)*(Vendas!$J$2:$J$3001=$B34)*ISNUMBER(Vendas!$U$2:$U$3001)) | E34: {=IF(D34<AMOSTRA_MIN,"n<mín",MEDIAN(IF((Vendas!$AK$2:$AK$3001="Validado")*(Vendas!$B$2:$B$3001=$A34)*(Vendas!$J$2:$J$3001=$B34)*ISNUMBER(Vendas!$U$2:$U$3001),Vendas!$U$2:$U$3001)))} | F34: =IF(D34=0,"-",SUMPRODUCT((Vendas!$AK$2:$AK$3001="Validado")*(Vendas!$B$2:$B$3001=$A34)*(Vendas!$J$2:$J$3001=$B34)*ISNUMBER(Vendas!$U$2:$U$3001)*(Vendas!$U$2:$U$3001<1))/D34) | G34: {=IF(D34<AMOSTRA_MIN,"n<mín",100*AVERAGE(IF((Vendas!$AK$2:$AK$3001="Validado")*(Vendas!$B$2:$B$3001=$A34)*(Vendas!$J$2:$J$3001=$B34)*ISNUMBER(Vendas!$U$2:$U$3001),ABS(Vendas!$U$2:$U$3001-E34)))/E34)} | H34: =SUMPRODUCT((Vendas!$AK$2:$AK$3001="Validado")*(Vendas!$B$2:$B$3001=$A34)*(Vendas!$J$2:$J$3001=$B34)*ISNUMBER(Vendas!$V$2:$V$3001)) | I34: {=IF(H34<AMOSTRA_MIN,"n<mín",MEDIAN(IF((Vendas!$AK$2:$AK$3001="Validado")*(Vendas!$B$2:$B$3001=$A34)*(Vendas!$J$2:$J$3001=$B34)*ISNUMBER(Vendas!$V$2:$V$3001),Vendas!$V$2:$V$3001)))} | J34: =IF(H34=0,"-",SUMPRODUCT((Vendas!$AK$2:$AK$3001="Validado")*(Vendas!$B$2:$B$3001=$A34)*(Vendas!$J$2:$J$3001=$B34)*ISNUMBER(Vendas!$V$2:$V$3001)*(Vendas!$V$2:$V$3001<=1))/H34) | K34: =SUMPRODUCT((Vendas!$AK$2:$AK$3001="Validado")*(Vendas!$B$2:$B$3001=$A34)*(Vendas!$J$2:$J$3001=$B34)*(Vendas!$P$2:$P$3001="Financiado")*ISNUMBER(Vendas!$S$2:$S$3001)) | L34: =SUMPRODUCT((Vendas!$AK$2:$AK$3001="Validado")*(Vendas!$B$2:$B$3001=$A34)*(Vendas!$J$2:$J$3001=$B34)*(Vendas!$P$2:$P$3001="À vista")*ISNUMBER(Vendas!$S$2:$S$3001)) | M34: {=IF(K34<AMOSTRA_MIN,"n<mín",MEDIAN(IF((Vendas!$AK$2:$AK$3001="Validado")*(Vendas!$B$2:$B$3001=$A34)*(Vendas!$J$2:$J$3001=$B34)*(Vendas!$P$2:$P$3001="Financiado")*ISNUMBER(Vendas!$S$2:$S$3001),Vendas!$S$2:$S$3001)))} | N34: {=IF(L34<AMOSTRA_MIN,"n<mín",MEDIAN(IF((Vendas!$AK$2:$AK$3001="Validado")*(Vendas!$B$2:$B$3001=$A34)*(Vendas!$J$2:$J$3001=$B34)*(Vendas!$P$2:$P$3001="À vista")*ISNUMBER(Vendas!$S$2:$S$3001),Vendas!$S$2:$S$3001)))} | O34: =IF(OR(K34<AMOSTRA_MIN,L34<AMOSTRA_MIN),"n<mín",N34/M34-1) | P34: =SUMPRODUCT((Vendas!$AK$2:$AK$3001="Validado")*(Vendas!$B$2:$B$3001=$A34)*(Vendas!$J$2:$J$3001=$B34)*ISNUMBER(Vendas!$W$2:$W$3001)) | Q34: {=IF(P34<AMOSTRA_MIN,"n<mín",MEDIAN(IF((Vendas!$AK$2:$AK$3001="Validado")*(Vendas!$B$2:$B$3001=$A34)*(Vendas!$J$2:$J$3001=$B34)*ISNUMBER(Vendas!$W$2:$W$3001),Vendas!$W$2:$W$3001)))} | R34: =IF(P34=0,"-",SUMPRODUCT((Vendas!$AK$2:$AK$3001="Validado")*(Vendas!$B$2:$B$3001=$A34)*(Vendas!$J$2:$J$3001=$B34)*ISNUMBER(Vendas!$W$2:$W$3001)*(Vendas!$W$2:$W$3001<1))/P34) | S34: =SUMPRODUCT((Vendas!$AK$2:$AK$3001="Validado")*(Vendas!$B$2:$B$3001=$A34)*(Vendas!$J$2:$J$3001=$B34)*ISNUMBER(Vendas!$X$2:$X$3001)) | T34: =IF(S34=0,"-",SUMPRODUCT((Vendas!$AK$2:$AK$3001="Validado")*(Vendas!$B$2:$B$3001=$A34)*(Vendas!$J$2:$J$3001=$B34)*ISNUMBER(Vendas!$X$2:$X$3001)*(Vendas!$X$2:$X$3001>=1))/S34)
A35: Bertioga | B35: Baixo | C35: =SUMPRODUCT((Vendas!$AK$2:$AK$3001="Validado")*(Vendas!$B$2:$B$3001=$A35)*(Vendas!$J$2:$J$3001=$B35)) | D35: =SUMPRODUCT((Vendas!$AK$2:$AK$3001="Validado")*(Vendas!$B$2:$B$3001=$A35)*(Vendas!$J$2:$J$3001=$B35)*ISNUMBER(Vendas!$U$2:$U$3001)) | E35: {=IF(D35<AMOSTRA_MIN,"n<mín",MEDIAN(IF((Vendas!$AK$2:$AK$3001="Validado")*(Vendas!$B$2:$B$3001=$A35)*(Vendas!$J$2:$J$3001=$B35)*ISNUMBER(Vendas!$U$2:$U$3001),Vendas!$U$2:$U$3001)))} | F35: =IF(D35=0,"-",SUMPRODUCT((Vendas!$AK$2:$AK$3001="Validado")*(Vendas!$B$2:$B$3001=$A35)*(Vendas!$J$2:$J$3001=$B35)*ISNUMBER(Vendas!$U$2:$U$3001)*(Vendas!$U$2:$U$3001<1))/D35) | G35: {=IF(D35<AMOSTRA_MIN,"n<mín",100*AVERAGE(IF((Vendas!$AK$2:$AK$3001="Validado")*(Vendas!$B$2:$B$3001=$A35)*(Vendas!$J$2:$J$3001=$B35)*ISNUMBER(Vendas!$U$2:$U$3001),ABS(Vendas!$U$2:$U$3001-E35)))/E35)} | H35: =SUMPRODUCT((Vendas!$AK$2:$AK$3001="Validado")*(Vendas!$B$2:$B$3001=$A35)*(Vendas!$J$2:$J$3001=$B35)*ISNUMBER(Vendas!$V$2:$V$3001)) | I35: {=IF(H35<AMOSTRA_MIN,"n<mín",MEDIAN(IF((Vendas!$AK$2:$AK$3001="Validado")*(Vendas!$B$2:$B$3001=$A35)*(Vendas!$J$2:$J$3001=$B35)*ISNUMBER(Vendas!$V$2:$V$3001),Vendas!$V$2:$V$3001)))} | J35: =IF(H35=0,"-",SUMPRODUCT((Vendas!$AK$2:$AK$3001="Validado")*(Vendas!$B$2:$B$3001=$A35)*(Vendas!$J$2:$J$3001=$B35)*ISNUMBER(Vendas!$V$2:$V$3001)*(Vendas!$V$2:$V$3001<=1))/H35) | K35: =SUMPRODUCT((Vendas!$AK$2:$AK$3001="Validado")*(Vendas!$B$2:$B$3001=$A35)*(Vendas!$J$2:$J$3001=$B35)*(Vendas!$P$2:$P$3001="Financiado")*ISNUMBER(Vendas!$S$2:$S$3001)) | L35: =SUMPRODUCT((Vendas!$AK$2:$AK$3001="Validado")*(Vendas!$B$2:$B$3001=$A35)*(Vendas!$J$2:$J$3001=$B35)*(Vendas!$P$2:$P$3001="À vista")*ISNUMBER(Vendas!$S$2:$S$3001)) | M35: {=IF(K35<AMOSTRA_MIN,"n<mín",MEDIAN(IF((Vendas!$AK$2:$AK$3001="Validado")*(Vendas!$B$2:$B$3001=$A35)*(Vendas!$J$2:$J$3001=$B35)*(Vendas!$P$2:$P$3001="Financiado")*ISNUMBER(Vendas!$S$2:$S$3001),Vendas!$S$2:$S$3001)))} | N35: {=IF(L35<AMOSTRA_MIN,"n<mín",MEDIAN(IF((Vendas!$AK$2:$AK$3001="Validado")*(Vendas!$B$2:$B$3001=$A35)*(Vendas!$J$2:$J$3001=$B35)*(Vendas!$P$2:$P$3001="À vista")*ISNUMBER(Vendas!$S$2:$S$3001),Vendas!$S$2:$S$3001)))} | O35: =IF(OR(K35<AMOSTRA_MIN,L35<AMOSTRA_MIN),"n<mín",N35/M35-1) | P35: =SUMPRODUCT((Vendas!$AK$2:$AK$3001="Validado")*(Vendas!$B$2:$B$3001=$A35)*(Vendas!$J$2:$J$3001=$B35)*ISNUMBER(Vendas!$W$2:$W$3001)) | Q35: {=IF(P35<AMOSTRA_MIN,"n<mín",MEDIAN(IF((Vendas!$AK$2:$AK$3001="Validado")*(Vendas!$B$2:$B$3001=$A35)*(Vendas!$J$2:$J$3001=$B35)*ISNUMBER(Vendas!$W$2:$W$3001),Vendas!$W$2:$W$3001)))} | R35: =IF(P35=0,"-",SUMPRODUCT((Vendas!$AK$2:$AK$3001="Validado")*(Vendas!$B$2:$B$3001=$A35)*(Vendas!$J$2:$J$3001=$B35)*ISNUMBER(Vendas!$W$2:$W$3001)*(Vendas!$W$2:$W$3001<1))/P35) | S35: =SUMPRODUCT((Vendas!$AK$2:$AK$3001="Validado")*(Vendas!$B$2:$B$3001=$A35)*(Vendas!$J$2:$J$3001=$B35)*ISNUMBER(Vendas!$X$2:$X$3001)) | T35: =IF(S35=0,"-",SUMPRODUCT((Vendas!$AK$2:$AK$3001="Validado")*(Vendas!$B$2:$B$3001=$A35)*(Vendas!$J$2:$J$3001=$B35)*ISNUMBER(Vendas!$X$2:$X$3001)*(Vendas!$X$2:$X$3001>=1))/S35)
A36: Bertioga | B36: Normal | C36: =SUMPRODUCT((Vendas!$AK$2:$AK$3001="Validado")*(Vendas!$B$2:$B$3001=$A36)*(Vendas!$J$2:$J$3001=$B36)) | D36: =SUMPRODUCT((Vendas!$AK$2:$AK$3001="Validado")*(Vendas!$B$2:$B$3001=$A36)*(Vendas!$J$2:$J$3001=$B36)*ISNUMBER(Vendas!$U$2:$U$3001)) | E36: {=IF(D36<AMOSTRA_MIN,"n<mín",MEDIAN(IF((Vendas!$AK$2:$AK$3001="Validado")*(Vendas!$B$2:$B$3001=$A36)*(Vendas!$J$2:$J$3001=$B36)*ISNUMBER(Vendas!$U$2:$U$3001),Vendas!$U$2:$U$3001)))} | F36: =IF(D36=0,"-",SUMPRODUCT((Vendas!$AK$2:$AK$3001="Validado")*(Vendas!$B$2:$B$3001=$A36)*(Vendas!$J$2:$J$3001=$B36)*ISNUMBER(Vendas!$U$2:$U$3001)*(Vendas!$U$2:$U$3001<1))/D36) | G36: {=IF(D36<AMOSTRA_MIN,"n<mín",100*AVERAGE(IF((Vendas!$AK$2:$AK$3001="Validado")*(Vendas!$B$2:$B$3001=$A36)*(Vendas!$J$2:$J$3001=$B36)*ISNUMBER(Vendas!$U$2:$U$3001),ABS(Vendas!$U$2:$U$3001-E36)))/E36)} | H36: =SUMPRODUCT((Vendas!$AK$2:$AK$3001="Validado")*(Vendas!$B$2:$B$3001=$A36)*(Vendas!$J$2:$J$3001=$B36)*ISNUMBER(Vendas!$V$2:$V$3001)) | I36: {=IF(H36<AMOSTRA_MIN,"n<mín",MEDIAN(IF((Vendas!$AK$2:$AK$3001="Validado")*(Vendas!$B$2:$B$3001=$A36)*(Vendas!$J$2:$J$3001=$B36)*ISNUMBER(Vendas!$V$2:$V$3001),Vendas!$V$2:$V$3001)))} | J36: =IF(H36=0,"-",SUMPRODUCT((Vendas!$AK$2:$AK$3001="Validado")*(Vendas!$B$2:$B$3001=$A36)*(Vendas!$J$2:$J$3001=$B36)*ISNUMBER(Vendas!$V$2:$V$3001)*(Vendas!$V$2:$V$3001<=1))/H36) | K36: =SUMPRODUCT((Vendas!$AK$2:$AK$3001="Validado")*(Vendas!$B$2:$B$3001=$A36)*(Vendas!$J$2:$J$3001=$B36)*(Vendas!$P$2:$P$3001="Financiado")*ISNUMBER(Vendas!$S$2:$S$3001)) | L36: =SUMPRODUCT((Vendas!$AK$2:$AK$3001="Validado")*(Vendas!$B$2:$B$3001=$A36)*(Vendas!$J$2:$J$3001=$B36)*(Vendas!$P$2:$P$3001="À vista")*ISNUMBER(Vendas!$S$2:$S$3001)) | M36: {=IF(K36<AMOSTRA_MIN,"n<mín",MEDIAN(IF((Vendas!$AK$2:$AK$3001="Validado")*(Vendas!$B$2:$B$3001=$A36)*(Vendas!$J$2:$J$3001=$B36)*(Vendas!$P$2:$P$3001="Financiado")*ISNUMBER(Vendas!$S$2:$S$3001),Vendas!$S$2:$S$3001)))} | N36: {=IF(L36<AMOSTRA_MIN,"n<mín",MEDIAN(IF((Vendas!$AK$2:$AK$3001="Validado")*(Vendas!$B$2:$B$3001=$A36)*(Vendas!$J$2:$J$3001=$B36)*(Vendas!$P$2:$P$3001="À vista")*ISNUMBER(Vendas!$S$2:$S$3001),Vendas!$S$2:$S$3001)))} | O36: =IF(OR(K36<AMOSTRA_MIN,L36<AMOSTRA_MIN),"n<mín",N36/M36-1) | P36: =SUMPRODUCT((Vendas!$AK$2:$AK$3001="Validado")*(Vendas!$B$2:$B$3001=$A36)*(Vendas!$J$2:$J$3001=$B36)*ISNUMBER(Vendas!$W$2:$W$3001)) | Q36: {=IF(P36<AMOSTRA_MIN,"n<mín",MEDIAN(IF((Vendas!$AK$2:$AK$3001="Validado")*(Vendas!$B$2:$B$3001=$A36)*(Vendas!$J$2:$J$3001=$B36)*ISNUMBER(Vendas!$W$2:$W$3001),Vendas!$W$2:$W$3001)))} | R36: =IF(P36=0,"-",SUMPRODUCT((Vendas!$AK$2:$AK$3001="Validado")*(Vendas!$B$2:$B$3001=$A36)*(Vendas!$J$2:$J$3001=$B36)*ISNUMBER(Vendas!$W$2:$W$3001)*(Vendas!$W$2:$W$3001<1))/P36) | S36: =SUMPRODUCT((Vendas!$AK$2:$AK$3001="Validado")*(Vendas!$B$2:$B$3001=$A36)*(Vendas!$J$2:$J$3001=$B36)*ISNUMBER(Vendas!$X$2:$X$3001)) | T36: =IF(S36=0,"-",SUMPRODUCT((Vendas!$AK$2:$AK$3001="Validado")*(Vendas!$B$2:$B$3001=$A36)*(Vendas!$J$2:$J$3001=$B36)*ISNUMBER(Vendas!$X$2:$X$3001)*(Vendas!$X$2:$X$3001>=1))/S36)
A37: Bertioga | B37: Alto | C37: =SUMPRODUCT((Vendas!$AK$2:$AK$3001="Validado")*(Vendas!$B$2:$B$3001=$A37)*(Vendas!$J$2:$J$3001=$B37)) | D37: =SUMPRODUCT((Vendas!$AK$2:$AK$3001="Validado")*(Vendas!$B$2:$B$3001=$A37)*(Vendas!$J$2:$J$3001=$B37)*ISNUMBER(Vendas!$U$2:$U$3001)) | E37: {=IF(D37<AMOSTRA_MIN,"n<mín",MEDIAN(IF((Vendas!$AK$2:$AK$3001="Validado")*(Vendas!$B$2:$B$3001=$A37)*(Vendas!$J$2:$J$3001=$B37)*ISNUMBER(Vendas!$U$2:$U$3001),Vendas!$U$2:$U$3001)))} | F37: =IF(D37=0,"-",SUMPRODUCT((Vendas!$AK$2:$AK$3001="Validado")*(Vendas!$B$2:$B$3001=$A37)*(Vendas!$J$2:$J$3001=$B37)*ISNUMBER(Vendas!$U$2:$U$3001)*(Vendas!$U$2:$U$3001<1))/D37) | G37: {=IF(D37<AMOSTRA_MIN,"n<mín",100*AVERAGE(IF((Vendas!$AK$2:$AK$3001="Validado")*(Vendas!$B$2:$B$3001=$A37)*(Vendas!$J$2:$J$3001=$B37)*ISNUMBER(Vendas!$U$2:$U$3001),ABS(Vendas!$U$2:$U$3001-E37)))/E37)} | H37: =SUMPRODUCT((Vendas!$AK$2:$AK$3001="Validado")*(Vendas!$B$2:$B$3001=$A37)*(Vendas!$J$2:$J$3001=$B37)*ISNUMBER(Vendas!$V$2:$V$3001)) | I37: {=IF(H37<AMOSTRA_MIN,"n<mín",MEDIAN(IF((Vendas!$AK$2:$AK$3001="Validado")*(Vendas!$B$2:$B$3001=$A37)*(Vendas!$J$2:$J$3001=$B37)*ISNUMBER(Vendas!$V$2:$V$3001),Vendas!$V$2:$V$3001)))} | J37: =IF(H37=0,"-",SUMPRODUCT((Vendas!$AK$2:$AK$3001="Validado")*(Vendas!$B$2:$B$3001=$A37)*(Vendas!$J$2:$J$3001=$B37)*ISNUMBER(Vendas!$V$2:$V$3001)*(Vendas!$V$2:$V$3001<=1))/H37) | K37: =SUMPRODUCT((Vendas!$AK$2:$AK$3001="Validado")*(Vendas!$B$2:$B$3001=$A37)*(Vendas!$J$2:$J$3001=$B37)*(Vendas!$P$2:$P$3001="Financiado")*ISNUMBER(Vendas!$S$2:$S$3001)) | L37: =SUMPRODUCT((Vendas!$AK$2:$AK$3001="Validado")*(Vendas!$B$2:$B$3001=$A37)*(Vendas!$J$2:$J$3001=$B37)*(Vendas!$P$2:$P$3001="À vista")*ISNUMBER(Vendas!$S$2:$S$3001)) | M37: {=IF(K37<AMOSTRA_MIN,"n<mín",MEDIAN(IF((Vendas!$AK$2:$AK$3001="Validado")*(Vendas!$B$2:$B$3001=$A37)*(Vendas!$J$2:$J$3001=$B37)*(Vendas!$P$2:$P$3001="Financiado")*ISNUMBER(Vendas!$S$2:$S$3001),Vendas!$S$2:$S$3001)))} | N37: {=IF(L37<AMOSTRA_MIN,"n<mín",MEDIAN(IF((Vendas!$AK$2:$AK$3001="Validado")*(Vendas!$B$2:$B$3001=$A37)*(Vendas!$J$2:$J$3001=$B37)*(Vendas!$P$2:$P$3001="À vista")*ISNUMBER(Vendas!$S$2:$S$3001),Vendas!$S$2:$S$3001)))} | O37: =IF(OR(K37<AMOSTRA_MIN,L37<AMOSTRA_MIN),"n<mín",N37/M37-1) | P37: =SUMPRODUCT((Vendas!$AK$2:$AK$3001="Validado")*(Vendas!$B$2:$B$3001=$A37)*(Vendas!$J$2:$J$3001=$B37)*ISNUMBER(Vendas!$W$2:$W$3001)) | Q37: {=IF(P37<AMOSTRA_MIN,"n<mín",MEDIAN(IF((Vendas!$AK$2:$AK$3001="Validado")*(Vendas!$B$2:$B$3001=$A37)*(Vendas!$J$2:$J$3001=$B37)*ISNUMBER(Vendas!$W$2:$W$3001),Vendas!$W$2:$W$3001)))} | R37: =IF(P37=0,"-",SUMPRODUCT((Vendas!$AK$2:$AK$3001="Validado")*(Vendas!$B$2:$B$3001=$A37)*(Vendas!$J$2:$J$3001=$B37)*ISNUMBER(Vendas!$W$2:$W$3001)*(Vendas!$W$2:$W$3001<1))/P37) | S37: =SUMPRODUCT((Vendas!$AK$2:$AK$3001="Validado")*(Vendas!$B$2:$B$3001=$A37)*(Vendas!$J$2:$J$3001=$B37)*ISNUMBER(Vendas!$X$2:$X$3001)) | T37: =IF(S37=0,"-",SUMPRODUCT((Vendas!$AK$2:$AK$3001="Validado")*(Vendas!$B$2:$B$3001=$A37)*(Vendas!$J$2:$J$3001=$B37)*ISNUMBER(Vendas!$X$2:$X$3001)*(Vendas!$X$2:$X$3001>=1))/S37)
A38: Bertioga | B38: Não informado | C38: =SUMPRODUCT((Vendas!$AK$2:$AK$3001="Validado")*(Vendas!$B$2:$B$3001=$A38)*(Vendas!$J$2:$J$3001=$B38)) | D38: =SUMPRODUCT((Vendas!$AK$2:$AK$3001="Validado")*(Vendas!$B$2:$B$3001=$A38)*(Vendas!$J$2:$J$3001=$B38)*ISNUMBER(Vendas!$U$2:$U$3001)) | E38: {=IF(D38<AMOSTRA_MIN,"n<mín",MEDIAN(IF((Vendas!$AK$2:$AK$3001="Validado")*(Vendas!$B$2:$B$3001=$A38)*(Vendas!$J$2:$J$3001=$B38)*ISNUMBER(Vendas!$U$2:$U$3001),Vendas!$U$2:$U$3001)))} | F38: =IF(D38=0,"-",SUMPRODUCT((Vendas!$AK$2:$AK$3001="Validado")*(Vendas!$B$2:$B$3001=$A38)*(Vendas!$J$2:$J$3001=$B38)*ISNUMBER(Vendas!$U$2:$U$3001)*(Vendas!$U$2:$U$3001<1))/D38) | G38: {=IF(D38<AMOSTRA_MIN,"n<mín",100*AVERAGE(IF((Vendas!$AK$2:$AK$3001="Validado")*(Vendas!$B$2:$B$3001=$A38)*(Vendas!$J$2:$J$3001=$B38)*ISNUMBER(Vendas!$U$2:$U$3001),ABS(Vendas!$U$2:$U$3001-E38)))/E38)} | H38: =SUMPRODUCT((Vendas!$AK$2:$AK$3001="Validado")*(Vendas!$B$2:$B$3001=$A38)*(Vendas!$J$2:$J$3001=$B38)*ISNUMBER(Vendas!$V$2:$V$3001)) | I38: {=IF(H38<AMOSTRA_MIN,"n<mín",MEDIAN(IF((Vendas!$AK$2:$AK$3001="Validado")*(Vendas!$B$2:$B$3001=$A38)*(Vendas!$J$2:$J$3001=$B38)*ISNUMBER(Vendas!$V$2:$V$3001),Vendas!$V$2:$V$3001)))} | J38: =IF(H38=0,"-",SUMPRODUCT((Vendas!$AK$2:$AK$3001="Validado")*(Vendas!$B$2:$B$3001=$A38)*(Vendas!$J$2:$J$3001=$B38)*ISNUMBER(Vendas!$V$2:$V$3001)*(Vendas!$V$2:$V$3001<=1))/H38) | K38: =SUMPRODUCT((Vendas!$AK$2:$AK$3001="Validado")*(Vendas!$B$2:$B$3001=$A38)*(Vendas!$J$2:$J$3001=$B38)*(Vendas!$P$2:$P$3001="Financiado")*ISNUMBER(Vendas!$S$2:$S$3001)) | L38: =SUMPRODUCT((Vendas!$AK$2:$AK$3001="Validado")*(Vendas!$B$2:$B$3001=$A38)*(Vendas!$J$2:$J$3001=$B38)*(Vendas!$P$2:$P$3001="À vista")*ISNUMBER(Vendas!$S$2:$S$3001)) | M38: {=IF(K38<AMOSTRA_MIN,"n<mín",MEDIAN(IF((Vendas!$AK$2:$AK$3001="Validado")*(Vendas!$B$2:$B$3001=$A38)*(Vendas!$J$2:$J$3001=$B38)*(Vendas!$P$2:$P$3001="Financiado")*ISNUMBER(Vendas!$S$2:$S$3001),Vendas!$S$2:$S$3001)))} | N38: {=IF(L38<AMOSTRA_MIN,"n<mín",MEDIAN(IF((Vendas!$AK$2:$AK$3001="Validado")*(Vendas!$B$2:$B$3001=$A38)*(Vendas!$J$2:$J$3001=$B38)*(Vendas!$P$2:$P$3001="À vista")*ISNUMBER(Vendas!$S$2:$S$3001),Vendas!$S$2:$S$3001)))} | O38: =IF(OR(K38<AMOSTRA_MIN,L38<AMOSTRA_MIN),"n<mín",N38/M38-1) | P38: =SUMPRODUCT((Vendas!$AK$2:$AK$3001="Validado")*(Vendas!$B$2:$B$3001=$A38)*(Vendas!$J$2:$J$3001=$B38)*ISNUMBER(Vendas!$W$2:$W$3001)) | Q38: {=IF(P38<AMOSTRA_MIN,"n<mín",MEDIAN(IF((Vendas!$AK$2:$AK$3001="Validado")*(Vendas!$B$2:$B$3001=$A38)*(Vendas!$J$2:$J$3001=$B38)*ISNUMBER(Vendas!$W$2:$W$3001),Vendas!$W$2:$W$3001)))} | R38: =IF(P38=0,"-",SUMPRODUCT((Vendas!$AK$2:$AK$3001="Validado")*(Vendas!$B$2:$B$3001=$A38)*(Vendas!$J$2:$J$3001=$B38)*ISNUMBER(Vendas!$W$2:$W$3001)*(Vendas!$W$2:$W$3001<1))/P38) | S38: =SUMPRODUCT((Vendas!$AK$2:$AK$3001="Validado")*(Vendas!$B$2:$B$3001=$A38)*(Vendas!$J$2:$J$3001=$B38)*ISNUMBER(Vendas!$X$2:$X$3001)) | T38: =IF(S38=0,"-",SUMPRODUCT((Vendas!$AK$2:$AK$3001="Validado")*(Vendas!$B$2:$B$3001=$A38)*(Vendas!$J$2:$J$3001=$B38)*ISNUMBER(Vendas!$X$2:$X$3001)*(Vendas!$X$2:$X$3001>=1))/S38)
A41: Por cidade e bairro
A42: Cidade | B42: Bairro | C42: Nº vendas validadas | D42: Nº c/ base ITBI | E42: Mediana Declarado ÷ Base ITBI | F42: % c/ base > declarado | G42: COD Declarado ÷ Base | H42: Nº c/ venal IPTU | I42: Mediana Declarado ÷ Venal | J42: % declarado ≤ venal | K42: Nº financiadas (c/ m²) | L42: Nº à vista (c/ m²) | M42: R$/m² mediano financiadas | N42: R$/m² mediano à vista | O42: Dif. à vista vs financiada | P42: Nº c/ valor leilão | Q42: Mediana Declarado ÷ Leilão | R42: % declarado < leilão | S42: Nº c/ valor financiado | T42: % financiado ≥ declarado
A43: São Sebastião | B43: Enseada | C43: =SUMPRODUCT((Vendas!$AK$2:$AK$3001="Validado")*(Vendas!$B$2:$B$3001=$A43)*(Vendas!$C$2:$C$3001=$B43)) | D43: =SUMPRODUCT((Vendas!$AK$2:$AK$3001="Validado")*(Vendas!$B$2:$B$3001=$A43)*(Vendas!$C$2:$C$3001=$B43)*ISNUMBER(Vendas!$U$2:$U$3001)) | E43: {=IF(D43<AMOSTRA_MIN,"n<mín",MEDIAN(IF((Vendas!$AK$2:$AK$3001="Validado")*(Vendas!$B$2:$B$3001=$A43)*(Vendas!$C$2:$C$3001=$B43)*ISNUMBER(Vendas!$U$2:$U$3001),Vendas!$U$2:$U$3001)))} | F43: =IF(D43=0,"-",SUMPRODUCT((Vendas!$AK$2:$AK$3001="Validado")*(Vendas!$B$2:$B$3001=$A43)*(Vendas!$C$2:$C$3001=$B43)*ISNUMBER(Vendas!$U$2:$U$3001)*(Vendas!$U$2:$U$3001<1))/D43) | G43: {=IF(D43<AMOSTRA_MIN,"n<mín",100*AVERAGE(IF((Vendas!$AK$2:$AK$3001="Validado")*(Vendas!$B$2:$B$3001=$A43)*(Vendas!$C$2:$C$3001=$B43)*ISNUMBER(Vendas!$U$2:$U$3001),ABS(Vendas!$U$2:$U$3001-E43)))/E43)} | H43: =SUMPRODUCT((Vendas!$AK$2:$AK$3001="Validado")*(Vendas!$B$2:$B$3001=$A43)*(Vendas!$C$2:$C$3001=$B43)*ISNUMBER(Vendas!$V$2:$V$3001)) | I43: {=IF(H43<AMOSTRA_MIN,"n<mín",MEDIAN(IF((Vendas!$AK$2:$AK$3001="Validado")*(Vendas!$B$2:$B$3001=$A43)*(Vendas!$C$2:$C$3001=$B43)*ISNUMBER(Vendas!$V$2:$V$3001),Vendas!$V$2:$V$3001)))} | J43: =IF(H43=0,"-",SUMPRODUCT((Vendas!$AK$2:$AK$3001="Validado")*(Vendas!$B$2:$B$3001=$A43)*(Vendas!$C$2:$C$3001=$B43)*ISNUMBER(Vendas!$V$2:$V$3001)*(Vendas!$V$2:$V$3001<=1))/H43) | K43: =SUMPRODUCT((Vendas!$AK$2:$AK$3001="Validado")*(Vendas!$B$2:$B$3001=$A43)*(Vendas!$C$2:$C$3001=$B43)*(Vendas!$P$2:$P$3001="Financiado")*ISNUMBER(Vendas!$S$2:$S$3001)) | L43: =SUMPRODUCT((Vendas!$AK$2:$AK$3001="Validado")*(Vendas!$B$2:$B$3001=$A43)*(Vendas!$C$2:$C$3001=$B43)*(Vendas!$P$2:$P$3001="À vista")*ISNUMBER(Vendas!$S$2:$S$3001)) | M43: {=IF(K43<AMOSTRA_MIN,"n<mín",MEDIAN(IF((Vendas!$AK$2:$AK$3001="Validado")*(Vendas!$B$2:$B$3001=$A43)*(Vendas!$C$2:$C$3001=$B43)*(Vendas!$P$2:$P$3001="Financiado")*ISNUMBER(Vendas!$S$2:$S$3001),Vendas!$S$2:$S$3001)))} | N43: {=IF(L43<AMOSTRA_MIN,"n<mín",MEDIAN(IF((Vendas!$AK$2:$AK$3001="Validado")*(Vendas!$B$2:$B$3001=$A43)*(Vendas!$C$2:$C$3001=$B43)*(Vendas!$P$2:$P$3001="À vista")*ISNUMBER(Vendas!$S$2:$S$3001),Vendas!$S$2:$S$3001)))} | O43: =IF(OR(K43<AMOSTRA_MIN,L43<AMOSTRA_MIN),"n<mín",N43/M43-1) | P43: =SUMPRODUCT((Vendas!$AK$2:$AK$3001="Validado")*(Vendas!$B$2:$B$3001=$A43)*(Vendas!$C$2:$C$3001=$B43)*ISNUMBER(Vendas!$W$2:$W$3001)) | Q43: {=IF(P43<AMOSTRA_MIN,"n<mín",MEDIAN(IF((Vendas!$AK$2:$AK$3001="Validado")*(Vendas!$B$2:$B$3001=$A43)*(Vendas!$C$2:$C$3001=$B43)*ISNUMBER(Vendas!$W$2:$W$3001),Vendas!$W$2:$W$3001)))} | R43: =IF(P43=0,"-",SUMPRODUCT((Vendas!$AK$2:$AK$3001="Validado")*(Vendas!$B$2:$B$3001=$A43)*(Vendas!$C$2:$C$3001=$B43)*ISNUMBER(Vendas!$W$2:$W$3001)*(Vendas!$W$2:$W$3001<1))/P43) | S43: =SUMPRODUCT((Vendas!$AK$2:$AK$3001="Validado")*(Vendas!$B$2:$B$3001=$A43)*(Vendas!$C$2:$C$3001=$B43)*ISNUMBER(Vendas!$X$2:$X$3001)) | T43: =IF(S43=0,"-",SUMPRODUCT((Vendas!$AK$2:$AK$3001="Validado")*(Vendas!$B$2:$B$3001=$A43)*(Vendas!$C$2:$C$3001=$B43)*ISNUMBER(Vendas!$X$2:$X$3001)*(Vendas!$X$2:$X$3001>=1))/S43)
A44: São Sebastião | B44: Jaraguá | C44: =SUMPRODUCT((Vendas!$AK$2:$AK$3001="Validado")*(Vendas!$B$2:$B$3001=$A44)*(Vendas!$C$2:$C$3001=$B44)) | D44: =SUMPRODUCT((Vendas!$AK$2:$AK$3001="Validado")*(Vendas!$B$2:$B$3001=$A44)*(Vendas!$C$2:$C$3001=$B44)*ISNUMBER(Vendas!$U$2:$U$3001)) | E44: {=IF(D44<AMOSTRA_MIN,"n<mín",MEDIAN(IF((Vendas!$AK$2:$AK$3001="Validado")*(Vendas!$B$2:$B$3001=$A44)*(Vendas!$C$2:$C$3001=$B44)*ISNUMBER(Vendas!$U$2:$U$3001),Vendas!$U$2:$U$3001)))} | F44: =IF(D44=0,"-",SUMPRODUCT((Vendas!$AK$2:$AK$3001="Validado")*(Vendas!$B$2:$B$3001=$A44)*(Vendas!$C$2:$C$3001=$B44)*ISNUMBER(Vendas!$U$2:$U$3001)*(Vendas!$U$2:$U$3001<1))/D44) | G44: {=IF(D44<AMOSTRA_MIN,"n<mín",100*AVERAGE(IF((Vendas!$AK$2:$AK$3001="Validado")*(Vendas!$B$2:$B$3001=$A44)*(Vendas!$C$2:$C$3001=$B44)*ISNUMBER(Vendas!$U$2:$U$3001),ABS(Vendas!$U$2:$U$3001-E44)))/E44)} | H44: =SUMPRODUCT((Vendas!$AK$2:$AK$3001="Validado")*(Vendas!$B$2:$B$3001=$A44)*(Vendas!$C$2:$C$3001=$B44)*ISNUMBER(Vendas!$V$2:$V$3001)) | I44: {=IF(H44<AMOSTRA_MIN,"n<mín",MEDIAN(IF((Vendas!$AK$2:$AK$3001="Validado")*(Vendas!$B$2:$B$3001=$A44)*(Vendas!$C$2:$C$3001=$B44)*ISNUMBER(Vendas!$V$2:$V$3001),Vendas!$V$2:$V$3001)))} | J44: =IF(H44=0,"-",SUMPRODUCT((Vendas!$AK$2:$AK$3001="Validado")*(Vendas!$B$2:$B$3001=$A44)*(Vendas!$C$2:$C$3001=$B44)*ISNUMBER(Vendas!$V$2:$V$3001)*(Vendas!$V$2:$V$3001<=1))/H44) | K44: =SUMPRODUCT((Vendas!$AK$2:$AK$3001="Validado")*(Vendas!$B$2:$B$3001=$A44)*(Vendas!$C$2:$C$3001=$B44)*(Vendas!$P$2:$P$3001="Financiado")*ISNUMBER(Vendas!$S$2:$S$3001)) | L44: =SUMPRODUCT((Vendas!$AK$2:$AK$3001="Validado")*(Vendas!$B$2:$B$3001=$A44)*(Vendas!$C$2:$C$3001=$B44)*(Vendas!$P$2:$P$3001="À vista")*ISNUMBER(Vendas!$S$2:$S$3001)) | M44: {=IF(K44<AMOSTRA_MIN,"n<mín",MEDIAN(IF((Vendas!$AK$2:$AK$3001="Validado")*(Vendas!$B$2:$B$3001=$A44)*(Vendas!$C$2:$C$3001=$B44)*(Vendas!$P$2:$P$3001="Financiado")*ISNUMBER(Vendas!$S$2:$S$3001),Vendas!$S$2:$S$3001)))} | N44: {=IF(L44<AMOSTRA_MIN,"n<mín",MEDIAN(IF((Vendas!$AK$2:$AK$3001="Validado")*(Vendas!$B$2:$B$3001=$A44)*(Vendas!$C$2:$C$3001=$B44)*(Vendas!$P$2:$P$3001="À vista")*ISNUMBER(Vendas!$S$2:$S$3001),Vendas!$S$2:$S$3001)))} | O44: =IF(OR(K44<AMOSTRA_MIN,L44<AMOSTRA_MIN),"n<mín",N44/M44-1) | P44: =SUMPRODUCT((Vendas!$AK$2:$AK$3001="Validado")*(Vendas!$B$2:$B$3001=$A44)*(Vendas!$C$2:$C$3001=$B44)*ISNUMBER(Vendas!$W$2:$W$3001)) | Q44: {=IF(P44<AMOSTRA_MIN,"n<mín",MEDIAN(IF((Vendas!$AK$2:$AK$3001="Validado")*(Vendas!$B$2:$B$3001=$A44)*(Vendas!$C$2:$C$3001=$B44)*ISNUMBER(Vendas!$W$2:$W$3001),Vendas!$W$2:$W$3001)))} | R44: =IF(P44=0,"-",SUMPRODUCT((Vendas!$AK$2:$AK$3001="Validado")*(Vendas!$B$2:$B$3001=$A44)*(Vendas!$C$2:$C$3001=$B44)*ISNUMBER(Vendas!$W$2:$W$3001)*(Vendas!$W$2:$W$3001<1))/P44) | S44: =SUMPRODUCT((Vendas!$AK$2:$AK$3001="Validado")*(Vendas!$B$2:$B$3001=$A44)*(Vendas!$C$2:$C$3001=$B44)*ISNUMBER(Vendas!$X$2:$X$3001)) | T44: =IF(S44=0,"-",SUMPRODUCT((Vendas!$AK$2:$AK$3001="Validado")*(Vendas!$B$2:$B$3001=$A44)*(Vendas!$C$2:$C$3001=$B44)*ISNUMBER(Vendas!$X$2:$X$3001)*(Vendas!$X$2:$X$3001>=1))/S44)
A45: São Sebastião | B45: Cigarras | C45: =SUMPRODUCT((Vendas!$AK$2:$AK$3001="Validado")*(Vendas!$B$2:$B$3001=$A45)*(Vendas!$C$2:$C$3001=$B45)) | D45: =SUMPRODUCT((Vendas!$AK$2:$AK$3001="Validado")*(Vendas!$B$2:$B$3001=$A45)*(Vendas!$C$2:$C$3001=$B45)*ISNUMBER(Vendas!$U$2:$U$3001)) | E45: {=IF(D45<AMOSTRA_MIN,"n<mín",MEDIAN(IF((Vendas!$AK$2:$AK$3001="Validado")*(Vendas!$B$2:$B$3001=$A45)*(Vendas!$C$2:$C$3001=$B45)*ISNUMBER(Vendas!$U$2:$U$3001),Vendas!$U$2:$U$3001)))} | F45: =IF(D45=0,"-",SUMPRODUCT((Vendas!$AK$2:$AK$3001="Validado")*(Vendas!$B$2:$B$3001=$A45)*(Vendas!$C$2:$C$3001=$B45)*ISNUMBER(Vendas!$U$2:$U$3001)*(Vendas!$U$2:$U$3001<1))/D45) | G45: {=IF(D45<AMOSTRA_MIN,"n<mín",100*AVERAGE(IF((Vendas!$AK$2:$AK$3001="Validado")*(Vendas!$B$2:$B$3001=$A45)*(Vendas!$C$2:$C$3001=$B45)*ISNUMBER(Vendas!$U$2:$U$3001),ABS(Vendas!$U$2:$U$3001-E45)))/E45)} | H45: =SUMPRODUCT((Vendas!$AK$2:$AK$3001="Validado")*(Vendas!$B$2:$B$3001=$A45)*(Vendas!$C$2:$C$3001=$B45)*ISNUMBER(Vendas!$V$2:$V$3001)) | I45: {=IF(H45<AMOSTRA_MIN,"n<mín",MEDIAN(IF((Vendas!$AK$2:$AK$3001="Validado")*(Vendas!$B$2:$B$3001=$A45)*(Vendas!$C$2:$C$3001=$B45)*ISNUMBER(Vendas!$V$2:$V$3001),Vendas!$V$2:$V$3001)))} | J45: =IF(H45=0,"-",SUMPRODUCT((Vendas!$AK$2:$AK$3001="Validado")*(Vendas!$B$2:$B$3001=$A45)*(Vendas!$C$2:$C$3001=$B45)*ISNUMBER(Vendas!$V$2:$V$3001)*(Vendas!$V$2:$V$3001<=1))/H45) | K45: =SUMPRODUCT((Vendas!$AK$2:$AK$3001="Validado")*(Vendas!$B$2:$B$3001=$A45)*(Vendas!$C$2:$C$3001=$B45)*(Vendas!$P$2:$P$3001="Financiado")*ISNUMBER(Vendas!$S$2:$S$3001)) | L45: =SUMPRODUCT((Vendas!$AK$2:$AK$3001="Validado")*(Vendas!$B$2:$B$3001=$A45)*(Vendas!$C$2:$C$3001=$B45)*(Vendas!$P$2:$P$3001="À vista")*ISNUMBER(Vendas!$S$2:$S$3001)) | M45: {=IF(K45<AMOSTRA_MIN,"n<mín",MEDIAN(IF((Vendas!$AK$2:$AK$3001="Validado")*(Vendas!$B$2:$B$3001=$A45)*(Vendas!$C$2:$C$3001=$B45)*(Vendas!$P$2:$P$3001="Financiado")*ISNUMBER(Vendas!$S$2:$S$3001),Vendas!$S$2:$S$3001)))} | N45: {=IF(L45<AMOSTRA_MIN,"n<mín",MEDIAN(IF((Vendas!$AK$2:$AK$3001="Validado")*(Vendas!$B$2:$B$3001=$A45)*(Vendas!$C$2:$C$3001=$B45)*(Vendas!$P$2:$P$3001="À vista")*ISNUMBER(Vendas!$S$2:$S$3001),Vendas!$S$2:$S$3001)))} | O45: =IF(OR(K45<AMOSTRA_MIN,L45<AMOSTRA_MIN),"n<mín",N45/M45-1) | P45: =SUMPRODUCT((Vendas!$AK$2:$AK$3001="Validado")*(Vendas!$B$2:$B$3001=$A45)*(Vendas!$C$2:$C$3001=$B45)*ISNUMBER(Vendas!$W$2:$W$3001)) | Q45: {=IF(P45<AMOSTRA_MIN,"n<mín",MEDIAN(IF((Vendas!$AK$2:$AK$3001="Validado")*(Vendas!$B$2:$B$3001=$A45)*(Vendas!$C$2:$C$3001=$B45)*ISNUMBER(Vendas!$W$2:$W$3001),Vendas!$W$2:$W$3001)))} | R45: =IF(P45=0,"-",SUMPRODUCT((Vendas!$AK$2:$AK$3001="Validado")*(Vendas!$B$2:$B$3001=$A45)*(Vendas!$C$2:$C$3001=$B45)*ISNUMBER(Vendas!$W$2:$W$3001)*(Vendas!$W$2:$W$3001<1))/P45) | S45: =SUMPRODUCT((Vendas!$AK$2:$AK$3001="Validado")*(Vendas!$B$2:$B$3001=$A45)*(Vendas!$C$2:$C$3001=$B45)*ISNUMBER(Vendas!$X$2:$X$3001)) | T45: =IF(S45=0,"-",SUMPRODUCT((Vendas!$AK$2:$AK$3001="Validado")*(Vendas!$B$2:$B$3001=$A45)*(Vendas!$C$2:$C$3001=$B45)*ISNUMBER(Vendas!$X$2:$X$3001)*(Vendas!$X$2:$X$3001>=1))/S45)
A46: São Sebastião | B46: São Francisco | C46: =SUMPRODUCT((Vendas!$AK$2:$AK$3001="Validado")*(Vendas!$B$2:$B$3001=$A46)*(Vendas!$C$2:$C$3001=$B46)) | D46: =SUMPRODUCT((Vendas!$AK$2:$AK$3001="Validado")*(Vendas!$B$2:$B$3001=$A46)*(Vendas!$C$2:$C$3001=$B46)*ISNUMBER(Vendas!$U$2:$U$3001)) | E46: {=IF(D46<AMOSTRA_MIN,"n<mín",MEDIAN(IF((Vendas!$AK$2:$AK$3001="Validado")*(Vendas!$B$2:$B$3001=$A46)*(Vendas!$C$2:$C$3001=$B46)*ISNUMBER(Vendas!$U$2:$U$3001),Vendas!$U$2:$U$3001)))} | F46: =IF(D46=0,"-",SUMPRODUCT((Vendas!$AK$2:$AK$3001="Validado")*(Vendas!$B$2:$B$3001=$A46)*(Vendas!$C$2:$C$3001=$B46)*ISNUMBER(Vendas!$U$2:$U$3001)*(Vendas!$U$2:$U$3001<1))/D46) | G46: {=IF(D46<AMOSTRA_MIN,"n<mín",100*AVERAGE(IF((Vendas!$AK$2:$AK$3001="Validado")*(Vendas!$B$2:$B$3001=$A46)*(Vendas!$C$2:$C$3001=$B46)*ISNUMBER(Vendas!$U$2:$U$3001),ABS(Vendas!$U$2:$U$3001-E46)))/E46)} | H46: =SUMPRODUCT((Vendas!$AK$2:$AK$3001="Validado")*(Vendas!$B$2:$B$3001=$A46)*(Vendas!$C$2:$C$3001=$B46)*ISNUMBER(Vendas!$V$2:$V$3001)) | I46: {=IF(H46<AMOSTRA_MIN,"n<mín",MEDIAN(IF((Vendas!$AK$2:$AK$3001="Validado")*(Vendas!$B$2:$B$3001=$A46)*(Vendas!$C$2:$C$3001=$B46)*ISNUMBER(Vendas!$V$2:$V$3001),Vendas!$V$2:$V$3001)))} | J46: =IF(H46=0,"-",SUMPRODUCT((Vendas!$AK$2:$AK$3001="Validado")*(Vendas!$B$2:$B$3001=$A46)*(Vendas!$C$2:$C$3001=$B46)*ISNUMBER(Vendas!$V$2:$V$3001)*(Vendas!$V$2:$V$3001<=1))/H46) | K46: =SUMPRODUCT((Vendas!$AK$2:$AK$3001="Validado")*(Vendas!$B$2:$B$3001=$A46)*(Vendas!$C$2:$C$3001=$B46)*(Vendas!$P$2:$P$3001="Financiado")*ISNUMBER(Vendas!$S$2:$S$3001)) | L46: =SUMPRODUCT((Vendas!$AK$2:$AK$3001="Validado")*(Vendas!$B$2:$B$3001=$A46)*(Vendas!$C$2:$C$3001=$B46)*(Vendas!$P$2:$P$3001="À vista")*ISNUMBER(Vendas!$S$2:$S$3001)) | M46: {=IF(K46<AMOSTRA_MIN,"n<mín",MEDIAN(IF((Vendas!$AK$2:$AK$3001="Validado")*(Vendas!$B$2:$B$3001=$A46)*(Vendas!$C$2:$C$3001=$B46)*(Vendas!$P$2:$P$3001="Financiado")*ISNUMBER(Vendas!$S$2:$S$3001),Vendas!$S$2:$S$3001)))} | N46: {=IF(L46<AMOSTRA_MIN,"n<mín",MEDIAN(IF((Vendas!$AK$2:$AK$3001="Validado")*(Vendas!$B$2:$B$3001=$A46)*(Vendas!$C$2:$C$3001=$B46)*(Vendas!$P$2:$P$3001="À vista")*ISNUMBER(Vendas!$S$2:$S$3001),Vendas!$S$2:$S$3001)))} | O46: =IF(OR(K46<AMOSTRA_MIN,L46<AMOSTRA_MIN),"n<mín",N46/M46-1) | P46: =SUMPRODUCT((Vendas!$AK$2:$AK$3001="Validado")*(Vendas!$B$2:$B$3001=$A46)*(Vendas!$C$2:$C$3001=$B46)*ISNUMBER(Vendas!$W$2:$W$3001)) | Q46: {=IF(P46<AMOSTRA_MIN,"n<mín",MEDIAN(IF((Vendas!$AK$2:$AK$3001="Validado")*(Vendas!$B$2:$B$3001=$A46)*(Vendas!$C$2:$C$3001=$B46)*ISNUMBER(Vendas!$W$2:$W$3001),Vendas!$W$2:$W$3001)))} | R46: =IF(P46=0,"-",SUMPRODUCT((Vendas!$AK$2:$AK$3001="Validado")*(Vendas!$B$2:$B$3001=$A46)*(Vendas!$C$2:$C$3001=$B46)*ISNUMBER(Vendas!$W$2:$W$3001)*(Vendas!$W$2:$W$3001<1))/P46) | S46: =SUMPRODUCT((Vendas!$AK$2:$AK$3001="Validado")*(Vendas!$B$2:$B$3001=$A46)*(Vendas!$C$2:$C$3001=$B46)*ISNUMBER(Vendas!$X$2:$X$3001)) | T46: =IF(S46=0,"-",SUMPRODUCT((Vendas!$AK$2:$AK$3001="Validado")*(Vendas!$B$2:$B$3001=$A46)*(Vendas!$C$2:$C$3001=$B46)*ISNUMBER(Vendas!$X$2:$X$3001)*(Vendas!$X$2:$X$3001>=1))/S46)
A47: São Sebastião | B47: Morro do Abrigo | C47: =SUMPRODUCT((Vendas!$AK$2:$AK$3001="Validado")*(Vendas!$B$2:$B$3001=$A47)*(Vendas!$C$2:$C$3001=$B47)) | D47: =SUMPRODUCT((Vendas!$AK$2:$AK$3001="Validado")*(Vendas!$B$2:$B$3001=$A47)*(Vendas!$C$2:$C$3001=$B47)*ISNUMBER(Vendas!$U$2:$U$3001)) | E47: {=IF(D47<AMOSTRA_MIN,"n<mín",MEDIAN(IF((Vendas!$AK$2:$AK$3001="Validado")*(Vendas!$B$2:$B$3001=$A47)*(Vendas!$C$2:$C$3001=$B47)*ISNUMBER(Vendas!$U$2:$U$3001),Vendas!$U$2:$U$3001)))} | F47: =IF(D47=0,"-",SUMPRODUCT((Vendas!$AK$2:$AK$3001="Validado")*(Vendas!$B$2:$B$3001=$A47)*(Vendas!$C$2:$C$3001=$B47)*ISNUMBER(Vendas!$U$2:$U$3001)*(Vendas!$U$2:$U$3001<1))/D47) | G47: {=IF(D47<AMOSTRA_MIN,"n<mín",100*AVERAGE(IF((Vendas!$AK$2:$AK$3001="Validado")*(Vendas!$B$2:$B$3001=$A47)*(Vendas!$C$2:$C$3001=$B47)*ISNUMBER(Vendas!$U$2:$U$3001),ABS(Vendas!$U$2:$U$3001-E47)))/E47)} | H47: =SUMPRODUCT((Vendas!$AK$2:$AK$3001="Validado")*(Vendas!$B$2:$B$3001=$A47)*(Vendas!$C$2:$C$3001=$B47)*ISNUMBER(Vendas!$V$2:$V$3001)) | I47: {=IF(H47<AMOSTRA_MIN,"n<mín",MEDIAN(IF((Vendas!$AK$2:$AK$3001="Validado")*(Vendas!$B$2:$B$3001=$A47)*(Vendas!$C$2:$C$3001=$B47)*ISNUMBER(Vendas!$V$2:$V$3001),Vendas!$V$2:$V$3001)))} | J47: =IF(H47=0,"-",SUMPRODUCT((Vendas!$AK$2:$AK$3001="Validado")*(Vendas!$B$2:$B$3001=$A47)*(Vendas!$C$2:$C$3001=$B47)*ISNUMBER(Vendas!$V$2:$V$3001)*(Vendas!$V$2:$V$3001<=1))/H47) | K47: =SUMPRODUCT((Vendas!$AK$2:$AK$3001="Validado")*(Vendas!$B$2:$B$3001=$A47)*(Vendas!$C$2:$C$3001=$B47)*(Vendas!$P$2:$P$3001="Financiado")*ISNUMBER(Vendas!$S$2:$S$3001)) | L47: =SUMPRODUCT((Vendas!$AK$2:$AK$3001="Validado")*(Vendas!$B$2:$B$3001=$A47)*(Vendas!$C$2:$C$3001=$B47)*(Vendas!$P$2:$P$3001="À vista")*ISNUMBER(Vendas!$S$2:$S$3001)) | M47: {=IF(K47<AMOSTRA_MIN,"n<mín",MEDIAN(IF((Vendas!$AK$2:$AK$3001="Validado")*(Vendas!$B$2:$B$3001=$A47)*(Vendas!$C$2:$C$3001=$B47)*(Vendas!$P$2:$P$3001="Financiado")*ISNUMBER(Vendas!$S$2:$S$3001),Vendas!$S$2:$S$3001)))} | N47: {=IF(L47<AMOSTRA_MIN,"n<mín",MEDIAN(IF((Vendas!$AK$2:$AK$3001="Validado")*(Vendas!$B$2:$B$3001=$A47)*(Vendas!$C$2:$C$3001=$B47)*(Vendas!$P$2:$P$3001="À vista")*ISNUMBER(Vendas!$S$2:$S$3001),Vendas!$S$2:$S$3001)))} | O47: =IF(OR(K47<AMOSTRA_MIN,L47<AMOSTRA_MIN),"n<mín",N47/M47-1) | P47: =SUMPRODUCT((Vendas!$AK$2:$AK$3001="Validado")*(Vendas!$B$2:$B$3001=$A47)*(Vendas!$C$2:$C$3001=$B47)*ISNUMBER(Vendas!$W$2:$W$3001)) | Q47: {=IF(P47<AMOSTRA_MIN,"n<mín",MEDIAN(IF((Vendas!$AK$2:$AK$3001="Validado")*(Vendas!$B$2:$B$3001=$A47)*(Vendas!$C$2:$C$3001=$B47)*ISNUMBER(Vendas!$W$2:$W$3001),Vendas!$W$2:$W$3001)))} | R47: =IF(P47=0,"-",SUMPRODUCT((Vendas!$AK$2:$AK$3001="Validado")*(Vendas!$B$2:$B$3001=$A47)*(Vendas!$C$2:$C$3001=$B47)*ISNUMBER(Vendas!$W$2:$W$3001)*(Vendas!$W$2:$W$3001<1))/P47) | S47: =SUMPRODUCT((Vendas!$AK$2:$AK$3001="Validado")*(Vendas!$B$2:$B$3001=$A47)*(Vendas!$C$2:$C$3001=$B47)*ISNUMBER(Vendas!$X$2:$X$3001)) | T47: =IF(S47=0,"-",SUMPRODUCT((Vendas!$AK$2:$AK$3001="Validado")*(Vendas!$B$2:$B$3001=$A47)*(Vendas!$C$2:$C$3001=$B47)*ISNUMBER(Vendas!$X$2:$X$3001)*(Vendas!$X$2:$X$3001>=1))/S47)
A48: São Sebastião | B48: Olaria | C48: =SUMPRODUCT((Vendas!$AK$2:$AK$3001="Validado")*(Vendas!$B$2:$B$3001=$A48)*(Vendas!$C$2:$C$3001=$B48)) | D48: =SUMPRODUCT((Vendas!$AK$2:$AK$3001="Validado")*(Vendas!$B$2:$B$3001=$A48)*(Vendas!$C$2:$C$3001=$B48)*ISNUMBER(Vendas!$U$2:$U$3001)) | E48: {=IF(D48<AMOSTRA_MIN,"n<mín",MEDIAN(IF((Vendas!$AK$2:$AK$3001="Validado")*(Vendas!$B$2:$B$3001=$A48)*(Vendas!$C$2:$C$3001=$B48)*ISNUMBER(Vendas!$U$2:$U$3001),Vendas!$U$2:$U$3001)))} | F48: =IF(D48=0,"-",SUMPRODUCT((Vendas!$AK$2:$AK$3001="Validado")*(Vendas!$B$2:$B$3001=$A48)*(Vendas!$C$2:$C$3001=$B48)*ISNUMBER(Vendas!$U$2:$U$3001)*(Vendas!$U$2:$U$3001<1))/D48) | G48: {=IF(D48<AMOSTRA_MIN,"n<mín",100*AVERAGE(IF((Vendas!$AK$2:$AK$3001="Validado")*(Vendas!$B$2:$B$3001=$A48)*(Vendas!$C$2:$C$3001=$B48)*ISNUMBER(Vendas!$U$2:$U$3001),ABS(Vendas!$U$2:$U$3001-E48)))/E48)} | H48: =SUMPRODUCT((Vendas!$AK$2:$AK$3001="Validado")*(Vendas!$B$2:$B$3001=$A48)*(Vendas!$C$2:$C$3001=$B48)*ISNUMBER(Vendas!$V$2:$V$3001)) | I48: {=IF(H48<AMOSTRA_MIN,"n<mín",MEDIAN(IF((Vendas!$AK$2:$AK$3001="Validado")*(Vendas!$B$2:$B$3001=$A48)*(Vendas!$C$2:$C$3001=$B48)*ISNUMBER(Vendas!$V$2:$V$3001),Vendas!$V$2:$V$3001)))} | J48: =IF(H48=0,"-",SUMPRODUCT((Vendas!$AK$2:$AK$3001="Validado")*(Vendas!$B$2:$B$3001=$A48)*(Vendas!$C$2:$C$3001=$B48)*ISNUMBER(Vendas!$V$2:$V$3001)*(Vendas!$V$2:$V$3001<=1))/H48) | K48: =SUMPRODUCT((Vendas!$AK$2:$AK$3001="Validado")*(Vendas!$B$2:$B$3001=$A48)*(Vendas!$C$2:$C$3001=$B48)*(Vendas!$P$2:$P$3001="Financiado")*ISNUMBER(Vendas!$S$2:$S$3001)) | L48: =SUMPRODUCT((Vendas!$AK$2:$AK$3001="Validado")*(Vendas!$B$2:$B$3001=$A48)*(Vendas!$C$2:$C$3001=$B48)*(Vendas!$P$2:$P$3001="À vista")*ISNUMBER(Vendas!$S$2:$S$3001)) | M48: {=IF(K48<AMOSTRA_MIN,"n<mín",MEDIAN(IF((Vendas!$AK$2:$AK$3001="Validado")*(Vendas!$B$2:$B$3001=$A48)*(Vendas!$C$2:$C$3001=$B48)*(Vendas!$P$2:$P$3001="Financiado")*ISNUMBER(Vendas!$S$2:$S$3001),Vendas!$S$2:$S$3001)))} | N48: {=IF(L48<AMOSTRA_MIN,"n<mín",MEDIAN(IF((Vendas!$AK$2:$AK$3001="Validado")*(Vendas!$B$2:$B$3001=$A48)*(Vendas!$C$2:$C$3001=$B48)*(Vendas!$P$2:$P$3001="À vista")*ISNUMBER(Vendas!$S$2:$S$3001),Vendas!$S$2:$S$3001)))} | O48: =IF(OR(K48<AMOSTRA_MIN,L48<AMOSTRA_MIN),"n<mín",N48/M48-1) | P48: =SUMPRODUCT((Vendas!$AK$2:$AK$3001="Validado")*(Vendas!$B$2:$B$3001=$A48)*(Vendas!$C$2:$C$3001=$B48)*ISNUMBER(Vendas!$W$2:$W$3001)) | Q48: {=IF(P48<AMOSTRA_MIN,"n<mín",MEDIAN(IF((Vendas!$AK$2:$AK$3001="Validado")*(Vendas!$B$2:$B$3001=$A48)*(Vendas!$C$2:$C$3001=$B48)*ISNUMBER(Vendas!$W$2:$W$3001),Vendas!$W$2:$W$3001)))} | R48: =IF(P48=0,"-",SUMPRODUCT((Vendas!$AK$2:$AK$3001="Validado")*(Vendas!$B$2:$B$3001=$A48)*(Vendas!$C$2:$C$3001=$B48)*ISNUMBER(Vendas!$W$2:$W$3001)*(Vendas!$W$2:$W$3001<1))/P48) | S48: =SUMPRODUCT((Vendas!$AK$2:$AK$3001="Validado")*(Vendas!$B$2:$B$3001=$A48)*(Vendas!$C$2:$C$3001=$B48)*ISNUMBER(Vendas!$X$2:$X$3001)) | T48: =IF(S48=0,"-",SUMPRODUCT((Vendas!$AK$2:$AK$3001="Validado")*(Vendas!$B$2:$B$3001=$A48)*(Vendas!$C$2:$C$3001=$B48)*ISNUMBER(Vendas!$X$2:$X$3001)*(Vendas!$X$2:$X$3001>=1))/S48)
A49: São Sebastião | B49: Arrastão | C49: =SUMPRODUCT((Vendas!$AK$2:$AK$3001="Validado")*(Vendas!$B$2:$B$3001=$A49)*(Vendas!$C$2:$C$3001=$B49)) | D49: =SUMPRODUCT((Vendas!$AK$2:$AK$3001="Validado")*(Vendas!$B$2:$B$3001=$A49)*(Vendas!$C$2:$C$3001=$B49)*ISNUMBER(Vendas!$U$2:$U$3001)) | E49: {=IF(D49<AMOSTRA_MIN,"n<mín",MEDIAN(IF((Vendas!$AK$2:$AK$3001="Validado")*(Vendas!$B$2:$B$3001=$A49)*(Vendas!$C$2:$C$3001=$B49)*ISNUMBER(Vendas!$U$2:$U$3001),Vendas!$U$2:$U$3001)))} | F49: =IF(D49=0,"-",SUMPRODUCT((Vendas!$AK$2:$AK$3001="Validado")*(Vendas!$B$2:$B$3001=$A49)*(Vendas!$C$2:$C$3001=$B49)*ISNUMBER(Vendas!$U$2:$U$3001)*(Vendas!$U$2:$U$3001<1))/D49) | G49: {=IF(D49<AMOSTRA_MIN,"n<mín",100*AVERAGE(IF((Vendas!$AK$2:$AK$3001="Validado")*(Vendas!$B$2:$B$3001=$A49)*(Vendas!$C$2:$C$3001=$B49)*ISNUMBER(Vendas!$U$2:$U$3001),ABS(Vendas!$U$2:$U$3001-E49)))/E49)} | H49: =SUMPRODUCT((Vendas!$AK$2:$AK$3001="Validado")*(Vendas!$B$2:$B$3001=$A49)*(Vendas!$C$2:$C$3001=$B49)*ISNUMBER(Vendas!$V$2:$V$3001)) | I49: {=IF(H49<AMOSTRA_MIN,"n<mín",MEDIAN(IF((Vendas!$AK$2:$AK$3001="Validado")*(Vendas!$B$2:$B$3001=$A49)*(Vendas!$C$2:$C$3001=$B49)*ISNUMBER(Vendas!$V$2:$V$3001),Vendas!$V$2:$V$3001)))} | J49: =IF(H49=0,"-",SUMPRODUCT((Vendas!$AK$2:$AK$3001="Validado")*(Vendas!$B$2:$B$3001=$A49)*(Vendas!$C$2:$C$3001=$B49)*ISNUMBER(Vendas!$V$2:$V$3001)*(Vendas!$V$2:$V$3001<=1))/H49) | K49: =SUMPRODUCT((Vendas!$AK$2:$AK$3001="Validado")*(Vendas!$B$2:$B$3001=$A49)*(Vendas!$C$2:$C$3001=$B49)*(Vendas!$P$2:$P$3001="Financiado")*ISNUMBER(Vendas!$S$2:$S$3001)) | L49: =SUMPRODUCT((Vendas!$AK$2:$AK$3001="Validado")*(Vendas!$B$2:$B$3001=$A49)*(Vendas!$C$2:$C$3001=$B49)*(Vendas!$P$2:$P$3001="À vista")*ISNUMBER(Vendas!$S$2:$S$3001)) | M49: {=IF(K49<AMOSTRA_MIN,"n<mín",MEDIAN(IF((Vendas!$AK$2:$AK$3001="Validado")*(Vendas!$B$2:$B$3001=$A49)*(Vendas!$C$2:$C$3001=$B49)*(Vendas!$P$2:$P$3001="Financiado")*ISNUMBER(Vendas!$S$2:$S$3001),Vendas!$S$2:$S$3001)))} | N49: {=IF(L49<AMOSTRA_MIN,"n<mín",MEDIAN(IF((Vendas!$AK$2:$AK$3001="Validado")*(Vendas!$B$2:$B$3001=$A49)*(Vendas!$C$2:$C$3001=$B49)*(Vendas!$P$2:$P$3001="À vista")*ISNUMBER(Vendas!$S$2:$S$3001),Vendas!$S$2:$S$3001)))} | O49: =IF(OR(K49<AMOSTRA_MIN,L49<AMOSTRA_MIN),"n<mín",N49/M49-1) | P49: =SUMPRODUCT((Vendas!$AK$2:$AK$3001="Validado")*(Vendas!$B$2:$B$3001=$A49)*(Vendas!$C$2:$C$3001=$B49)*ISNUMBER(Vendas!$W$2:$W$3001)) | Q49: {=IF(P49<AMOSTRA_MIN,"n<mín",MEDIAN(IF((Vendas!$AK$2:$AK$3001="Validado")*(Vendas!$B$2:$B$3001=$A49)*(Vendas!$C$2:$C$3001=$B49)*ISNUMBER(Vendas!$W$2:$W$3001),Vendas!$W$2:$W$3001)))} | R49: =IF(P49=0,"-",SUMPRODUCT((Vendas!$AK$2:$AK$3001="Validado")*(Vendas!$B$2:$B$3001=$A49)*(Vendas!$C$2:$C$3001=$B49)*ISNUMBER(Vendas!$W$2:$W$3001)*(Vendas!$W$2:$W$3001<1))/P49) | S49: =SUMPRODUCT((Vendas!$AK$2:$AK$3001="Validado")*(Vendas!$B$2:$B$3001=$A49)*(Vendas!$C$2:$C$3001=$B49)*ISNUMBER(Vendas!$X$2:$X$3001)) | T49: =IF(S49=0,"-",SUMPRODUCT((Vendas!$AK$2:$AK$3001="Validado")*(Vendas!$B$2:$B$3001=$A49)*(Vendas!$C$2:$C$3001=$B49)*ISNUMBER(Vendas!$X$2:$X$3001)*(Vendas!$X$2:$X$3001>=1))/S49)
A50: São Sebastião | B50: Pontal da Cruz | C50: =SUMPRODUCT((Vendas!$AK$2:$AK$3001="Validado")*(Vendas!$B$2:$B$3001=$A50)*(Vendas!$C$2:$C$3001=$B50)) | D50: =SUMPRODUCT((Vendas!$AK$2:$AK$3001="Validado")*(Vendas!$B$2:$B$3001=$A50)*(Vendas!$C$2:$C$3001=$B50)*ISNUMBER(Vendas!$U$2:$U$3001)) | E50: {=IF(D50<AMOSTRA_MIN,"n<mín",MEDIAN(IF((Vendas!$AK$2:$AK$3001="Validado")*(Vendas!$B$2:$B$3001=$A50)*(Vendas!$C$2:$C$3001=$B50)*ISNUMBER(Vendas!$U$2:$U$3001),Vendas!$U$2:$U$3001)))} | F50: =IF(D50=0,"-",SUMPRODUCT((Vendas!$AK$2:$AK$3001="Validado")*(Vendas!$B$2:$B$3001=$A50)*(Vendas!$C$2:$C$3001=$B50)*ISNUMBER(Vendas!$U$2:$U$3001)*(Vendas!$U$2:$U$3001<1))/D50) | G50: {=IF(D50<AMOSTRA_MIN,"n<mín",100*AVERAGE(IF((Vendas!$AK$2:$AK$3001="Validado")*(Vendas!$B$2:$B$3001=$A50)*(Vendas!$C$2:$C$3001=$B50)*ISNUMBER(Vendas!$U$2:$U$3001),ABS(Vendas!$U$2:$U$3001-E50)))/E50)} | H50: =SUMPRODUCT((Vendas!$AK$2:$AK$3001="Validado")*(Vendas!$B$2:$B$3001=$A50)*(Vendas!$C$2:$C$3001=$B50)*ISNUMBER(Vendas!$V$2:$V$3001)) | I50: {=IF(H50<AMOSTRA_MIN,"n<mín",MEDIAN(IF((Vendas!$AK$2:$AK$3001="Validado")*(Vendas!$B$2:$B$3001=$A50)*(Vendas!$C$2:$C$3001=$B50)*ISNUMBER(Vendas!$V$2:$V$3001),Vendas!$V$2:$V$3001)))} | J50: =IF(H50=0,"-",SUMPRODUCT((Vendas!$AK$2:$AK$3001="Validado")*(Vendas!$B$2:$B$3001=$A50)*(Vendas!$C$2:$C$3001=$B50)*ISNUMBER(Vendas!$V$2:$V$3001)*(Vendas!$V$2:$V$3001<=1))/H50) | K50: =SUMPRODUCT((Vendas!$AK$2:$AK$3001="Validado")*(Vendas!$B$2:$B$3001=$A50)*(Vendas!$C$2:$C$3001=$B50)*(Vendas!$P$2:$P$3001="Financiado")*ISNUMBER(Vendas!$S$2:$S$3001)) | L50: =SUMPRODUCT((Vendas!$AK$2:$AK$3001="Validado")*(Vendas!$B$2:$B$3001=$A50)*(Vendas!$C$2:$C$3001=$B50)*(Vendas!$P$2:$P$3001="À vista")*ISNUMBER(Vendas!$S$2:$S$3001)) | M50: {=IF(K50<AMOSTRA_MIN,"n<mín",MEDIAN(IF((Vendas!$AK$2:$AK$3001="Validado")*(Vendas!$B$2:$B$3001=$A50)*(Vendas!$C$2:$C$3001=$B50)*(Vendas!$P$2:$P$3001="Financiado")*ISNUMBER(Vendas!$S$2:$S$3001),Vendas!$S$2:$S$3001)))} | N50: {=IF(L50<AMOSTRA_MIN,"n<mín",MEDIAN(IF((Vendas!$AK$2:$AK$3001="Validado")*(Vendas!$B$2:$B$3001=$A50)*(Vendas!$C$2:$C$3001=$B50)*(Vendas!$P$2:$P$3001="À vista")*ISNUMBER(Vendas!$S$2:$S$3001),Vendas!$S$2:$S$3001)))} | O50: =IF(OR(K50<AMOSTRA_MIN,L50<AMOSTRA_MIN),"n<mín",N50/M50-1) | P50: =SUMPRODUCT((Vendas!$AK$2:$AK$3001="Validado")*(Vendas!$B$2:$B$3001=$A50)*(Vendas!$C$2:$C$3001=$B50)*ISNUMBER(Vendas!$W$2:$W$3001)) | Q50: {=IF(P50<AMOSTRA_MIN,"n<mín",MEDIAN(IF((Vendas!$AK$2:$AK$3001="Validado")*(Vendas!$B$2:$B$3001=$A50)*(Vendas!$C$2:$C$3001=$B50)*ISNUMBER(Vendas!$W$2:$W$3001),Vendas!$W$2:$W$3001)))} | R50: =IF(P50=0,"-",SUMPRODUCT((Vendas!$AK$2:$AK$3001="Validado")*(Vendas!$B$2:$B$3001=$A50)*(Vendas!$C$2:$C$3001=$B50)*ISNUMBER(Vendas!$W$2:$W$3001)*(Vendas!$W$2:$W$3001<1))/P50) | S50: =SUMPRODUCT((Vendas!$AK$2:$AK$3001="Validado")*(Vendas!$B$2:$B$3001=$A50)*(Vendas!$C$2:$C$3001=$B50)*ISNUMBER(Vendas!$X$2:$X$3001)) | T50: =IF(S50=0,"-",SUMPRODUCT((Vendas!$AK$2:$AK$3001="Validado")*(Vendas!$B$2:$B$3001=$A50)*(Vendas!$C$2:$C$3001=$B50)*ISNUMBER(Vendas!$X$2:$X$3001)*(Vendas!$X$2:$X$3001>=1))/S50)
A51: São Sebastião | B51: Praia Deserta | C51: =SUMPRODUCT((Vendas!$AK$2:$AK$3001="Validado")*(Vendas!$B$2:$B$3001=$A51)*(Vendas!$C$2:$C$3001=$B51)) | D51: =SUMPRODUCT((Vendas!$AK$2:$AK$3001="Validado")*(Vendas!$B$2:$B$3001=$A51)*(Vendas!$C$2:$C$3001=$B51)*ISNUMBER(Vendas!$U$2:$U$3001)) | E51: {=IF(D51<AMOSTRA_MIN,"n<mín",MEDIAN(IF((Vendas!$AK$2:$AK$3001="Validado")*(Vendas!$B$2:$B$3001=$A51)*(Vendas!$C$2:$C$3001=$B51)*ISNUMBER(Vendas!$U$2:$U$3001),Vendas!$U$2:$U$3001)))} | F51: =IF(D51=0,"-",SUMPRODUCT((Vendas!$AK$2:$AK$3001="Validado")*(Vendas!$B$2:$B$3001=$A51)*(Vendas!$C$2:$C$3001=$B51)*ISNUMBER(Vendas!$U$2:$U$3001)*(Vendas!$U$2:$U$3001<1))/D51) | G51: {=IF(D51<AMOSTRA_MIN,"n<mín",100*AVERAGE(IF((Vendas!$AK$2:$AK$3001="Validado")*(Vendas!$B$2:$B$3001=$A51)*(Vendas!$C$2:$C$3001=$B51)*ISNUMBER(Vendas!$U$2:$U$3001),ABS(Vendas!$U$2:$U$3001-E51)))/E51)} | H51: =SUMPRODUCT((Vendas!$AK$2:$AK$3001="Validado")*(Vendas!$B$2:$B$3001=$A51)*(Vendas!$C$2:$C$3001=$B51)*ISNUMBER(Vendas!$V$2:$V$3001)) | I51: {=IF(H51<AMOSTRA_MIN,"n<mín",MEDIAN(IF((Vendas!$AK$2:$AK$3001="Validado")*(Vendas!$B$2:$B$3001=$A51)*(Vendas!$C$2:$C$3001=$B51)*ISNUMBER(Vendas!$V$2:$V$3001),Vendas!$V$2:$V$3001)))} | J51: =IF(H51=0,"-",SUMPRODUCT((Vendas!$AK$2:$AK$3001="Validado")*(Vendas!$B$2:$B$3001=$A51)*(Vendas!$C$2:$C$3001=$B51)*ISNUMBER(Vendas!$V$2:$V$3001)*(Vendas!$V$2:$V$3001<=1))/H51) | K51: =SUMPRODUCT((Vendas!$AK$2:$AK$3001="Validado")*(Vendas!$B$2:$B$3001=$A51)*(Vendas!$C$2:$C$3001=$B51)*(Vendas!$P$2:$P$3001="Financiado")*ISNUMBER(Vendas!$S$2:$S$3001)) | L51: =SUMPRODUCT((Vendas!$AK$2:$AK$3001="Validado")*(Vendas!$B$2:$B$3001=$A51)*(Vendas!$C$2:$C$3001=$B51)*(Vendas!$P$2:$P$3001="À vista")*ISNUMBER(Vendas!$S$2:$S$3001)) | M51: {=IF(K51<AMOSTRA_MIN,"n<mín",MEDIAN(IF((Vendas!$AK$2:$AK$3001="Validado")*(Vendas!$B$2:$B$3001=$A51)*(Vendas!$C$2:$C$3001=$B51)*(Vendas!$P$2:$P$3001="Financiado")*ISNUMBER(Vendas!$S$2:$S$3001),Vendas!$S$2:$S$3001)))} | N51: {=IF(L51<AMOSTRA_MIN,"n<mín",MEDIAN(IF((Vendas!$AK$2:$AK$3001="Validado")*(Vendas!$B$2:$B$3001=$A51)*(Vendas!$C$2:$C$3001=$B51)*(Vendas!$P$2:$P$3001="À vista")*ISNUMBER(Vendas!$S$2:$S$3001),Vendas!$S$2:$S$3001)))} | O51: =IF(OR(K51<AMOSTRA_MIN,L51<AMOSTRA_MIN),"n<mín",N51/M51-1) | P51: =SUMPRODUCT((Vendas!$AK$2:$AK$3001="Validado")*(Vendas!$B$2:$B$3001=$A51)*(Vendas!$C$2:$C$3001=$B51)*ISNUMBER(Vendas!$W$2:$W$3001)) | Q51: {=IF(P51<AMOSTRA_MIN,"n<mín",MEDIAN(IF((Vendas!$AK$2:$AK$3001="Validado")*(Vendas!$B$2:$B$3001=$A51)*(Vendas!$C$2:$C$3001=$B51)*ISNUMBER(Vendas!$W$2:$W$3001),Vendas!$W$2:$W$3001)))} | R51: =IF(P51=0,"-",SUMPRODUCT((Vendas!$AK$2:$AK$3001="Validado")*(Vendas!$B$2:$B$3001=$A51)*(Vendas!$C$2:$C$3001=$B51)*ISNUMBER(Vendas!$W$2:$W$3001)*(Vendas!$W$2:$W$3001<1))/P51) | S51: =SUMPRODUCT((Vendas!$AK$2:$AK$3001="Validado")*(Vendas!$B$2:$B$3001=$A51)*(Vendas!$C$2:$C$3001=$B51)*ISNUMBER(Vendas!$X$2:$X$3001)) | T51: =IF(S51=0,"-",SUMPRODUCT((Vendas!$AK$2:$AK$3001="Validado")*(Vendas!$B$2:$B$3001=$A51)*(Vendas!$C$2:$C$3001=$B51)*ISNUMBER(Vendas!$X$2:$X$3001)*(Vendas!$X$2:$X$3001>=1))/S51)
A52: São Sebastião | B52: Porto Grande | C52: =SUMPRODUCT((Vendas!$AK$2:$AK$3001="Validado")*(Vendas!$B$2:$B$3001=$A52)*(Vendas!$C$2:$C$3001=$B52)) | D52: =SUMPRODUCT((Vendas!$AK$2:$AK$3001="Validado")*(Vendas!$B$2:$B$3001=$A52)*(Vendas!$C$2:$C$3001=$B52)*ISNUMBER(Vendas!$U$2:$U$3001)) | E52: {=IF(D52<AMOSTRA_MIN,"n<mín",MEDIAN(IF((Vendas!$AK$2:$AK$3001="Validado")*(Vendas!$B$2:$B$3001=$A52)*(Vendas!$C$2:$C$3001=$B52)*ISNUMBER(Vendas!$U$2:$U$3001),Vendas!$U$2:$U$3001)))} | F52: =IF(D52=0,"-",SUMPRODUCT((Vendas!$AK$2:$AK$3001="Validado")*(Vendas!$B$2:$B$3001=$A52)*(Vendas!$C$2:$C$3001=$B52)*ISNUMBER(Vendas!$U$2:$U$3001)*(Vendas!$U$2:$U$3001<1))/D52) | G52: {=IF(D52<AMOSTRA_MIN,"n<mín",100*AVERAGE(IF((Vendas!$AK$2:$AK$3001="Validado")*(Vendas!$B$2:$B$3001=$A52)*(Vendas!$C$2:$C$3001=$B52)*ISNUMBER(Vendas!$U$2:$U$3001),ABS(Vendas!$U$2:$U$3001-E52)))/E52)} | H52: =SUMPRODUCT((Vendas!$AK$2:$AK$3001="Validado")*(Vendas!$B$2:$B$3001=$A52)*(Vendas!$C$2:$C$3001=$B52)*ISNUMBER(Vendas!$V$2:$V$3001)) | I52: {=IF(H52<AMOSTRA_MIN,"n<mín",MEDIAN(IF((Vendas!$AK$2:$AK$3001="Validado")*(Vendas!$B$2:$B$3001=$A52)*(Vendas!$C$2:$C$3001=$B52)*ISNUMBER(Vendas!$V$2:$V$3001),Vendas!$V$2:$V$3001)))} | J52: =IF(H52=0,"-",SUMPRODUCT((Vendas!$AK$2:$AK$3001="Validado")*(Vendas!$B$2:$B$3001=$A52)*(Vendas!$C$2:$C$3001=$B52)*ISNUMBER(Vendas!$V$2:$V$3001)*(Vendas!$V$2:$V$3001<=1))/H52) | K52: =SUMPRODUCT((Vendas!$AK$2:$AK$3001="Validado")*(Vendas!$B$2:$B$3001=$A52)*(Vendas!$C$2:$C$3001=$B52)*(Vendas!$P$2:$P$3001="Financiado")*ISNUMBER(Vendas!$S$2:$S$3001)) | L52: =SUMPRODUCT((Vendas!$AK$2:$AK$3001="Validado")*(Vendas!$B$2:$B$3001=$A52)*(Vendas!$C$2:$C$3001=$B52)*(Vendas!$P$2:$P$3001="À vista")*ISNUMBER(Vendas!$S$2:$S$3001)) | M52: {=IF(K52<AMOSTRA_MIN,"n<mín",MEDIAN(IF((Vendas!$AK$2:$AK$3001="Validado")*(Vendas!$B$2:$B$3001=$A52)*(Vendas!$C$2:$C$3001=$B52)*(Vendas!$P$2:$P$3001="Financiado")*ISNUMBER(Vendas!$S$2:$S$3001),Vendas!$S$2:$S$3001)))} | N52: {=IF(L52<AMOSTRA_MIN,"n<mín",MEDIAN(IF((Vendas!$AK$2:$AK$3001="Validado")*(Vendas!$B$2:$B$3001=$A52)*(Vendas!$C$2:$C$3001=$B52)*(Vendas!$P$2:$P$3001="À vista")*ISNUMBER(Vendas!$S$2:$S$3001),Vendas!$S$2:$S$3001)))} | O52: =IF(OR(K52<AMOSTRA_MIN,L52<AMOSTRA_MIN),"n<mín",N52/M52-1) | P52: =SUMPRODUCT((Vendas!$AK$2:$AK$3001="Validado")*(Vendas!$B$2:$B$3001=$A52)*(Vendas!$C$2:$C$3001=$B52)*ISNUMBER(Vendas!$W$2:$W$3001)) | Q52: {=IF(P52<AMOSTRA_MIN,"n<mín",MEDIAN(IF((Vendas!$AK$2:$AK$3001="Validado")*(Vendas!$B$2:$B$3001=$A52)*(Vendas!$C$2:$C$3001=$B52)*ISNUMBER(Vendas!$W$2:$W$3001),Vendas!$W$2:$W$3001)))} | R52: =IF(P52=0,"-",SUMPRODUCT((Vendas!$AK$2:$AK$3001="Validado")*(Vendas!$B$2:$B$3001=$A52)*(Vendas!$C$2:$C$3001=$B52)*ISNUMBER(Vendas!$W$2:$W$3001)*(Vendas!$W$2:$W$3001<1))/P52) | S52: =SUMPRODUCT((Vendas!$AK$2:$AK$3001="Validado")*(Vendas!$B$2:$B$3001=$A52)*(Vendas!$C$2:$C$3001=$B52)*ISNUMBER(Vendas!$X$2:$X$3001)) | T52: =IF(S52=0,"-",SUMPRODUCT((Vendas!$AK$2:$AK$3001="Validado")*(Vendas!$B$2:$B$3001=$A52)*(Vendas!$C$2:$C$3001=$B52)*ISNUMBER(Vendas!$X$2:$X$3001)*(Vendas!$X$2:$X$3001>=1))/S52)
A53: São Sebastião | B53: Centro | C53: =SUMPRODUCT((Vendas!$AK$2:$AK$3001="Validado")*(Vendas!$B$2:$B$3001=$A53)*(Vendas!$C$2:$C$3001=$B53)) | D53: =SUMPRODUCT((Vendas!$AK$2:$AK$3001="Validado")*(Vendas!$B$2:$B$3001=$A53)*(Vendas!$C$2:$C$3001=$B53)*ISNUMBER(Vendas!$U$2:$U$3001)) | E53: {=IF(D53<AMOSTRA_MIN,"n<mín",MEDIAN(IF((Vendas!$AK$2:$AK$3001="Validado")*(Vendas!$B$2:$B$3001=$A53)*(Vendas!$C$2:$C$3001=$B53)*ISNUMBER(Vendas!$U$2:$U$3001),Vendas!$U$2:$U$3001)))} | F53: =IF(D53=0,"-",SUMPRODUCT((Vendas!$AK$2:$AK$3001="Validado")*(Vendas!$B$2:$B$3001=$A53)*(Vendas!$C$2:$C$3001=$B53)*ISNUMBER(Vendas!$U$2:$U$3001)*(Vendas!$U$2:$U$3001<1))/D53) | G53: {=IF(D53<AMOSTRA_MIN,"n<mín",100*AVERAGE(IF((Vendas!$AK$2:$AK$3001="Validado")*(Vendas!$B$2:$B$3001=$A53)*(Vendas!$C$2:$C$3001=$B53)*ISNUMBER(Vendas!$U$2:$U$3001),ABS(Vendas!$U$2:$U$3001-E53)))/E53)} | H53: =SUMPRODUCT((Vendas!$AK$2:$AK$3001="Validado")*(Vendas!$B$2:$B$3001=$A53)*(Vendas!$C$2:$C$3001=$B53)*ISNUMBER(Vendas!$V$2:$V$3001)) | I53: {=IF(H53<AMOSTRA_MIN,"n<mín",MEDIAN(IF((Vendas!$AK$2:$AK$3001="Validado")*(Vendas!$B$2:$B$3001=$A53)*(Vendas!$C$2:$C$3001=$B53)*ISNUMBER(Vendas!$V$2:$V$3001),Vendas!$V$2:$V$3001)))} | J53: =IF(H53=0,"-",SUMPRODUCT((Vendas!$AK$2:$AK$3001="Validado")*(Vendas!$B$2:$B$3001=$A53)*(Vendas!$C$2:$C$3001=$B53)*ISNUMBER(Vendas!$V$2:$V$3001)*(Vendas!$V$2:$V$3001<=1))/H53) | K53: =SUMPRODUCT((Vendas!$AK$2:$AK$3001="Validado")*(Vendas!$B$2:$B$3001=$A53)*(Vendas!$C$2:$C$3001=$B53)*(Vendas!$P$2:$P$3001="Financiado")*ISNUMBER(Vendas!$S$2:$S$3001)) | L53: =SUMPRODUCT((Vendas!$AK$2:$AK$3001="Validado")*(Vendas!$B$2:$B$3001=$A53)*(Vendas!$C$2:$C$3001=$B53)*(Vendas!$P$2:$P$3001="À vista")*ISNUMBER(Vendas!$S$2:$S$3001)) | M53: {=IF(K53<AMOSTRA_MIN,"n<mín",MEDIAN(IF((Vendas!$AK$2:$AK$3001="Validado")*(Vendas!$B$2:$B$3001=$A53)*(Vendas!$C$2:$C$3001=$B53)*(Vendas!$P$2:$P$3001="Financiado")*ISNUMBER(Vendas!$S$2:$S$3001),Vendas!$S$2:$S$3001)))} | N53: {=IF(L53<AMOSTRA_MIN,"n<mín",MEDIAN(IF((Vendas!$AK$2:$AK$3001="Validado")*(Vendas!$B$2:$B$3001=$A53)*(Vendas!$C$2:$C$3001=$B53)*(Vendas!$P$2:$P$3001="À vista")*ISNUMBER(Vendas!$S$2:$S$3001),Vendas!$S$2:$S$3001)))} | O53: =IF(OR(K53<AMOSTRA_MIN,L53<AMOSTRA_MIN),"n<mín",N53/M53-1) | P53: =SUMPRODUCT((Vendas!$AK$2:$AK$3001="Validado")*(Vendas!$B$2:$B$3001=$A53)*(Vendas!$C$2:$C$3001=$B53)*ISNUMBER(Vendas!$W$2:$W$3001)) | Q53: {=IF(P53<AMOSTRA_MIN,"n<mín",MEDIAN(IF((Vendas!$AK$2:$AK$3001="Validado")*(Vendas!$B$2:$B$3001=$A53)*(Vendas!$C$2:$C$3001=$B53)*ISNUMBER(Vendas!$W$2:$W$3001),Vendas!$W$2:$W$3001)))} | R53: =IF(P53=0,"-",SUMPRODUCT((Vendas!$AK$2:$AK$3001="Validado")*(Vendas!$B$2:$B$3001=$A53)*(Vendas!$C$2:$C$3001=$B53)*ISNUMBER(Vendas!$W$2:$W$3001)*(Vendas!$W$2:$W$3001<1))/P53) | S53: =SUMPRODUCT((Vendas!$AK$2:$AK$3001="Validado")*(Vendas!$B$2:$B$3001=$A53)*(Vendas!$C$2:$C$3001=$B53)*ISNUMBER(Vendas!$X$2:$X$3001)) | T53: =IF(S53=0,"-",SUMPRODUCT((Vendas!$AK$2:$AK$3001="Validado")*(Vendas!$B$2:$B$3001=$A53)*(Vendas!$C$2:$C$3001=$B53)*ISNUMBER(Vendas!$X$2:$X$3001)*(Vendas!$X$2:$X$3001>=1))/S53)
A54: São Sebastião | B54: Topolândia | C54: =SUMPRODUCT((Vendas!$AK$2:$AK$3001="Validado")*(Vendas!$B$2:$B$3001=$A54)*(Vendas!$C$2:$C$3001=$B54)) | D54: =SUMPRODUCT((Vendas!$AK$2:$AK$3001="Validado")*(Vendas!$B$2:$B$3001=$A54)*(Vendas!$C$2:$C$3001=$B54)*ISNUMBER(Vendas!$U$2:$U$3001)) | E54: {=IF(D54<AMOSTRA_MIN,"n<mín",MEDIAN(IF((Vendas!$AK$2:$AK$3001="Validado")*(Vendas!$B$2:$B$3001=$A54)*(Vendas!$C$2:$C$3001=$B54)*ISNUMBER(Vendas!$U$2:$U$3001),Vendas!$U$2:$U$3001)))} | F54: =IF(D54=0,"-",SUMPRODUCT((Vendas!$AK$2:$AK$3001="Validado")*(Vendas!$B$2:$B$3001=$A54)*(Vendas!$C$2:$C$3001=$B54)*ISNUMBER(Vendas!$U$2:$U$3001)*(Vendas!$U$2:$U$3001<1))/D54) | G54: {=IF(D54<AMOSTRA_MIN,"n<mín",100*AVERAGE(IF((Vendas!$AK$2:$AK$3001="Validado")*(Vendas!$B$2:$B$3001=$A54)*(Vendas!$C$2:$C$3001=$B54)*ISNUMBER(Vendas!$U$2:$U$3001),ABS(Vendas!$U$2:$U$3001-E54)))/E54)} | H54: =SUMPRODUCT((Vendas!$AK$2:$AK$3001="Validado")*(Vendas!$B$2:$B$3001=$A54)*(Vendas!$C$2:$C$3001=$B54)*ISNUMBER(Vendas!$V$2:$V$3001)) | I54: {=IF(H54<AMOSTRA_MIN,"n<mín",MEDIAN(IF((Vendas!$AK$2:$AK$3001="Validado")*(Vendas!$B$2:$B$3001=$A54)*(Vendas!$C$2:$C$3001=$B54)*ISNUMBER(Vendas!$V$2:$V$3001),Vendas!$V$2:$V$3001)))} | J54: =IF(H54=0,"-",SUMPRODUCT((Vendas!$AK$2:$AK$3001="Validado")*(Vendas!$B$2:$B$3001=$A54)*(Vendas!$C$2:$C$3001=$B54)*ISNUMBER(Vendas!$V$2:$V$3001)*(Vendas!$V$2:$V$3001<=1))/H54) | K54: =SUMPRODUCT((Vendas!$AK$2:$AK$3001="Validado")*(Vendas!$B$2:$B$3001=$A54)*(Vendas!$C$2:$C$3001=$B54)*(Vendas!$P$2:$P$3001="Financiado")*ISNUMBER(Vendas!$S$2:$S$3001)) | L54: =SUMPRODUCT((Vendas!$AK$2:$AK$3001="Validado")*(Vendas!$B$2:$B$3001=$A54)*(Vendas!$C$2:$C$3001=$B54)*(Vendas!$P$2:$P$3001="À vista")*ISNUMBER(Vendas!$S$2:$S$3001)) | M54: {=IF(K54<AMOSTRA_MIN,"n<mín",MEDIAN(IF((Vendas!$AK$2:$AK$3001="Validado")*(Vendas!$B$2:$B$3001=$A54)*(Vendas!$C$2:$C$3001=$B54)*(Vendas!$P$2:$P$3001="Financiado")*ISNUMBER(Vendas!$S$2:$S$3001),Vendas!$S$2:$S$3001)))} | N54: {=IF(L54<AMOSTRA_MIN,"n<mín",MEDIAN(IF((Vendas!$AK$2:$AK$3001="Validado")*(Vendas!$B$2:$B$3001=$A54)*(Vendas!$C$2:$C$3001=$B54)*(Vendas!$P$2:$P$3001="À vista")*ISNUMBER(Vendas!$S$2:$S$3001),Vendas!$S$2:$S$3001)))} | O54: =IF(OR(K54<AMOSTRA_MIN,L54<AMOSTRA_MIN),"n<mín",N54/M54-1) | P54: =SUMPRODUCT((Vendas!$AK$2:$AK$3001="Validado")*(Vendas!$B$2:$B$3001=$A54)*(Vendas!$C$2:$C$3001=$B54)*ISNUMBER(Vendas!$W$2:$W$3001)) | Q54: {=IF(P54<AMOSTRA_MIN,"n<mín",MEDIAN(IF((Vendas!$AK$2:$AK$3001="Validado")*(Vendas!$B$2:$B$3001=$A54)*(Vendas!$C$2:$C$3001=$B54)*ISNUMBER(Vendas!$W$2:$W$3001),Vendas!$W$2:$W$3001)))} | R54: =IF(P54=0,"-",SUMPRODUCT((Vendas!$AK$2:$AK$3001="Validado")*(Vendas!$B$2:$B$3001=$A54)*(Vendas!$C$2:$C$3001=$B54)*ISNUMBER(Vendas!$W$2:$W$3001)*(Vendas!$W$2:$W$3001<1))/P54) | S54: =SUMPRODUCT((Vendas!$AK$2:$AK$3001="Validado")*(Vendas!$B$2:$B$3001=$A54)*(Vendas!$C$2:$C$3001=$B54)*ISNUMBER(Vendas!$X$2:$X$3001)) | T54: =IF(S54=0,"-",SUMPRODUCT((Vendas!$AK$2:$AK$3001="Validado")*(Vendas!$B$2:$B$3001=$A54)*(Vendas!$C$2:$C$3001=$B54)*ISNUMBER(Vendas!$X$2:$X$3001)*(Vendas!$X$2:$X$3001>=1))/S54)
... A97: Bertioga | B97: T.I. (Terras Indígenas do Rio Silveiras) | C97: =SUMPRODUCT((Vendas!$AK$2:$AK$3001="Validado")*(Vendas!$B$2:$B$3001=$A97)*(Vendas!$C$2:$C$3001=$B97)) | D97: =SUMPRODUCT((Vendas!$AK$2:$AK$3001="Validado")*(Vendas!$B$2:$B$3001=$A97)*(Vendas!$C$2:$C$3001=$B97)*ISNUMBER(Vendas!$U$2:$U$3001)) | E97: {=IF(D97<AMOSTRA_MIN,"n<mín",MEDIAN(IF((Vendas!$AK$2:$AK$3001="Validado")*(Vendas!$B$2:$B$3001=$A97)*(Vendas!$C$2:$C$3001=$B97)*ISNUMBER(Vendas!$U$2:$U$3001),Vendas!$U$2:$U$3001)))} | F97: =IF(D97=0,"-",SUMPRODUCT((Vendas!$AK$2:$AK$3001="Validado")*(Vendas!$B$2:$B$3001=$A97)*(Vendas!$C$2:$C$3001=$B97)*ISNUMBER(Vendas!$U$2:$U$3001)*(Vendas!$U$2:$U$3001<1))/D97) | G97: {=IF(D97<AMOSTRA_MIN,"n<mín",100*AVERAGE(IF((Vendas!$AK$2:$AK$3001="Validado")*(Vendas!$B$2:$B$3001=$A97)*(Vendas!$C$2:$C$3001=$B97)*ISNUMBER(Vendas!$U$2:$U$3001),ABS(Vendas!$U$2:$U$3001-E97)))/E97)} | H97: =SUMPRODUCT((Vendas!$AK$2:$AK$3001="Validado")*(Vendas!$B$2:$B$3001=$A97)*(Vendas!$C$2:$C$3001=$B97)*ISNUMBER(Vendas!$V$2:$V$3001)) | I97: {=IF(H97<AMOSTRA_MIN,"n<mín",MEDIAN(IF((Vendas!$AK$2:$AK$3001="Validado")*(Vendas!$B$2:$B$3001=$A97)*(Vendas!$C$2:$C$3001=$B97)*ISNUMBER(Vendas!$V$2:$V$3001),Vendas!$V$2:$V$3001)))} | J97: =IF(H97=0,"-",SUMPRODUCT((Vendas!$AK$2:$AK$3001="Validado")*(Vendas!$B$2:$B$3001=$A97)*(Vendas!$C$2:$C$3001=$B97)*ISNUMBER(Vendas!$V$2:$V$3001)*(Vendas!$V$2:$V$3001<=1))/H97) | K97: =SUMPRODUCT((Vendas!$AK$2:$AK$3001="Validado")*(Vendas!$B$2:$B$3001=$A97)*(Vendas!$C$2:$C$3001=$B97)*(Vendas!$P$2:$P$3001="Financiado")*ISNUMBER(Vendas!$S$2:$S$3001)) | L97: =SUMPRODUCT((Vendas!$AK$2:$AK$3001="Validado")*(Vendas!$B$2:$B$3001=$A97)*(Vendas!$C$2:$C$3001=$B97)*(Vendas!$P$2:$P$3001="À vista")*ISNUMBER(Vendas!$S$2:$S$3001)) | M97: {=IF(K97<AMOSTRA_MIN,"n<mín",MEDIAN(IF((Vendas!$AK$2:$AK$3001="Validado")*(Vendas!$B$2:$B$3001=$A97)*(Vendas!$C$2:$C$3001=$B97)*(Vendas!$P$2:$P$3001="Financiado")*ISNUMBER(Vendas!$S$2:$S$3001),Vendas!$S$2:$S$3001)))} | N97: {=IF(L97<AMOSTRA_MIN,"n<mín",MEDIAN(IF((Vendas!$AK$2:$AK$3001="Validado")*(Vendas!$B$2:$B$3001=$A97)*(Vendas!$C$2:$C$3001=$B97)*(Vendas!$P$2:$P$3001="À vista")*ISNUMBER(Vendas!$S$2:$S$3001),Vendas!$S$2:$S$3001)))} | O97: =IF(OR(K97<AMOSTRA_MIN,L97<AMOSTRA_MIN),"n<mín",N97/M97-1) | P97: =SUMPRODUCT((Vendas!$AK$2:$AK$3001="Validado")*(Vendas!$B$2:$B$3001=$A97)*(Vendas!$C$2:$C$3001=$B97)*ISNUMBER(Vendas!$W$2:$W$3001)) | Q97: {=IF(P97<AMOSTRA_MIN,"n<mín",MEDIAN(IF((Vendas!$AK$2:$AK$3001="Validado")*(Vendas!$B$2:$B$3001=$A97)*(Vendas!$C$2:$C$3001=$B97)*ISNUMBER(Vendas!$W$2:$W$3001),Vendas!$W$2:$W$3001)))} | R97: =IF(P97=0,"-",SUMPRODUCT((Vendas!$AK$2:$AK$3001="Validado")*(Vendas!$B$2:$B$3001=$A97)*(Vendas!$C$2:$C$3001=$B97)*ISNUMBER(Vendas!$W$2:$W$3001)*(Vendas!$W$2:$W$3001<1))/P97) | S97: =SUMPRODUCT((Vendas!$AK$2:$AK$3001="Validado")*(Vendas!$B$2:$B$3001=$A97)*(Vendas!$C$2:$C$3001=$B97)*ISNUMBER(Vendas!$X$2:$X$3001)) | T97: =IF(S97=0,"-",SUMPRODUCT((Vendas!$AK$2:$AK$3001="Validado")*(Vendas!$B$2:$B$3001=$A97)*(Vendas!$C$2:$C$3001=$B97)*ISNUMBER(Vendas!$X$2:$X$3001)*(Vendas!$X$2:$X$3001>=1))/S97)

Sheet Padrão
A1: Critério de padrão construtivo
A3: Item | B3: Critério
A4: Regra geral | B4: O padrão só é preenchido a partir de documento ou vistoria. Sem informação, use 'Não informado'. Nunca deduzir pelo preço, bairro ou anúncio.
A5: 1ª opção — Cadastro municipal | B5: Se o ITBI/IPTU trouxer a classe/tipo/padrão construtivo da prefeitura, copie o texto literal em 'Padrão (texto do documento)' e converta para Baixo/Normal/Alto com a tabela de equivalência do importador (arquivo mapa_colunas.json, chave 'mapa_padrao'). Origem: Cadastro municipal.
A6: 2ª opção — Documento | B6: Memorial descritivo, habite-se ou incorporação registrada na matrícula que declare o padrão (a NBR 12721 exige que incorporações informem o padrão: baixo, normal ou alto). Origem: Certidão/memorial/habite-se.
A7: 3ª opção — Vistoria própria | B7: Classificação feita por vistoria do imóvel seguindo os projetos-padrão da ABNT NBR 12721 (Baixo / Normal / Alto), registrando a data e quem vistoriou em Observações. Origem: Vistoria própria.
A8: Baixo | B8: NBR 12721 — padrão de acabamento baixo.
A9: Normal | B9: NBR 12721 — padrão de acabamento normal.
A10: Alto | B10: NBR 12721 — padrão de acabamento alto.
A11: Não informado | B11: O documento não informa e não houve vistoria.

Sheet Fontes
A1: Registro dos documentos recebidos
A3: Código do documento | B3: Tipo | C3: Órgão / Cartório | D3: Nº protocolo / matrícula | E3: Data do pedido | F3: Data da resposta/emissão | G3: Arquivo (caminho) | H3: Custo (R$) | I3: Observações

Sheet Regras
A1: Regras de validação
A3: Regra | B3: Descrição
A4: 1. Valor real | B4: Valor de venda = valor declarado na escritura registrada (ato R de compra e venda na matrícula) ou valor da transação informado pela prefeitura no ITBI. Valor anunciado, avaliação de corretor ou estimativa NUNCA entram.
A5: 2. Natureza | B5: Só compra e venda onerosa. Doação, herança/inventário, permuta, integralização de capital, cessão, dação em pagamento, adjudicação, arrematação/leilão e consolidação de propriedade fiduciária ficam fora (o importador lista como rejeitadas).
A6: 3. Valor e base de cálculo | B6: Valor de venda e base de cálculo do ITBI ficam em colunas separadas. Um não substitui o outro.
A7: 4. Subdeclaração | B7: Quando o valor de venda é menor ou igual ao valor venal do IPTU a coluna Alerta sinaliza. O valor NÃO é corrigido: o alerta só indica que o valor declarado pode estar abaixo do praticado.
A8: 5. Duplicidade | B8: A mesma venda (mesma cidade + matrícula ou inscrição + data) não pode aparecer duas vezes, mesmo que venha da LAI e da certidão. Mantém-se a linha da certidão e cita-se o protocolo LAI em Observações.
A9: 6. Metragem | B9: Sem área no documento, a área fica vazia e o R$/m² também. Nunca estimar.
A10: 7. Bairro | B10: Só bairros da lista oficial (aba Bairros). Nomes populares são convertidos pelo importador via 'apelidos_bairro' do mapa_colunas.json, sempre de forma explícita.
A11: 8. Padrão | B11: Conforme aba Padrão. Sem documento ou vistoria: 'Não informado'.
A12: 9. Foto | B12: Somente foto real do imóvel: tirada no local, link do Street View nas coordenadas do imóvel ou imagem constante de documento. Nunca imagem de anúncio de outro imóvel.
A13: 10. Forma de pagamento | B13: Financiado só com registro de alienação fiduciária/hipoteca na matrícula ou financiamento informado no ITBI. À vista só se o documento disser. Fora disso, 'Não informado'.
A14: 11. Análise ITBI | B14: A aba Análise ITBI e o script analisar_subdeclaracao.py só usam vendas Validado e só mostram mediana/comparação com amostra ≥ mínima (célula B4). Método em docs/analise_subdeclaracao_ITBI.md.
A15: 12. Status | B15: Validado = documento conferido e arquivado (aba Fontes). Pendente = falta conferir. Rejeitado = não atende às regras. O Resumo usa só Validado.

Sheet Referências
A1: Referências e canais
A3: Assunto | B3: Descrição | C3: Link
A4: Bairros de Bertioga | B4: LC 99/2013 de Bertioga, Anexo 1 | C4: https://www.bertioga.sp.gov.br/wp/wp-content/uploads/2015/06/Lei-Complementar-99.2013.pdf
A5: Bairros de São Sebastião | B5: IBGE – malha de bairros do Censo 2022 (SP) | C5: https://geoftp.ibge.gov.br/organizacao_do_territorio/malhas_territoriais/malhas_de_setores_censitarios__divisoes_intramunicipais/censo_2022/bairros/shp/UF/SP_bairros_CD2022.zip
A6: CRI São Sebastião | B6: Oficial de Registro de Imóveis e Anexos de São Sebastião | C6: https://www.risaosebastiao.com.br
A7: CRI Bertioga (desde 01/04/2025) | B7: Oficial de Registro de Imóveis de Bertioga — criado pela Lei Estadual nº 18.075/2024 | C7: https://registrobertioga.com.br/
A8: Lei de criação do CRI Bertioga | B8: Lei Estadual nº 18.075, de 27/12/2024 | C8: https://www.al.sp.gov.br/repositorio/legislacao/lei/2024/lei-18075-27.12.2024.html
A9: Matrículas antigas de Bertioga | B9: 1º Oficial de Registro de Imóveis de Santos (atendia Bertioga até a instalação do CRI local) | C9: https://www.1risantos.com.br/
A10: Certidão online | B10: RI Digital / SAEC (ONR) — antigo registradores.onr.org.br | C10: https://ridigital.org.br/
A11: e-SIC São Sebastião | B11: Sistema de Informação ao Cidadão da Prefeitura | C11: http://www.saosebastiao.sp.gov.br/esic/
A12: Transparência Bertioga | B12: Portal da Transparência (seção e-SIC) | C12: https://transparencia-bertioga.smarapd.com.br/#/esic
A13: Ouvidoria Bertioga | B13: Fala Cidadão | C13: https://sistemas-smarapd.bertioga.sp.gov.br/falacidadao/#!/demanda
A14: Código Tributário de Bertioga | B14: LC 116/2015 (art. 82 – base de cálculo do ITBI) | C14: https://sapl.bertioga.sp.leg.br/media/sapl/public/normajuridica/2015/3823/3823_texto_integral.pdf
... A16: Lei de Acesso à Informação | B16: Lei nº 12.527/2011 | C16: https://www.planalto.gov.br/ccivil_03/_ato2011-2014/2011/lei/l12527.htm
A18: Links verificados em 01/10/2026. O site da Prefeitura de São Sebastião estava fora do ar durante a verificação; confirme o endereço do e-SIC antes de protocolar.

Sheet Galeria
A1: Galeria de fachadas
A2: Gerada por scripts/vincular_fotos.py a partir da pasta fotos/. Não editar à mão.
A4: ID | B4: Cidade | C4: Bairro | D4: Endereço | E4: Arquivo | F4: Miniatura
